Workbook

Sheet Crop Prices (2022-2024) (2)
A1: WHOLESALE PRICES - CONVENTIONAL
A2: Crop | B2: Type | C2: Year | D2: Unit | E2: Unit type | F2: Average Price ($) | G2: Average price ($/lb) | H2: Source | I2: Notes
A3: Green beans (Vancouver) | B3: Conventional Wholesale - CTN 20 LBS | C3: 2022 | D3: 20 | E3: lbs | F3: 40.85 | G3: =F3/D3 -> 2.0425 | H3: Agriculture & Agri-Food Canada | I3: Used green bean prices as proxy for purple beans
A4: Green beans (Vancouver) | B4: Conventional Wholesale - CTN 20 LBS | C4: 2023 | D4: 20 | E4: lbs | F4: 43.25 | G4: =F4/D4 -> 2.1625 | H4: Agriculture & Agri-Food Canada
A5: Green beans (Vancouver) | B5: Conventional Wholesale - CTN 20 LBS | C5: 2024 | D5: 20 | E5: lbs | F5: 44.5 | G5: =F5/D5 -> 2.225 | H5: Agriculture & Agri-Food Canada
A6: Carrots (Vancouver) | B6: Conventional Wholesale - unspecified Ctn 10x5 lbs BC | C6: 2022 | D6: 50 | E6: lbs | F6: 40.375 | G6: =F6/D6 -> 0.8075 | H6: Agriculture & Agri-Food Canada | I6: Used the unspecified prices as the tops were removed. Used 10x5 lbs line - not available for 2024
A7: Carrots (Vancouver) | B7: Conventional Wholesale - unspecified Ctn 10x5 lbs BC | C7: 2023 | D7: 50 | E7: lbs | F7: 46.475 | G7: =F7/D7 -> 0.9295 | H7: Agriculture & Agri-Food Canada | I7: Used the unspecified prices as the tops were removed. Used 10x5 lbs line - doesn't cover all three years
A8: Carrots (Vancouver) | B8: Conventional Wholesale - unspecified Bag 24x2 lbs BC | C8: 2024 | D8: 48 | E8: lbs | F8: 66.25 | G8: =F8/D8 -> 1.3802083 | H8: Agriculture & Agri-Food Canada | I8: Used the unspecified prices as the tops were removed. Used 24 x 2 lbs bag line - not available for 2022
A9: Kale (Vancouver) | B9: Conventional Wholesale - 24 CT | C9: 2022 | D9: 20 | E9: lbs | F9: 26.85 | G9: =F9/D9 -> 1.3425 | H9: Agriculture & Agri-Food Canada | I9: Used conventional green kale prices (no Red Russian). Assumed that 24CT = 20# (based on Organic BC reporting)
A10: Kale (Vancouver) | B10: Conventional Wholesale - 24 CT | C10: 2023 | D10: 20 | E10: lbs | F10: 30.15 | G10: =F10/D10 -> 1.5075 | H10: Agriculture & Agri-Food Canada
A11: Kale (Vancouver) | B11: Conventional Wholesale - 24 CT | C11: 2024 | D11: 20 | E11: lbs | F11: 28.5 | G11: =F11/D11 -> 1.425 | H11: Agriculture & Agri-Food Canada
A13: WHOLESALE PRICES - ORGANIC
A14: Organic Crops | B14: Type | C14: Year | D14: Unit | E14: Unit type | F14: Average Price ($) | G14: Average price ($/lb)
A15: Green beans (BC) | B15: Organic Wholesale - green bulk 20# BC | C15: 2022 | D15: 20 | E15: lbs | F15: 65.4 | G15: =F15/D15 -> 3.27 | H15: Organic BC - SEP 2022 | I15: Used September data as this was when most of the crops were harvested. Used green instead of purple beans.
A16: Green beans (BC) | B16: Organic Wholesale - green bulk 20# BC | C16: 2023 | D16: 20 | E16: lbs | F16: 71.5 | G16: =F16/D16 -> 3.575 | H16: Organic BC - AUG 2023 | I16: Used August data - no September available. Used green instead of purple beans.
A17: Green beans (BC) | B17: Organic Wholesale - green bulk 20# BC | C17: 2024 | D17: 20 | E17: lbs | F17: 59.8 | G17: =F17/D17 -> 2.99 | H17: Organic BC - SEP 2024 | I17: Used September data as this was when most of the crops were harvested. Used green instead of purple beans.
A18: Carrots (BC) | B18: Organic Wholesale - table 25# BC | C18: 2022 | D18: 25 | E18: lbs | F18: 52.1 | G18: =F18/D18 -> 2.084 | H18: Organic BC - SEP 2022 | I18: Used September data as this was when most of the crops were harvested. Looked at table carrots.
A19: Carrots (BC) | B19: Organic Wholesale - table 25# BC | C19: 2023 | D19: 25 | E19: lbs | F19: 58.8 | G19: =F19/D19 -> 2.352 | H19: Organic BC - AUG 2023 | I19: Used August data - no September available. Looked at table carrots.
A20: Carrots (BC) | B20: Organic Wholesale - table 25# CA | C20: 2024 | D20: 25 | E20: lbs | F20: 58.1 | G20: =F20/D20 -> 2.324 | H20: Organic BC - SEP 2024 | I20: Used September data as this was when most of the crops were harvested. Looked at table carrots - no BC.
A21: Kale (BC) | B21: Organic Wholesale - green curly 24CT BC | C21: 2022 | D21: 20 | E21: lbs | F21: 64.2 | G21: =F21/D21 -> 3.21 | H21: Organic BC - SEP 2022 | I21: Used September data for green curly kale (no red Russian).
A22: Kale (BC) | B22: Organic Wholesale - green curly 24CT BC | C22: 2023 | D22: 20 | E22: lbs | F22: 68.4 | G22: =F22/D22 -> 3.42 | H22: Organic BC - AUG 2023 | I22: Used August data for green curly kale (no red Russian).
A23: Kale (BC) | B23: Organic Wholesale - green curly 24CT BC | C23: 2024 | D23: 20 | E23: lbs | F23: 57.2 | G23: =F23/D23 -> 2.86 | H23: Organic BC - SEP 2024 | I23: Used September data for green curly kale (no red Russian).
A25: DIRECT MARKETING PRICES - CONVENTIONAL
A26: Crop | B26: Type | C26: Year | D26: Unit | E26: Unit type | F26: Average Price ($) | G26: Average price ($/lb) | H26: Source | I26: Notes
A27: Green beans | B27: Conventional Direct Marketing | C27: 2022 | D27: 1 | E27: lbs | F27: =(F3*1.7)/20 -> 3.47225 | G27: =F27/D27 -> 3.47225 | H27: Conventional wholesale numbers * 1.7 | I27: I multiplied the wholesale average price by 1.7 and divided by the unit number to get this price.
A28: Green beans | B28: Conventional Direct Marketing | C28: 2023 | D28: 1 | E28: lbs | F28: =(F4*1.7)/20 -> 3.67625 | G28: =F28/D28 -> 3.67625 | H28: Conventional wholesale numbers * 1.7
A29: Green beans | B29: Conventional Direct Marketing | C29: 2024 | D29: 1 | E29: lbs | F29: =(F5*1.7)/20 -> 3.7825 | G29: =F29/D29 -> 3.7825 | H29: Conventional wholesale numbers * 1.7
A30: Carrots | B30: Conventional Direct Marketing | C30: 2022 | D30: 1 | E30: lbs | F30: =(F6*1.7)/20 -> 3.431875 | G30: =F30/D30 -> 3.431875 | H30: Conventional wholesale numbers * 1.7
A31: Carrots | B31: Conventional Direct Marketing | C31: 2023 | D31: 1 | E31: lbs | F31: =(F7*1.7)/20 -> 3.950375 | G31: =F31/D31 -> 3.950375 | H31: Conventional wholesale numbers * 1.7
A32: Carrots | B32: Conventional Direct Marketing | C32: 2024 | D32: 1 | E32: lbs | F32: =(F8*1.7)/20 -> 5.63125 | G32: =F32/D32 -> 5.63125 | H32: Conventional wholesale numbers * 1.7
A33: Kale | B33: Conventional Direct Marketing | C33: 2022 | D33: 1 | E33: lbs | F33: =(F9*1.7)/20 -> 2.28225 | G33: =F33/D33 -> 2.28225 | H33: Conventional wholesale numbers * 1.7
A34: Kale | B34: Conventional Direct Marketing | C34: 2023 | D34: 1 | E34: lbs | F34: =(F10*1.7)/20 -> 2.56275 | G34: =F34/D34 -> 2.56275 | H34: Conventional wholesale numbers * 1.7
A35: Kale | B35: Conventional Direct Marketing | C35: 2024 | D35: 1 | E35: lbs | F35: =(F11*1.7)/20 -> 2.4225 | G35: =F35/D35 -> 2.4225 | H35: Conventional wholesale numbers * 1.7
A37: DIRECT MARKETING PRICES - ORGANIC
A38: Organic Crop | B38: Type | C38: Year | D38: Unit | E38: Unit type | F38: Average Price ($) | G38: Average price ($/lb) | H38: Source | I38: Notes
A39: Green beans | B39: Organic Direct Marketing | C39: 2022 | D39: 1 | E39: lbs | F39: =(F15*1.8)/D15 -> 5.886 | G39: =F39/D39 -> 5.886 | H39: Organic wholesale numbers * 1.8 | I39: I multiplied the wholesale average price by 1.8 and divided by the unit number to get this price.
A40: Green beans | B40: Organic Direct Marketing | C40: 2023 | D40: 1 | E40: lbs | F40: =(F16*1.8)/D16 -> 6.435 | G40: =F40/D40 -> 6.435 | H40: Organic wholesale numbers * 1.8
A41: Green beans | B41: Organic Direct Marketing | C41: 2024 | D41: 1 | E41: lbs | F41: =(F17*1.8)/D17 -> 5.382 | G41: =F41/D41 -> 5.382 | H41: Organic wholesale numbers * 1.8
A42: Carrots | B42: Organic Direct Marketing | C42: 2022 | D42: 1 | E42: lbs | F42: =(F18*1.8)/D18 -> 3.7512 | G42: =F42/D42 -> 3.7512 | H42: Organic wholesale numbers * 1.8
A43: Carrots | B43: Organic Direct Marketing | C43: 2023 | D43: 1 | E43: lbs | F43: =(F19*1.8)/D19 -> 4.2336 | G43: =F43/D43 -> 4.2336 | H43: Organic wholesale numbers * 1.8
A44: Carrots | B44: Organic Direct Marketing | C44: 2024 | D44: 1 | E44: lbs | F44: =(F20*1.8)/D20 -> 4.1832 | G44: =F44/D44 -> 4.1832 | H44: Organic wholesale numbers * 1.8
A45: Kale | B45: Organic Direct Marketing | C45: 2022 | D45: 1 | E45: lbs | F45: =(F21*1.8)/D21 -> 5.778 | G45: =F45/D45 -> 5.778 | H45: Organic wholesale numbers * 1.8
A46: Kale | B46: Organic Direct Marketing | C46: 2023 | D46: 1 | E46: lbs | F46: =(F22*1.8)/D22 -> 6.156 | G46: =F46/D46 -> 6.156 | H46: Organic wholesale numbers * 1.8
A47: Kale | B47: Organic Direct Marketing | C47: 2024 | D47: 1 | E47: lbs | F47: =(F23*1.8)/D23 -> 5.148 | G47: =F47/D47 -> 5.148 | H47: Organic wholesale numbers * 1.8

Sheet Financial Data (R)
A1: Number | B1: Year | C1: Treatment | D1: Replicate | E1: Inorganic Fertilizer | F1: Tillage | G1: Cover crops | H1: Compost | I1: Grazing | J1: Bean Harvest (g) | K1: Carrot Gr. 1 Harvest (g) | L1: Kale Harvest (g) | M1: Total Harvest (g) | N1: Total Revenue - Wholesale ($) | O1: Total Revenue - Direct Marketing ($) | P1: Total Revenue - Wholesale 33% Sort Outs ($) | Q1: Total Revenue - Direct Marketing 20% Unsold ($) | R1: Total Annual Variable Cost - Wholesale ($) | S1: Total Annual Variable Cost - Direct Marketing ($) | T1: Total Annual Labour Cost - Wholesale ($) | U1: Labour Cost - Land Preparation ($) | V1: Labour Cost - Planting ($) | W1: Labour Cost - Weeding ($) | X1: Labour Cost - Bean Harvest ($) | Y1: Labour Cost - Carrot Harvest ($) | Z1: Labour Cost - Kale Harvest ($) | AA1: Labour Cost - Livestock Management ($) | AB1: Total Annual Labour Cost - Direct Marketing ($) | AC1: Total Annual Input Cost ($) | AD1: Net Returns Over Variable Cost - Wholesale ($) | AE1: Net Returns Over Variable Cost - Direct Marketing ($) | AF1: Net Returns Over Variable Cost - Wholesale 33% Sort Outs ($) | AG1: Net Returns Over Variable Cost - Direct Marketing 20% Unsold ($)
A2: 1 | B2: 2022 | C2: 1 | D2: 1 | E2: Yes | F2: Yes | G2: No | H2: No | I2: No | J2: 3247.3 | K2: 1689.2 | L2: 30.2 | M2: =SUM(J2:L2) -> 4966.7 | N2: {=TRANSPOSE('Cost-Benefit Analysis 2022'!B10:U10)} -> 17.718955 | O2: {=TRANSPOSE('Cost-Benefit Analysis 2022'!B11:U11)} -> 30.122223 | P2: {=TRANSPOSE('Cost-Benefit Analysis 2022'!B12:U12)} -> 11.812637 | Q2: {=TRANSPOSE('Cost-Benefit Analysis 2022'!B13:U13)} -> 24.097779 | R2: {=TRANSPOSE('Cost-Benefit Analysis 2022'!B43:U43)} -> 33.915989 | S2: {=TRANSPOSE('Cost-Benefit Analysis 2022'!B44:U44)} -> 40.029028 | T2: {=TRANSPOSE('Cost-Benefit Analysis 2022'!B41:U41)} -> 25.561667 | U2: {=TRANSPOSE('Cost-Benefit Analysis 2022'!B18:U18)} -> 7.1077083 | V2: {=TRANSPOSE('Cost-Benefit Analysis 2022'!B26:U26)} -> 0 | W2: {=TRANSPOSE('Cost-Benefit Analysis 2022'!B28:U28)} -> 11.998333 | X2: {=TRANSPOSE('Cost-Benefit Analysis 2022'!B30:U30)} -> 4.9558333 | Y2: {=TRANSPOSE('Cost-Benefit Analysis 2022'!B31:U31)} -> 1.0433333 | Z2: {=TRANSPOSE('Cost-Benefit Analysis 2022'!B32:U32)} -> 0.45645833 | AA2: {=TRANSPOSE('Cost-Benefit Analysis 2022'!B34:U34)} -> 0 | AB2: {=TRANSPOSE('Cost-Benefit Analysis 2022'!B42:U42)} -> 25.561667 | AC2: {=TRANSPOSE('Cost-Benefit Analysis 2022'!B40:U40)} -> 1.67875 | AD2: {=TRANSPOSE('Cost-Benefit Analysis 2022'!B47:U47)} -> -16.197034 | AE2: {=TRANSPOSE('Cost-Benefit Analysis 2022'!B48:U48)} -> -9.9068048 | AF2: {=TRANSPOSE('Cost-Benefit Analysis 2022'!B49:U49)} -> -22.103352 | AG2: {=TRANSPOSE('Cost-Benefit Analysis 2022'!B50:U50)} -> -15.931249
A3: 2 | B3: 2022 | C3: 1 | D3: 2 | E3: Yes | F3: Yes | G3: No | H3: No | I3: No | J3: 3715.1 | K3: 4814.5 | L3: 49.8 | M3: =SUM(J3:L3) -> 8579.4 | N3: 25.447203 | O3: 43.260245 | P3: 16.964802 | Q3: 34.608196 | R3: 37.999926 | S3: 46.779211 | T3: 27.713542 | U3: 7.1077083 | V3: 0 | W3: 10.1725 | X3: 5.4775 | Y3: 4.4341667 | Z3: 0.52166667 | AA3: 0 | AB3: 27.713542 | AC3: 1.67875 | AD3: -12.552723 | AE3: -3.518966 | AF3: -21.035124 | AG3: -12.171015
A4: 3 | B4: 2022 | C4: 1 | D4: 3 | E4: Yes | F4: Yes | G4: No | H4: No | I4: No | J4: 3278.9 | K4: 1862.1 | L4: 48.5 | M4: =SUM(J4:L4) -> 5189.5 | N4: 18.223213 | O4: 30.979462 | P4: 12.148808 | Q4: 24.783569 | R4: 37.106845 | S4: 43.393853 | T4: 28.626458 | U4: 7.1077083 | V4: 0 | W4: 13.041667 | X4: 4.695 | Y4: 3.3908333 | Z4: 0.39125 | AA4: 0 | AB4: 28.626458 | AC4: 1.67875 | AD4: -18.883632 | AE4: -12.414392 | AF4: -24.958036 | AG4: -18.610284
A5: 4 | B5: 2022 | C5: 1 | D5: 4 | E5: Yes | F5: Yes | G5: No | H5: No | I5: No | J5: 3817.4 | K5: 4125.3 | L5: 56.7 | M5: =SUM(J5:L5) -> 7999.4 | N5: 24.701339 | O5: 41.992277 | P5: 16.467559 | Q5: 33.593821 | R5: 45.312418 | S5: 53.83438 | T5: 35.2125 | U5: 7.1077083 | V5: 0 | W5: 18.519167 | X5: 5.4775 | Y5: 3.6516667 | Z5: 0.45645833 | AA5: 0 | AB5: 35.2125 | AC5: 1.67875 | AD5: -20.611079 | AE5: -11.842103 | AF5: -28.844859 | AG5: -20.240559
A6: 5 | B6: 2022 | C6: 2 | D6: 1 | E6: Yes | F6: Yes | G6: Yes | H6: No | I6: No | J6: 2610.8 | K6: 3185.6 | L6: 62.5 | M6: =SUM(J6:L6) -> 5858.9 | N6: 17.612371 | O6: 29.941031 | P6: 11.741581 | Q6: 23.952825 | R6: 37.361218 | S6: 43.437486 | T6: 26.148542 | U6: 7.1077083 | V6: 0.39125 | W6: 11.998333 | X6: 3.9125 | Y6: 2.3475 | Z6: 0.39125 | AA6: 0 | AB6: 26.148542 | AC6: 4.56375 | AD6: -19.748847 | AE6: -13.496455 | AF6: -25.619637 | AG6: -19.484661
A7: 6 | B7: 2022 | C7: 2 | D7: 2 | E7: Yes | F7: Yes | G7: Yes | H7: No | I7: No | J7: 2854.6 | K7: 2558.5 | L7: 25.5 | M7: =SUM(J7:L7) -> 5438.6 | N7: 17.484295 | O7: 29.723302 | P7: 11.656197 | Q7: 23.778642 | R7: 43.915241 | S7: 49.947322 | T7: 32.734583 | U7: 7.1077083 | V7: 0.39125 | W7: 18.258333 | X7: 4.4341667 | Y7: 2.0866667 | Z7: 0.45645833 | AA7: 0 | AB7: 32.734583 | AC7: 4.56375 | AD7: -26.430945 | AE7: -20.22402 | AF7: -32.259044 | AG7: -26.168681
A8: 7 | B8: 2022 | C8: 2 | D8: 3 | E8: Yes | F8: Yes | G8: Yes | H8: No | I8: No | J8: 2594.8 | K8: 4424.3 | L8: 54.2 | M8: =SUM(J8:L8) -> 7073.3 | N8: 19.720933 | O8: 33.525586 | P8: 13.147289 | Q8: 26.820469 | R8: 43.30065 | S8: 50.104372 | T8: 31.560833 | U8: 7.1077083 | V8: 0.39125 | W8: 16.954167 | X8: 4.1733333 | Y8: 2.6083333 | Z8: 0.32604167 | AA8: 0 | AB8: 31.560833 | AC8: 4.56375 | AD8: -23.579717 | AE8: -16.578786 | AF8: -30.153361 | AG8: -23.283903
A9: 8 | B9: 2022 | C9: 2 | D9: 4 | E9: Yes | F9: Yes | G9: Yes | H9: No | I9: No | J9: 3891.4 | K9: 2473.9 | L9: 30.4 | M9: =SUM(J9:L9) -> 6395.7 | N9: 22.01684 | O9: 37.428628 | P9: 14.677894 | Q9: 29.942903 | R9: 40.092543 | S9: 47.688353 | T9: 27.77875 | U9: 7.1077083 | V9: 0.39125 | W9: 11.7375 | X9: 6.26 | Y9: 1.8258333 | Z9: 0.45645833 | AA9: 0 | AB9: 27.77875 | AC9: 4.56375 | AD9: -18.075703 | AE9: -10.259725 | AF9: -25.41465 | AG9: -17.745451
A10: 9 | B10: 2022 | C10: 3 | D10: 1 | E10: No | F10: Yes | G10: Yes | H10: Yes | I10: No | J10: 2536.2 | K10: 1919.2 | L10: 42.1 | M10: =SUM(J10:L10) -> 4497.5 | N10: 27.399332 | O10: 49.318797 | P10: 18.266221 | Q10: 39.455038 | R10: 64.443583 | S10: 74.855329 | T10: 32.212917 | U10: 8.411875 | V10: 0.39125 | W10: 17.736667 | X10: 3.9125 | Y10: 1.3041667 | Z10: 0.45645833 | AA10: 0 | AB10: 32.212917 | AC10: 23.135 | AD10: -37.044251 | AE10: -25.536532 | AF10: -46.177362 | AG10: -35.400291
A11: 10 | B11: 2022 | C11: 3 | D11: 2 | E11: No | F11: Yes | G11: Yes | H11: Yes | I11: No | J11: 2176 | K11: 2085.2 | L11: 38.2 | M11: =SUM(J11:L11) -> 4299.4 | N11: 25.537684 | O11: 45.967832 | P11: 17.025123 | Q11: 36.774266 | R11: 66.912546 | S11: 76.616866 | T11: 35.147292 | U11: 8.411875 | V11: 0.39125 | W11: 21.1275 | X11: 3.3908333 | Y11: 1.3041667 | Z11: 0.52166667 | AA11: 0 | AB11: 35.147292 | AC11: 23.135 | AD11: -41.374862 | AE11: -30.649034 | AF11: -49.887423 | AG11: -39.842601
A12: 11 | B12: 2022 | C12: 3 | D12: 3 | E12: No | F12: Yes | G12: Yes | H12: Yes | I12: No | J12: 4021.8 | K12: 3142.1 | L12: 58.1 | M12: =SUM(J12:L12) -> 7222 | N12: 43.840957 | O12: 78.913722 | P12: 29.227304 | Q12: 63.130977 | R12: 63.141697 | S12: 79.801261 | T12: 26.800625 | U12: 8.411875 | V12: 0.39125 | W12: 9.39 | X12: 6.26 | Y12: 1.8258333 | Z12: 0.52166667 | AA12: 0 | AB12: 26.800625 | AC12: 23.135 | AD12: -19.300741 | AE12: -0.88753913 | AF12: -33.914393 | AG12: -16.670284
A13: 12 | B13: 2022 | C13: 3 | D13: 4 | E13: No | F13: Yes | G13: Yes | H13: Yes | I13: No | J13: 3052.1 | K13: 1884.5 | L13: 58.2 | M13: =SUM(J13:L13) -> 4994.8 | N13: 31.073025 | O13: 55.931445 | P13: 20.71535 | Q13: 44.745156 | R13: 67.18784 | S13: 78.995589 | T13: 34.03875 | U13: 8.411875 | V13: 0.39125 | W13: 19.5625 | X13: 4.1733333 | Y13: 1.0433333 | Z13: 0.45645833 | AA13: 0 | AB13: 34.03875 | AC13: 23.135 | AD13: -36.114815 | AE13: -23.064144 | AF13: -46.47249 | AG13: -34.250433
A14: 13 | B14: 2022 | C14: 4 | D14: 1 | E14: No | F14: Yes | G14: Yes | H14: Yes | I14: Yes | J14: 3237.7 | K14: 2724.2 | L14: 47.8 | M14: =SUM(J14:L14) -> 6009.7 | N14: 36.195384 | O14: 65.15169 | P14: 24.130256 | Q14: 52.121352 | R14: 60.839054 | S14: 74.5933 | T14: 26.409375 | U14: 8.411875 | V14: 0.39125 | W14: 10.955 | X14: 4.9558333 | Y14: 1.3041667 | Z14: 0.39125 | AA14: 0 | AB14: 26.409375 | AC14: 23.135 | AD14: -24.643671 | AE14: -9.4416096 | AF14: -36.708799 | AG14: -22.471948
... A21: 20 | B21: 2022 | C21: 5 | D21: 4 | E21: No | F21: No | G21: Yes | H21: Yes | I21: Yes | J21: 3500.6 | K21: 3023.3 | L21: 73.4 | M21: =SUM(J21:L21) -> 6597.3 | N21: 39.646022 | O21: 71.36284 | P21: 26.430682 | Q21: 57.090272 | R21: 60.267131 | S21: 75.332619 | T21: 24.974792 | U21: 8.411875 | V21: 0.39125 | W21: 8.8683333 | X21: 5.2166667 | Y21: 1.3041667 | Z21: 0.7825 | AA21: 0 | AB21: 24.974792 | AC21: 23.135 | AD21: -20.621108 | AE21: -3.969779 | AF21: -33.836449 | AG21: -18.242347
A22: 21 | B22: 2023 | C22: 1 | D22: 1 | E22: Yes | F22: Yes | G22: No | H22: No | I22: No | J22: 4597.3 | K22: 3881.2 | L22: 537.8 | M22: =SUM(J22:L22) -> 9016.3 | N22: {=TRANSPOSE('Cost-Benefit Analysis 2023'!B10:U10)} -> 31.658315 | O22: {=TRANSPOSE('Cost-Benefit Analysis 2023'!B11:U11)} -> 53.819136 | P22: {=TRANSPOSE('Cost-Benefit Analysis 2023'!B12:U12)} -> 21.105543 | Q22: {=TRANSPOSE('Cost-Benefit Analysis 2023'!B13:U13)} -> 43.055308 | R22: {=TRANSPOSE('Cost-Benefit Analysis 2023'!B43:U43)} -> 76.924969 | S22: {=TRANSPOSE('Cost-Benefit Analysis 2023'!B44:U44)} -> 87.847088 | T22: {=TRANSPOSE('Cost-Benefit Analysis 2023'!B41:U41)} -> 60.465755 | U22: {=TRANSPOSE('Cost-Benefit Analysis 2023'!B18:U18)} -> 5.1907552 | V22: {=TRANSPOSE('Cost-Benefit Analysis 2023'!B26:U26)} -> 0 | W22: {=TRANSPOSE('Cost-Benefit Analysis 2023'!B28:U28)} -> 34.477083 | X22: {=TRANSPOSE('Cost-Benefit Analysis 2023'!B30:U30)} -> 13.4 | Y22: {=TRANSPOSE('Cost-Benefit Analysis 2023'!B31:U31)} -> 4.3270833 | Z22: {=TRANSPOSE('Cost-Benefit Analysis 2023'!B32:U32)} -> 3.0708333 | AA22: {=TRANSPOSE('Cost-Benefit Analysis 2023'!B34:U34)} -> 0 | AB22: {=TRANSPOSE('Cost-Benefit Analysis 2023'!B42:U42)} -> 60.465755 | AC22: {=TRANSPOSE('Cost-Benefit Analysis 2023'!B40:U40)} -> 1.67875 | AD22: {=TRANSPOSE('Cost-Benefit Analysis 2023'!B47:U47)} -> -45.266654 | AE22: {=TRANSPOSE('Cost-Benefit Analysis 2023'!B48:U48)} -> -34.027953 | AF22: {=TRANSPOSE('Cost-Benefit Analysis 2023'!B49:U49)} -> -55.819426 | AG22: {=TRANSPOSE('Cost-Benefit Analysis 2023'!B50:U50)} -> -44.79178
A23: 22 | B23: 2023 | C23: 1 | D23: 2 | E23: Yes | F23: Yes | G23: No | H23: No | I23: No | J23: 5548.2 | K23: 6626.2 | L23: 1769.5 | M23: =SUM(J23:L23) -> 13943.9 | N23: 45.910289 | O23: 78.047491 | P23: 30.606859 | Q23: 62.437993 | R23: 75.788657 | S23: 91.627707 | T23: 55.76645 | U23: 5.1907552 | V23: 0 | W23: 26.218403 | X23: 12.283333 | Y23: 6.8395833 | Z23: 5.234375 | AA23: 0 | AB23: 55.76645 | AC23: 1.67875 | AD23: -29.878369 | AE23: -13.580216 | AF23: -45.181798 | AG23: -29.189714
A24: 23 | B24: 2023 | C24: 1 | D24: 3 | E24: Yes | F24: Yes | G24: No | H24: No | I24: No | J24: 7776.3 | K24: 7038.2 | L24: 856.2 | M24: =SUM(J24:L24) -> 15670.7 | N24: 54.341693 | O24: 92.380877 | P24: 36.227795 | Q24: 73.904702 | R24: 73.313522 | S24: 92.061406 | T24: 51.183464 | U24: 5.1907552 | V24: 0 | W24: 22.19375 | X24: 15.005208 | Y24: 4.6760417 | Z24: 4.1177083 | AA24: 0 | AB24: 51.183464 | AC24: 1.67875 | AD24: -18.971829 | AE24: 0.3194714 | AF24: -37.085727 | AG24: -18.156704
A25: 24 | B25: 2023 | C25: 1 | D25: 4 | E25: Yes | F25: Yes | G25: No | H25: No | I25: No | J25: 4944.4 | K25: 5829.2 | L25: 959.2 | M25: =SUM(J25:L25) -> 11732.8 | N25: 38.705458 | O25: 65.799279 | P25: 25.803639 | Q25: 52.639423 | R25: 75.008734 | S25: 88.362117 | T25: 56.787734 | U25: 5.1907552 | V25: 0 | W25: 30.170938 | X25: 11.096875 | Y25: 6.0020833 | Z25: 4.3270833 | AA25: 0 | AB25: 56.787734 | AC25: 1.67875 | AD25: -36.303276 | AE25: -22.562839 | AF25: -49.205096 | AG25: -35.722694
A26: 25 | B26: 2023 | C26: 2 | D26: 1 | E26: Yes | F26: Yes | G26: Yes | H26: No | I26: No | J26: 4342.5 | K26: 6182.4 | L26: 1879.1 | M26: =SUM(J26:L26) -> 12404 | N26: 39.616937 | O26: 67.348793 | P26: 26.411291 | Q26: 53.879034 | R26: 68.975406 | S26: 82.643249 | T26: 47.641536 | U26: 5.1907552 | V26: 0.41875 | W26: 21.792448 | X26: 9.4916667 | Y26: 5.5833333 | Z26: 5.1645833 | AA26: 0 | AB26: 47.641536 | AC26: 4.56375 | AD26: -29.358469 | AE26: -15.294457 | AF26: -42.564115 | AG26: -28.764215
A27: 26 | B27: 2023 | C27: 2 | D27: 2 | E27: Yes | F27: Yes | G27: Yes | H27: No | I27: No | J27: 7257.3 | K27: 4988.9 | L27: 751.2 | M27: =SUM(J27:L27) -> 12997.4 | N27: 47.318979 | O27: 80.442264 | P27: 31.545986 | Q27: 64.353811 | R27: 77.939406 | S27: 94.264454 | T27: 54.680026 | U27: 5.1907552 | V27: 0.41875 | W27: 24.783021 | X27: 15.772917 | Y27: 3.978125 | Z27: 4.5364583 | AA27: 0 | AB27: 54.680026 | AC27: 4.56375 | AD27: -30.620427 | AE27: -13.82219 | AF27: -46.39342 | AG27: -29.910643
A28: 27 | B28: 2023 | C28: 2 | D28: 3 | E28: Yes | F28: Yes | G28: Yes | H28: No | I28: No | J28: 6263.2 | K28: 4164 | L28: 1908.1 | M28: =SUM(J28:L28) -> 12335.3 | N28: 44.734149 | O28: 76.048054 | P28: 29.822766 | Q28: 60.838443 | R28: 80.21747 | S28: 95.650751 | T28: 57.604297 | U28: 5.1907552 | V28: 0.41875 | W28: 28.684375 | X28: 13.609375 | Y28: 4.3270833 | Z28: 5.3739583 | AA28: 0 | AB28: 57.604297 | AC28: 4.56375 | AD28: -35.48332 | AE28: -19.602697 | AF28: -50.394703 | AG28: -34.812308
A29: 28 | B29: 2023 | C29: 2 | D29: 4 | E29: Yes | F29: Yes | G29: Yes | H29: No | I29: No | J29: 6946.6 | K29: 6127.5 | L29: 1503.2 | M29: =SUM(J29:L29) -> 14577.3 | N29: 50.670182 | O29: 86.139309 | P29: 33.780121 | Q29: 68.911447 | R29: 79.747311 | S29: 97.228524 | T29: 55.65013 | U29: 5.1907552 | V29: 0.41875 | W29: 24.566667 | X29: 14.028125 | Y29: 7.3979167 | Z29: 4.0479167 | AA29: 0 | AB29: 55.65013 | AC29: 4.56375 | AD29: -29.077129 | AE29: -11.089215 | AF29: -45.96719 | AG29: -28.317077
A30: 29 | B30: 2023 | C30: 3 | D30: 1 | E30: No | F30: Yes | G30: Yes | H30: Yes | I30: No | J30: 4710.9 | K30: 5154.3 | L30: 327.3 | M30: =SUM(J30:L30) -> 10192.5 | N30: 66.323309 | O30: 119.38196 | P30: 44.21554 | Q30: 95.505566 | R30: 105.62283 | S30: 130.82569 | T30: 49.79112 | U30: 6.5865885 | V30: 0.41875 | W30: 26.035781 | X30: 10.259375 | Y30: 3.2802083 | Z30: 3.2104167 | AA30: 0 | AB30: 49.79112 | AC30: 32.385 | AD30: -39.299523 | AE30: -11.443733 | AF30: -61.407293 | AG30: -35.320125
A31: 30 | B31: 2023 | C31: 3 | D31: 2 | E31: No | F31: Yes | G31: Yes | H31: Yes | I31: No | J31: 4455.5 | K31: 3988.8 | L31: 1206.7 | M31: =SUM(J31:L31) -> 9651 | N31: 64.897441 | O31: 116.81539 | P31: 43.264961 | Q31: 93.452315 | R31: 103.51808 | S31: 128.17911 | T31: 48.042839 | U31: 6.5865885 | V31: 0.41875 | W31: 21.077083 | X31: 9.9104167 | Y31: 5.5833333 | Z31: 4.4666667 | AA31: 0 | AB31: 48.042839 | AC31: 32.385 | AD31: -38.620643 | AE31: -11.363718 | AF31: -60.253124 | AG31: -34.726797
A32: 31 | B32: 2023 | C32: 3 | D32: 3 | E32: No | F32: Yes | G32: Yes | H32: Yes | I32: No | J32: 6886.8 | K32: 7913 | L32: 1344.7 | M32: =SUM(J32:L32) -> 16144.5 | N32: 105.44833 | O32: 189.807 | P32: 70.29889 | Q32: 151.8456 | R32: 112.12039 | S32: 152.19076 | T32: 46.507422 | U32: 6.5865885 | V32: 0.41875 | W32: 15.703125 | X32: 14.795833 | Y32: 4.6760417 | Z32: 4.3270833 | AA32: 0 | AB32: 46.507422 | AC32: 32.385 | AD32: -6.6720563 | AE32: 37.616244 | AF32: -41.821501 | AG32: -0.34515627
A33: 32 | B33: 2023 | C33: 3 | D33: 4 | E33: No | F33: Yes | G33: Yes | H33: Yes | I33: No | J33: 5338.5 | K33: 6661.4 | L33: 191.2 | M33: =SUM(J33:L33) -> 12191.1 | N33: 78.058311 | O33: 140.50496 | P33: 52.038874 | Q33: 112.40397 | R33: 109.71164 | S33: 139.37379 | T33: 50.946172 | U33: 6.5865885 | V33: 0.41875 | W33: 24.259583 | X33: 12.283333 | Y33: 4.7458333 | Z33: 2.6520833 | AA33: 0 | AB33: 50.946172 | AC33: 32.385 | AD33: -31.653324 | AE33: 1.1311666 | AF33: -57.672761 | AG33: -26.969825
A34: 33 | B34: 2023 | C34: 4 | D34: 1 | E34: No | F34: Yes | G34: Yes | H34: Yes | I34: Yes | J34: 7562.5 | K34: 5642.2 | L34: 982 | M34: =SUM(J34:L34) -> 14186.7 | N34: 96.264476 | O34: 173.27606 | P34: 64.176317 | Q34: 138.62085 | R34: 130.74448 | S34: 167.32498 | T34: 67.427474 | U34: 7.6334635 | V34: 0.41875 | W34: 20.85026 | X34: 19.122917 | Y34: 5.3041667 | Z34: 3.6291667 | AA34: 10.46875 | AB34: 67.427474 | AC34: 32.385 | AD34: -34.480002 | AE34: 5.9510778 | AF34: -66.568161 | AG34: -28.704134
... A41: 40 | B41: 2023 | C41: 5 | D41: 4 | E41: No | F41: No | G41: Yes | H41: Yes | I41: Yes | J41: 7099.5 | K41: 4564.2 | L41: 1006.9 | M41: =SUM(J41:L41) -> 12670.6 | N41: 87.213347 | O41: 156.98403 | P41: 58.142232 | Q41: 125.58722 | R41: 115.95943 | S41: 149.1005 | T41: 60.771094 | U41: 13.522135 | V41: 0.41875 | W41: 11.585417 | X41: 17.727083 | Y41: 2.7916667 | Z41: 4.2572917 | AA41: 10.46875 | AB41: 60.771094 | AC41: 32.385 | AD41: -28.746083 | AE41: 7.8835226 | AF41: -57.817199 | AG41: -23.513282
A42: 41 | B42: 2024 | C42: 1 | D42: 1 | E42: Yes | F42: Yes | G42: No | H42: No | I42: No | J42: 912 | K42: 6487.9 | L42: 521.2 | M42: =SUM(J42:L42) -> 7921.1 | N42: {=TRANSPOSE('Cost-Benefit Analysis 2024'!B10:U10)} -> 15.721093 | O42: {=TRANSPOSE('Cost-Benefit Analysis 2024'!B11:U11)} -> 26.725858 | P42: {=TRANSPOSE('Cost-Benefit Analysis 2024'!B12:U12)} -> 10.480729 | Q42: {=TRANSPOSE('Cost-Benefit Analysis 2024'!B13:U13)} -> 21.380686 | R42: {=TRANSPOSE('Cost-Benefit Analysis 2024'!B43:U43)} -> 104.46637 | S42: {=TRANSPOSE('Cost-Benefit Analysis 2024'!B44:U44)} -> 109.89014 | T42: {=TRANSPOSE('Cost-Benefit Analysis 2024'!B41:U41)} -> 91.522188 | U42: {=TRANSPOSE('Cost-Benefit Analysis 2024'!B18:U18)} -> 5.3921875 | V42: {=TRANSPOSE('Cost-Benefit Analysis 2024'!B26:U26)} -> 0 | W42: {=TRANSPOSE('Cost-Benefit Analysis 2024'!B28:U28)} -> 65.9025 | X42: {=TRANSPOSE('Cost-Benefit Analysis 2024'!B30:U30)} -> 5.51 | Y42: {=TRANSPOSE('Cost-Benefit Analysis 2024'!B31:U31)} -> 7.6125 | Z42: {=TRANSPOSE('Cost-Benefit Analysis 2024'!B32:U32)} -> 7.105 | AA42: {=TRANSPOSE('Cost-Benefit Analysis 2024'!B34:U34)} -> 0 | AB42: {=TRANSPOSE('Cost-Benefit Analysis 2024'!B42:U42)} -> 91.522188 | AC42: {=TRANSPOSE('Cost-Benefit Analysis 2024'!B40:U40)} -> 1.67875 | AD42: {=TRANSPOSE('Cost-Benefit Analysis 2024'!B47:U47)} -> -88.745274 | AE42: {=TRANSPOSE('Cost-Benefit Analysis 2024'!B48:U48)} -> -83.164286 | AF42: {=TRANSPOSE('Cost-Benefit Analysis 2024'!B49:U49)} -> -93.985638 | AG42: {=TRANSPOSE('Cost-Benefit Analysis 2024'!B50:U50)} -> -88.509458
A43: 42 | B43: 2024 | C43: 1 | D43: 2 | E43: Yes | F43: Yes | G43: No | H43: No | I43: No | J43: 2653.8 | K43: 5297.4 | L43: 994.1 | M43: =SUM(J43:L43) -> 8945.3 | N43: 23.98737 | O43: 40.778529 | P43: 15.99158 | Q43: 32.622824 | R43: 91.090436 | S43: 99.366079 | T43: 76.079687 | U43: 5.3921875 | V43: 0 | W43: 44.95 | X43: 9.425 | Y43: 9.135 | Z43: 7.1775 | AA43: 0 | AB43: 76.079687 | AC43: 1.67875 | AD43: -67.103066 | AE43: -58.58755 | AF43: -75.098856 | AG43: -66.743256
A44: 43 | B44: 2024 | C44: 1 | D44: 3 | E44: Yes | F44: Yes | G44: No | H44: No | I44: No | J44: 5381.1 | K44: 6034 | L44: 1966.6 | M44: =SUM(J44:L44) -> 13381.7 | N44: 41.511823 | O44: 70.570099 | P44: 27.674549 | Q44: 56.456079 | R44: 98.08155 | S44: 112.40313 | T44: 78.689687 | U44: 5.3921875 | V44: 0 | W44: 41.8325 | X44: 15.4425 | Y44: 7.83 | Z44: 8.1925 | AA44: 0 | AB44: 78.689687 | AC44: 1.67875 | AD44: -56.569726 | AE44: -41.833029 | AF44: -70.407001 | AG44: -55.947049
A45: 44 | B45: 2024 | C45: 1 | D45: 4 | E45: Yes | F45: Yes | G45: No | H45: No | I45: No | J45: 4159.9 | K45: 4460.7 | L45: 1432.6 | M45: =SUM(J45:L45) -> 10053.2 | N45: 31.513461 | O45: 53.572883 | P45: 21.008974 | Q45: 42.858307 | R45: 106.21046 | S45: 117.0826 | T45: 89.318188 | U45: 5.3921875 | V45: 0 | W45: 55.4625 | X45: 14.471 | Y45: 6.3075 | Z45: 7.685 | AA45: 0 | AB45: 89.318188 | AC45: 1.67875 | AD45: -74.696998 | AE45: -63.50972 | AF45: -85.201485 | AG45: -74.224296
A46: 45 | B46: 2024 | C46: 2 | D46: 1 | E46: Yes | F46: Yes | G46: Yes | H46: No | I46: No | J46: 3708 | K46: 6510 | L46: 1006.7 | M46: =SUM(J46:L46) -> 11224.7 | N46: 30.994247 | O46: 52.690219 | P46: 20.662831 | Q46: 42.152175 | R46: 95.749655 | S46: 106.44267 | T46: 76.587188 | U46: 5.3921875 | V46: 0.435 | W46: 44.2975 | X46: 11.0925 | Y46: 8.0475 | Z46: 7.3225 | AA46: 0 | AB46: 76.587188 | AC46: 4.07875 | AD46: -64.755409 | AE46: -53.752451 | AF46: -75.086824 | AG46: -64.290495
A47: 46 | B47: 2024 | C47: 2 | D47: 2 | E47: Yes | F47: Yes | G47: Yes | H47: No | I47: No | J47: 3844.7 | K47: 4290 | L47: 821.5 | M47: =SUM(J47:L47) -> 8956.2 | N47: 27.794645 | O47: 47.250896 | P47: 18.529763 | Q47: 37.800717 | R47: 86.829755 | S47: 96.418907 | T47: 68.467187 | U47: 5.3921875 | V47: 0.435 | W47: 39.295 | X47: 12.47 | Y47: 4.785 | Z47: 6.09 | AA47: 0 | AB47: 68.467187 | AC47: 4.07875 | AD47: -59.03511 | AE47: -49.168011 | AF47: -68.299992 | AG47: -58.618191
A48: 47 | B48: 2024 | C48: 2 | D48: 3 | E48: Yes | F48: Yes | G48: Yes | H48: No | I48: No | J48: 3178.7 | K48: 6220.2 | L48: 1054.5 | M48: =SUM(J48:L48) -> 10453.4 | N48: 28.118786 | O48: 47.801937 | P48: 18.745857 | Q48: 38.241549 | R48: 94.95829 | S48: 104.65927 | T48: 76.514687 | U48: 5.3921875 | V48: 0.435 | W48: 45.7475 | X48: 11.02 | Y48: 6.96 | Z48: 6.96 | AA48: 0 | AB48: 76.514687 | AC48: 4.07875 | AD48: -66.839504 | AE48: -56.857335 | AF48: -76.212433 | AG48: -66.417722
A49: 48 | B49: 2024 | C49: 2 | D49: 4 | E49: Yes | F49: Yes | G49: Yes | H49: No | I49: No | J49: 6492.1 | K49: 10110.9 | L49: 1051.6 | M49: =SUM(J49:L49) -> 17654.6 | N49: 50.125873 | O49: 85.213984 | P49: 33.417249 | Q49: 68.171187 | R49: 109.52256 | S49: 126.81599 | T49: 85.577188 | U49: 5.3921875 | V49: 0.435 | W49: 45.1675 | X49: 19.575 | Y49: 9.135 | Z49: 5.8725 | AA49: 0 | AB49: 85.577188 | AC49: 4.07875 | AD49: -59.396689 | AE49: -41.602004 | AF49: -76.105313 | AG49: -58.644801
A50: 49 | B50: 2024 | C50: 3 | D50: 1 | E50: No | F50: Yes | G50: Yes | H50: Yes | I50: No | J50: 1802.8 | K50: 5757.4 | L50: 728.3 | M50: =SUM(J50:L50) -> 8288.5 | N50: 45.974115 | O50: 82.753406 | P50: 30.64941 | Q50: 66.202725 | R50: 128.03671 | S50: 145.50687 | T50: 81.058021 | U50: 7.6880208 | V50: 0.435 | W50: 51.475 | X50: 7.395 | Y50: 6.96 | Z50: 7.105 | AA50: 0 | AB50: 81.058021 | AC50: 28.15 | AD50: -82.062591 | AE50: -62.753463 | AF50: -97.387296 | AG50: -79.304144
A51: 50 | B51: 2024 | C51: 3 | D51: 2 | E51: No | F51: Yes | G51: Yes | H51: Yes | I51: No | J51: 2525 | K51: 2891.7 | L51: 1496 | M51: =SUM(J51:L51) -> 6912.7 | N51: 40.892709 | O51: 73.606876 | P51: 27.261806 | Q51: 58.885501 | R51: 110.96135 | S51: 126.50058 | T51: 65.253021 | U51: 7.6880208 | V51: 0.435 | W51: 36.6125 | X51: 9.3525 | Y51: 3.48 | Z51: 7.685 | AA51: 0 | AB51: 65.253021 | AC51: 28.15 | AD51: -70.068645 | AE51: -52.893708 | AF51: -83.699548 | AG51: -67.615083
A52: 51 | B52: 2024 | C52: 3 | D52: 3 | E52: No | F52: Yes | G52: Yes | H52: Yes | I52: No | J52: 5394.5 | K52: 1942.5 | L52: 2180.2 | M52: =SUM(J52:L52) -> 9517.2 | N52: 59.258706 | O52: 106.66567 | P52: 39.505804 | Q52: 85.332537 | R52: 122.36785 | S52: 144.88616 | T52: 72.068021 | U52: 7.6880208 | V52: 0.435 | W52: 37.3375 | X52: 16.24 | Y52: 1.74 | Z52: 8.6275 | AA52: 0 | AB52: 72.068021 | AC52: 28.15 | AD52: -63.109147 | AE52: -38.220491 | AF52: -82.862049 | AG52: -59.553625
A53: 52 | B53: 2024 | C53: 3 | D53: 4 | E53: No | F53: Yes | G53: Yes | H53: Yes | I53: No | J53: 5439.1 | K53: 6867.5 | L53: 2762 | M53: =SUM(J53:L53) -> 15068.6 | N53: 88.454528 | O53: 159.21815 | P53: 58.969685 | Q53: 127.37452 | R53: 150.22781 | S53: 183.84053 | T53: 92.629021 | U53: 7.6880208 | V53: 0.435 | W53: 54.7085 | X53: 15.805 | Y53: 6.3075 | Z53: 7.685 | AA53: 0 | AB53: 92.629021 | AC53: 28.15 | AD53: -61.773281 | AE53: -24.622379 | AF53: -91.258124 | AG53: -56.466009
A54: 53 | B54: 2024 | C54: 4 | D54: 1 | E54: No | F54: Yes | G54: Yes | H54: Yes | I54: Yes | J54: 5200.8 | K54: 2142.5 | L54: 816.8 | M54: =SUM(J54:L54) -> 8160.1 | N54: 50.410041 | O54: 90.738074 | P54: 33.606694 | Q54: 72.590459 | R54: 134.80069 | S54: 153.9565 | T54: 86.713021 | U54: 8.7755208 | V54: 0.435 | W54: 43.935 | X54: 14.21 | Y54: 1.74 | Z54: 6.7425 | AA54: 10.875 | AB54: 86.713021 | AC54: 28.15 | AD54: -84.390646 | AE54: -63.218429 | AF54: -101.19399 | AG54: -81.366044
... A61: 60 | B61: 2024 | C61: 5 | D61: 4 | E61: No | F61: No | G61: Yes | H61: Yes | I61: Yes | J61: 5637.7 | K61: 3866.5 | L61: 603.1 | M61: =SUM(J61:L61) -> 10107.3 | N61: 60.77557 | O61: 109.39603 | P61: 40.517047 | Q61: 87.516821 | R61: 128.9091 | S61: 152.00382 | T61: 84.565208 | U61: 14.892708 | V61: 0.435 | W61: 32.915 | X61: 17.11 | Y61: 2.03 | Z61: 6.3075 | AA61: 10.875 | AB61: 84.565208 | AC61: 28.15 | AD61: -68.133531 | AE61: -42.607791 | AF61: -88.392054 | AG61: -64.486996

Sheet TIP Benchmarks (R)
A1: class | B1: year | C1: expenses | D1: margin
A2: 0-50 | B2: 2018-2022 | C2: 1.3155 | D2: -0.3155
A3: 0-50 | B3: 2023 | C3: 2.3363 | D3: -1.3363
A4: 50-100 | B4: 2018-2022 | C4: 1.0338 | D4: -0.0338
A5: 50-100 | B5: 2023 | C5: 1.5408 | D5: -0.5408
A6: 100-500 | B6: 2018-2022 | C6: 0.8759 | D6: 0.11
A7: 100-500 | B7: 2023 | C7: 0.9264 | D7: 0.0736
A8: 500-1M | B8: 2018-2022 | C8: 0.8516 | D8: 0.1484
A9: 500-1M | B9: 2023 | C9: 0.8751 | D9: 0.125
A10: 1M+ | B10: 2018-2022 | C10: 0.9092 | D10: 0.0748
A11: 1M+ | B11: 2023 | C11: 0.9397 | D11: 0.0603

Sheet Cost-Benefit Analysis 2022
B1: Treatment 1-1 | C1: Treatment 1-2 | D1: Treatment 1-3 | E1: Treatment 1-4 | F1: Treatment 2-1 | G1: Treatment 2-2 | H1: Treatment 2-3 | I1: Treatment 2-4 | J1: Treatment 3-1 | K1: Treatment 3-2 | L1: Treatment 3-3 | M1: Treatment 3-4 | N1: Treatment 4-1 | O1: Treatment 4-2 | P1: Treatment 4-3 | Q1: Treatment 4-4 | R1: Treatment 5-1 | S1: Treatment 5-2 | T1: Treatment 5-3 | U1: Treatment 5-4 | V1: TOTAL
A2: REVENUE
A3: Bean Revenue (2.5 x 1 m) - WHOLESALE | B3: ='Crop Revenue (2022-2024)'!C5 -> 14.622403 | C3: ='Crop Revenue (2022-2024)'!D5 -> 16.728879 | D3: ='Crop Revenue (2022-2024)'!E5 -> 14.764696 | E3: ='Crop Revenue (2022-2024)'!F5 -> 17.18953 | F3: ='Crop Revenue (2022-2024)'!G5 -> 11.75628 | G3: ='Crop Revenue (2022-2024)'!H5 -> 12.854097 | H3: ='Crop Revenue (2022-2024)'!I5 -> 11.684233 | I3: ='Crop Revenue (2022-2024)'!J5 -> 17.522747 | ... U3: ='Crop Revenue (2022-2024)'!V5 -> 25.236231 | V3: =SUM(B3:U3) -> 338.78516
A4: Carrot Revenue (2.5 x 1 m) - WHOLESALE | B4: ='Crop Revenue (2022-2024)'!C17 -> 3.0071692 | C4: ='Crop Revenue (2022-2024)'!D17 -> 8.5709307 | D4: ='Crop Revenue (2022-2024)'!E17 -> 3.3149714 | E4: ='Crop Revenue (2022-2024)'!F17 -> 7.3439942 | F4: ='Crop Revenue (2022-2024)'!G17 -> 5.6711095 | G4: ='Crop Revenue (2022-2024)'!H17 -> 4.5547255 | H4: ='Crop Revenue (2022-2024)'!I17 -> 7.8762838 | I4: ='Crop Revenue (2022-2024)'!J17 -> 4.4041178 | ... U4: ='Crop Revenue (2022-2024)'!V17 -> 13.890351 | V4: =SUM(B4:U4) -> 169.82538
A5: Kale Revenue (2.5 x 1 m) - WHOLESALE | B5: ='Crop Revenue (2022-2024)'!C29 -> 0.089383117 | C5: ='Crop Revenue (2022-2024)'!D29 -> 0.14739335 | D5: ='Crop Revenue (2022-2024)'!E29 -> 0.14354573 | E5: ='Crop Revenue (2022-2024)'!F29 -> 0.16781532 | F5: ='Crop Revenue (2022-2024)'!G29 -> 0.18498162 | G5: ='Crop Revenue (2022-2024)'!H29 -> 0.0754725 | H5: ='Crop Revenue (2022-2024)'!I29 -> 0.16041606 | I5: ='Crop Revenue (2022-2024)'!J29 -> 0.089975058 | ... U5: ='Crop Revenue (2022-2024)'!V29 -> 0.51943995 | V5: =SUM(B5:U5) -> 5.663174
A6: Bean Revenue (2.5 x 1 m) - DIRECT MARKETING | B6: ='Crop Revenue (2022-2024)'!C41 -> 24.858084 | C6: ='Crop Revenue (2022-2024)'!D41 -> 28.439094 | D6: ='Crop Revenue (2022-2024)'!E41 -> 25.099982 | E6: ='Crop Revenue (2022-2024)'!F41 -> 29.2222 | F6: ='Crop Revenue (2022-2024)'!G41 -> 19.985676 | G6: ='Crop Revenue (2022-2024)'!H41 -> 21.851966 | H6: ='Crop Revenue (2022-2024)'!I41 -> 19.863196 | I6: ='Crop Revenue (2022-2024)'!J41 -> 29.78867 | ... U6: ='Crop Revenue (2022-2024)'!V41 -> 45.425216 | V6: =SUM(B6:U6) -> 598.101
A7: Carrot Revenue (2.5 x 1 m) - DIRECT MARKETING | B7: ='Crop Revenue (2022-2024)'!C53 -> 5.1121876 | C7: ='Crop Revenue (2022-2024)'!D53 -> 14.570582 | D7: ='Crop Revenue (2022-2024)'!E53 -> 5.6354514 | E7: ='Crop Revenue (2022-2024)'!F53 -> 12.48479 | F7: ='Crop Revenue (2022-2024)'!G53 -> 9.6408862 | G7: ='Crop Revenue (2022-2024)'!H53 -> 7.7430334 | H7: ='Crop Revenue (2022-2024)'!I53 -> 13.389683 | I7: ='Crop Revenue (2022-2024)'!J53 -> 7.4870003 | ... U7: ='Crop Revenue (2022-2024)'!V53 -> 25.002632 | V7: =SUM(B7:U7) -> 301.21135
A8: Kale Revenue (2.5 x 1 m) - DIRECT MARKETING | B8: ='Crop Revenue (2022-2024)'!C65 -> 0.1519513 | C8: ='Crop Revenue (2022-2024)'!D65 -> 0.2505687 | D8: ='Crop Revenue (2022-2024)'!E65 -> 0.24402775 | E8: ='Crop Revenue (2022-2024)'!F65 -> 0.28528605 | F8: ='Crop Revenue (2022-2024)'!G65 -> 0.31446875 | G8: ='Crop Revenue (2022-2024)'!H65 -> 0.12830325 | H8: ='Crop Revenue (2022-2024)'!I65 -> 0.2727073 | I8: ='Crop Revenue (2022-2024)'!J65 -> 0.1529576 | ... U8: ='Crop Revenue (2022-2024)'!V65 -> 0.93499192 | V8: =SUM(B8:U8) -> 10.087815
A9: Livestock Revenue | B9: 0 | C9: 0 | D9: 0 | E9: 0 | F9: 0 | G9: 0 | H9: 0 | I9: 0 | J9: 0 | K9: 0 | L9: 0 | M9: 0 | N9: 0 | O9: 0 | P9: 0 | Q9: 0 | R9: 0 | S9: 0 | T9: 0 | U9: 0 | V9: =SUM(B9:U9) -> 0
A10: TOTAL REVENUE - WHOLESALE | B10: =SUM(B3:B5,B9) -> 17.718955 | C10: =SUM(C3:C5,C9) -> 25.447203 | D10: =SUM(D3:D5,D9) -> 18.223213 | E10: =SUM(E3:E5,E9) -> 24.701339 | F10: =SUM(F3:F5,F9) -> 17.612371 | G10: =SUM(G3:G5,G9) -> 17.484295 | H10: =SUM(H3:H5,H9) -> 19.720933 | I10: =SUM(I3:I5,I9) -> 22.01684 | ... U10: =SUM(U3:U5,U9) -> 39.646022 | V10: =SUM(B10:U10) -> 514.27371
A11: TOTAL REVENUE - DIRECT MARKETING | B11: =SUM(B6:B9) -> 30.122223 | C11: =SUM(C6:C9) -> 43.260245 | D11: =SUM(D6:D9) -> 30.979462 | E11: =SUM(E6:E9) -> 41.992277 | F11: =SUM(F6:F9) -> 29.941031 | G11: =SUM(G6:G9) -> 29.723302 | H11: =SUM(H6:H9) -> 33.525586 | I11: =SUM(I6:I9) -> 37.428628 | ... U11: =SUM(U6:U9) -> 71.36284 | V11: =SUM(B11:U11) -> 909.40016
A12: TOTAL REVENUE - WHOLESALE WITH 33% SORT-OUTS | B12: =(2/3)*B10 -> 11.812637 | C12: =(2/3)*C10 -> 16.964802 | D12: =(2/3)*D10 -> 12.148808 | E12: =(2/3)*E10 -> 16.467559 | F12: =(2/3)*F10 -> 11.741581 | G12: =(2/3)*G10 -> 11.656197 | H12: =(2/3)*H10 -> 13.147289 | I12: =(2/3)*I10 -> 14.677894 | ... U12: =(2/3)*U10 -> 26.430682 | V12: =SUM(B12:U12) -> 342.84914
A13: TOTAL REVENUE - DIRECT MARKETING WITH 20% UNSOLD | B13: =0.8*B11 -> 24.097779 | C13: =0.8*C11 -> 34.608196 | D13: =0.8*D11 -> 24.783569 | E13: =0.8*E11 -> 33.593821 | F13: =0.8*F11 -> 23.952825 | G13: =0.8*G11 -> 23.778642 | H13: =0.8*H11 -> 26.820469 | I13: =0.8*I11 -> 29.942903 | ... U13: =0.8*U11 -> 57.090272 | V13: =SUM(B13:U13) -> 727.52013
A15: ANNUAL VARIABLE COST | B15: =AVERAGE(B10:E10) -> 21.522677
A16: TOTAL LAND PREPARATION COST
A17: Machine Cost - Land Preparation | B17: ='Land Prep Costs (2022-2024)'!$I$10 -> 1.2458333 | C17: ='Land Prep Costs (2022-2024)'!$I$10 -> 1.2458333 | D17: ='Land Prep Costs (2022-2024)'!$I$10 -> 1.2458333 | E17: ='Land Prep Costs (2022-2024)'!$I$10 -> 1.2458333 | F17: ='Land Prep Costs (2022-2024)'!$I$10 -> 1.2458333 | G17: ='Land Prep Costs (2022-2024)'!$I$10 -> 1.2458333 | H17: ='Land Prep Costs (2022-2024)'!$I$10 -> 1.2458333 | I17: ='Land Prep Costs (2022-2024)'!$I$10 -> 1.2458333 | ... U17: ='Land Prep Costs (2022-2024)'!$I$10 -> 1.2458333 | V17: =SUM(B17:U17) -> 24.916667 | X17: Questions
A18: Labour Cost - Land Preparation | B18: ='Land Prep Costs (2022-2024)'!$I$29 -> 7.1077083 | C18: ='Land Prep Costs (2022-2024)'!$I$29 -> 7.1077083 | D18: ='Land Prep Costs (2022-2024)'!$I$29 -> 7.1077083 | E18: ='Land Prep Costs (2022-2024)'!$I$29 -> 7.1077083 | F18: ='Land Prep Costs (2022-2024)'!$I$29 -> 7.1077083 | G18: ='Land Prep Costs (2022-2024)'!$I$29 -> 7.1077083 | H18: ='Land Prep Costs (2022-2024)'!$I$29 -> 7.1077083 | I18: ='Land Prep Costs (2022-2024)'!$I$29 -> 7.1077083 | J18: ='Land Prep Costs (2022-2024)'!$I$30 -> 8.411875 | K18: ='Land Prep Costs (2022-2024)'!$I$30 -> 8.411875 | L18: ='Land Prep Costs (2022-2024)'!$I$30 -> 8.411875 | M18: ='Land Prep Costs (2022-2024)'!$I$30 -> 8.411875 | N18: ='Land Prep Costs (2022-2024)'!$I$30 -> 8.411875 | O18: ='Land Prep Costs (2022-2024)'!$I$30 -> 8.411875 | P18: ='Land Prep Costs (2022-2024)'!$I$30 -> 8.411875 | Q18: ='Land Prep Costs (2022-2024)'!$I$30 -> 8.411875 | ... U18: ='Land Prep Costs (2022-2024)'!$I$30 -> 8.411875 | V18: =SUM(B18:U18) -> 157.80417 | X18: 1. What about weed whacking and mower use? Also for carrying crops
A19: Fuel | B19: ='Costs (2022-2024)'!$I$16 -> 1 | C19: ='Costs (2022-2024)'!$I$16 -> 1 | D19: ='Costs (2022-2024)'!$I$16 -> 1 | E19: ='Costs (2022-2024)'!$I$16 -> 1 | F19: ='Costs (2022-2024)'!$I$16 -> 1 | G19: ='Costs (2022-2024)'!$I$16 -> 1 | H19: ='Costs (2022-2024)'!$I$16 -> 1 | I19: ='Costs (2022-2024)'!$I$16 -> 1 | ... U19: ='Costs (2022-2024)'!$I$16 -> 1 | V19: =SUM(B19:U19) -> 20 | X19: 2. How do I quantify sheep revenue?
A20: TOTAL FERTILITY & NUTRIENT COST | X20: 3. What about fuel costs?
A21: Inorganic Fertilizer | B21: ='Costs (2022-2024)'!$I$9 -> 1.67875 | C21: ='Costs (2022-2024)'!$I$9 -> 1.67875 | D21: ='Costs (2022-2024)'!$I$9 -> 1.67875 | E21: ='Costs (2022-2024)'!$I$9 -> 1.67875 | F21: ='Costs (2022-2024)'!$I$9 -> 1.67875 | G21: ='Costs (2022-2024)'!$I$9 -> 1.67875 | H21: ='Costs (2022-2024)'!$I$9 -> 1.67875 | I21: ='Costs (2022-2024)'!$I$9 -> 1.67875 | J21: 0 | K21: 0 | L21: 0 | M21: 0 | N21: 0 | O21: 0 | P21: 0 | Q21: 0 | R21: 0 | S21: 0 | T21: 0 | U21: 0 | V21: =SUM(B21:U21) -> 13.43 | X21: 4. What about post-harvest?
A22: Compost | B22: 0 | C22: 0 | D22: 0 | E22: 0 | F22: 0 | G22: 0 | H22: 0 | I22: 0 | J22: =243/12 -> 20.25 | K22: =243/12 -> 20.25 | L22: =243/12 -> 20.25 | M22: =243/12 -> 20.25 | N22: =243/12 -> 20.25 | O22: =243/12 -> 20.25 | P22: =243/12 -> 20.25 | Q22: =243/12 -> 20.25 | ... U22: =243/12 -> 20.25 | V22: =SUM(B22:U22) -> 243
A23: TOTAL SEED COST
A24: Cover Crop Seeds | B24: 0 | C24: 0 | D24: 0 | E24: 0 | F24: ='Costs (2022-2024)'!$I$6 -> 2.885 | G24: ='Costs (2022-2024)'!$I$6 -> 2.885 | H24: ='Costs (2022-2024)'!$I$6 -> 2.885 | I24: ='Costs (2022-2024)'!$I$6 -> 2.885 | J24: ='Costs (2022-2024)'!$I$6 -> 2.885 | K24: ='Costs (2022-2024)'!$I$6 -> 2.885 | L24: ='Costs (2022-2024)'!$I$6 -> 2.885 | M24: ='Costs (2022-2024)'!$I$6 -> 2.885 | ... U24: ='Costs (2022-2024)'!$I$6 -> 2.885 | V24: =SUM(B24:U24) -> 46.16
A25: TOTAL PLANTING COST
A26: Labour Cost - Planting | B26: ='Labour Costs (2022-2024)'!C4 -> 0 | C26: ='Labour Costs (2022-2024)'!D4 -> 0 | D26: ='Labour Costs (2022-2024)'!E4 -> 0 | E26: ='Labour Costs (2022-2024)'!F4 -> 0 | F26: ='Labour Costs (2022-2024)'!G4 -> 0.39125 | G26: ='Labour Costs (2022-2024)'!H4 -> 0.39125 | H26: ='Labour Costs (2022-2024)'!I4 -> 0.39125 | I26: ='Labour Costs (2022-2024)'!J4 -> 0.39125 | ... U26: ='Labour Costs (2022-2024)'!V4 -> 0.39125 | V26: =SUM(B26:U26) -> 6.26
A27: TOTAL WEEDING & PEST MANAGEMENT COST
A28: Labour Cost - Weeding | B28: ='Labour Costs (2022-2024)'!C11 -> 11.998333 | C28: ='Labour Costs (2022-2024)'!D11 -> 10.1725 | D28: ='Labour Costs (2022-2024)'!E11 -> 13.041667 | E28: ='Labour Costs (2022-2024)'!F11 -> 18.519167 | F28: ='Labour Costs (2022-2024)'!G11 -> 11.998333 | G28: ='Labour Costs (2022-2024)'!H11 -> 18.258333 | H28: ='Labour Costs (2022-2024)'!I11 -> 16.954167 | I28: ='Labour Costs (2022-2024)'!J11 -> 11.7375 | ... U28: ='Labour Costs (2022-2024)'!V11 -> 8.8683333 | V28: =SUM(B28:U28) -> 327.34583
A29: TOTAL HARVEST COST
A30: Labour Cost - Bean Harvest | B30: ='Labour Costs (2022-2024)'!C20 -> 4.9558333 | C30: ='Labour Costs (2022-2024)'!D20 -> 5.4775 | D30: ='Labour Costs (2022-2024)'!E20 -> 4.695 | E30: ='Labour Costs (2022-2024)'!F20 -> 5.4775 | F30: ='Labour Costs (2022-2024)'!G20 -> 3.9125 | G30: ='Labour Costs (2022-2024)'!H20 -> 4.4341667 | H30: ='Labour Costs (2022-2024)'!I20 -> 4.1733333 | I30: ='Labour Costs (2022-2024)'!J20 -> 6.26 | ... U30: ='Labour Costs (2022-2024)'!V20 -> 5.2166667 | V30: =SUM(B30:U30) -> 85.553333 | AJ30: ='Crop Prices (2022-2024)'!I15/'Crop Prices (2022-2024)'!D15 -> 3.27
A31: Labour Cost - Carrot Harvest | B31: ='Labour Costs (2022-2024)'!C21 -> 1.0433333 | C31: ='Labour Costs (2022-2024)'!D21 -> 4.4341667 | D31: ='Labour Costs (2022-2024)'!E21 -> 3.3908333 | E31: ='Labour Costs (2022-2024)'!F21 -> 3.6516667 | F31: ='Labour Costs (2022-2024)'!G21 -> 2.3475 | G31: ='Labour Costs (2022-2024)'!H21 -> 2.0866667 | H31: ='Labour Costs (2022-2024)'!I21 -> 2.6083333 | I31: ='Labour Costs (2022-2024)'!J21 -> 1.8258333 | ... U31: ='Labour Costs (2022-2024)'!V21 -> 1.3041667 | V31: =SUM(B31:U31) -> 37.299167
A32: Labour Cost - Kale Harvest | B32: ='Labour Costs (2022-2024)'!C22 -> 0.45645833 | C32: ='Labour Costs (2022-2024)'!D22 -> 0.52166667 | D32: ='Labour Costs (2022-2024)'!E22 -> 0.39125 | E32: ='Labour Costs (2022-2024)'!F22 -> 0.45645833 | F32: ='Labour Costs (2022-2024)'!G22 -> 0.39125 | G32: ='Labour Costs (2022-2024)'!H22 -> 0.45645833 | H32: ='Labour Costs (2022-2024)'!I22 -> 0.32604167 | I32: ='Labour Costs (2022-2024)'!J22 -> 0.45645833 | ... U32: ='Labour Costs (2022-2024)'!V22 -> 0.7825 | V32: =SUM(B32:U32) -> 9.4552083
A33: TOTAL LIVESTOCK COST
A34: Labour Cost - Livestock Management | B34: ='Labour Costs (2022-2024)'!C37 -> 0 | C34: ='Labour Costs (2022-2024)'!D37 -> 0 | D34: ='Labour Costs (2022-2024)'!E37 -> 0 | E34: ='Labour Costs (2022-2024)'!F37 -> 0 | F34: ='Labour Costs (2022-2024)'!G37 -> 0 | G34: ='Labour Costs (2022-2024)'!H37 -> 0 | H34: ='Labour Costs (2022-2024)'!I37 -> 0 | I34: ='Labour Costs (2022-2024)'!J37 -> 0 | ... U34: ='Labour Costs (2022-2024)'!V37 -> 0 | V34: =SUM(B34:U34) -> 0
A35: Equipment - Livestock | B35: 0 | C35: 0 | D35: 0 | E35: 0 | F35: 0 | G35: 0 | H35: 0 | I35: 0 | J35: 0 | K35: 0 | L35: 0 | M35: 0 | N35: 0 | O35: 0 | P35: 0 | Q35: 0 | R35: 0 | S35: 0 | T35: 0 | U35: 0 | V35: =SUM(B35:U35) -> 0
A36: Livestock Cost | B36: 0 | C36: 0 | D36: 0 | E36: 0 | F36: 0 | G36: 0 | H36: 0 | I36: 0 | J36: 0 | K36: 0 | L36: 0 | M36: 0 | N36: 0 | O36: 0 | P36: 0 | Q36: 0 | R36: 0 | S36: 0 | T36: 0 | U36: 0 | V36: =SUM(B36:U36) -> 0
A37: TOTAL MARKETING COST
A38: Associated Marketing Costs - Wholesale (25% of Total Revenue) | B38: =B10*0.25 -> 4.4297387 | C38: =C10*0.25 -> 6.3618007 | D38: =D10*0.25 -> 4.5558032 | E38: =E10*0.25 -> 6.1753348 | F38: =F10*0.25 -> 4.4030928 | G38: =G10*0.25 -> 4.3710739 | H38: =H10*0.25 -> 4.9302333 | I38: =I10*0.25 -> 5.5042101 | ... U38: =U10*0.25 -> 9.9115056 | V38: =SUM(B38:U38) -> 128.56843
A39: Associated Marketing Costs - Direct Marketing (35% of Total Revenue) | B39: =B11*0.35 -> 10.542778 | C39: =C11*0.35 -> 15.141086 | D39: =D11*0.35 -> 10.842812 | E39: =E11*0.35 -> 14.697297 | F39: =F11*0.35 -> 10.479361 | G39: =G11*0.35 -> 10.403156 | H39: =H11*0.35 -> 11.733955 | I39: =I11*0.35 -> 13.10002 | ... U39: =U11*0.35 -> 24.976994 | V39: =SUM(B39:U39) -> 318.29006 | W39: Note: I figured that total marketing costs will be 25% of the annual variable cost.
A40: TOTAL INPUT COST | B40: =SUM(B21,B22,B24) -> 1.67875 | C40: =SUM(C21,C22,C24) -> 1.67875 | D40: =SUM(D21,D22,D24) -> 1.67875 | E40: =SUM(E21,E22,E24) -> 1.67875 | F40: =SUM(F21,F22,F24) -> 4.56375 | G40: =SUM(G21,G22,G24) -> 4.56375 | H40: =SUM(H21,H22,H24) -> 4.56375 | I40: =SUM(I21,I22,I24) -> 4.56375 | ... U40: =SUM(U21,U22,U24) -> 23.135 | V40: =SUM(B40:U40) -> 302.59
A41: TOTAL ANNUAL LABOUR COST - WHOLESALE | B41: =SUM(B18+B26+B28+B30+B31+B32+B34) -> 25.561667 | C41: =SUM(C18+C26+C28+C30+C31+C32+C34) -> 27.713542 | D41: =SUM(D18+D26+D28+D30+D31+D32+D34) -> 28.626458 | E41: =SUM(E18+E26+E28+E30+E31+E32+E34) -> 35.2125 | F41: =SUM(F18+F26+F28+F30+F31+F32+F34) -> 26.148542 | G41: =SUM(G18+G26+G28+G30+G31+G32+G34) -> 32.734583 | H41: =SUM(H18+H26+H28+H30+H31+H32+H34) -> 31.560833 | I41: =SUM(I18+I26+I28+I30+I31+I32+I34) -> 27.77875 | ... U41: =SUM(U18+U26+U28+U30+U31+U32+U34) -> 24.974792 | V41: =SUM(B41:U41) -> 623.71771
A42: TOTAL ANNUAL LABOUR COST - DIRECT MARKETING | B42: =SUM(B18+B26+B28+B30+B31+B32+B34) -> 25.561667 | C42: =SUM(C18+C26+C28+C30+C31+C32+C34) -> 27.713542 | D42: =SUM(D18+D26+D28+D30+D31+D32+D34) -> 28.626458 | E42: =SUM(E18+E26+E28+E30+E31+E32+E34) -> 35.2125 | F42: =SUM(F18+F26+F28+F30+F31+F32+F34) -> 26.148542 | G42: =SUM(G18+G26+G28+G30+G31+G32+G34) -> 32.734583 | H42: =SUM(H18+H26+H28+H30+H31+H32+H34) -> 31.560833 | I42: =SUM(I18+I26+I28+I30+I31+I32+I34) -> 27.77875 | ... U42: =SUM(U18+U26+U28+U30+U31+U32+U34) -> 24.974792 | V42: =SUM(B42:U42) -> 623.71771
A43: TOTAL ANNUAL VARIABLE COST - WHOLESALE | B43: =SUM(B16:B36,B38) -> 33.915989 | C43: =SUM(C16:C36,C38) -> 37.999926 | D43: =SUM(D16:D36,D38) -> 37.106845 | E43: =SUM(E16:E36,E38) -> 45.312418 | F43: =SUM(F16:F36,F38) -> 37.361218 | G43: =SUM(G16:G36,G38) -> 43.915241 | H43: =SUM(H16:H36,H38) -> 43.30065 | I43: =SUM(I16:I36,I38) -> 40.092543 | ... U43: =SUM(U16:U36,U38) -> 60.267131 | V43: =SUM(B43:U43) -> 1099.7928
A44: TOTAL ANNUAL VARIABLE COST - DIRECT MARKETING | B44: =SUM(B16:B36,B39) -> 40.029028 | C44: =SUM(C16:C36,C39) -> 46.779211 | D44: =SUM(D16:D36,D39) -> 43.393853 | E44: =SUM(E16:E36,E39) -> 53.83438 | F44: =SUM(F16:F36,F39) -> 43.437486 | G44: =SUM(G16:G36,G39) -> 49.947322 | H44: =SUM(H16:H36,H39) -> 50.104372 | I44: =SUM(I16:I36,I39) -> 47.688353 | ... U44: =SUM(U16:U36,U39) -> 75.332619 | V44: =SUM(B44:U44) -> 1289.5144
A46: NET RETURNS
A47: RETURNS OVER VARIABLE COST - WHOLESALE | B47: =B10-B43 -> -16.197034 | C47: =C10-C43 -> -12.552723 | D47: =D10-D43 -> -18.883632 | E47: =E10-E43 -> -20.611079 | F47: =F10-F43 -> -19.748847 | G47: =G10-G43 -> -26.430945 | H47: =H10-H43 -> -23.579717 | I47: =I10-I43 -> -18.075703 | ... U47: =U10-U43 -> -20.621108 | V47: =AVERAGE(B47:U47) -> -29.275955
A48: RETURNS OVER VARIABLE COST - DIRECT MARKETING | B48: =B11-B44 -> -9.9068048 | C48: =C11-C44 -> -3.518966 | D48: =D11-D44 -> -12.414392 | E48: =E11-E44 -> -11.842103 | F48: =F11-F44 -> -13.496455 | G48: =G11-G44 -> -20.22402 | H48: =H11-H44 -> -16.578786 | I48: =I11-I44 -> -10.259725 | ... U48: =U11-U44 -> -3.969779 | V48: =AVERAGE(B48:U48) -> -19.005714
A49: RETURNS OVER VARIABLE COST - WHOLESALE WITH 33% SORT OUTS | B49: =B12-B43 -> -22.103352 | C49: =C12-C43 -> -21.035124 | D49: =D12-D43 -> -24.958036 | E49: =E12-E43 -> -28.844859 | F49: =F12-F43 -> -25.619637 | G49: =G12-G43 -> -32.259044 | H49: =H12-H43 -> -30.153361 | I49: =I12-I43 -> -25.41465 | ... U49: =U12-U43 -> -33.836449 | V49: =AVERAGE(B49:U49) -> -37.847183
A50: RETURNS OVER VARIABLE COST - DIRECT MARKETING WITH 20% UNSOLD | B50: =B13-B44 -> -15.931249 | C50: =C13-C44 -> -12.171015 | D50: =D13-D44 -> -18.610284 | E50: =E13-E44 -> -20.240559 | F50: =F13-F44 -> -19.484661 | G50: =G13-G44 -> -26.168681 | H50: =H13-H44 -> -23.283903 | I50: =I13-I44 -> -17.745451 | ... U50: =U13-U44 -> -18.242347 | V50: =AVERAGE(B50:U50) -> -28.099715

Sheet Cost-Benefit Analysis 2023
B1: Treatment 1-1 | C1: Treatment 1-2 | D1: Treatment 1-3 | E1: Treatment 1-4 | F1: Treatment 2-1 | G1: Treatment 2-2 | H1: Treatment 2-3 | I1: Treatment 2-4 | J1: Treatment 3-1 | K1: Treatment 3-2 | L1: Treatment 3-3 | M1: Treatment 3-4 | N1: Treatment 4-1 | O1: Treatment 4-2 | P1: Treatment 4-3 | Q1: Treatment 4-4 | R1: Treatment 5-1 | S1: Treatment 5-2 | T1: Treatment 5-3 | U1: Treatment 5-4 | V1: TOTAL
A2: REVENUE
A3: Bean Revenue (2.5 x 1 m) - WHOLESALE | B3: ='Crop Revenue (2022-2024)'!C8 -> 21.917611 | C3: ='Crop Revenue (2022-2024)'!D8 -> 26.451024 | D3: ='Crop Revenue (2022-2024)'!E8 -> 37.073482 | E3: ='Crop Revenue (2022-2024)'!F8 -> 23.572409 | F3: ='Crop Revenue (2022-2024)'!G8 -> 20.702853 | G3: ='Crop Revenue (2022-2024)'!H8 -> 34.599152 | H3: ='Crop Revenue (2022-2024)'!I8 -> 29.859784 | I3: ='Crop Revenue (2022-2024)'!J8 -> 33.117891 | ... U3: ='Crop Revenue (2022-2024)'!V8 -> 55.954893 | V3: =SUM(B3:U3) -> 777.32225
A4: Carrot Revenue (2.5 x 1 m) - WHOLESALE | B4: ='Crop Revenue (2022-2024)'!C20 -> 7.9533423 | C4: ='Crop Revenue (2022-2024)'!D20 -> 13.578387 | D4: ='Crop Revenue (2022-2024)'!E20 -> 14.422656 | E4: ='Crop Revenue (2022-2024)'!F20 -> 11.945178 | F4: ='Crop Revenue (2022-2024)'!G20 -> 12.668954 | G4: ='Crop Revenue (2022-2024)'!H20 -> 10.223238 | H4: ='Crop Revenue (2022-2024)'!I20 -> 8.5328552 | I4: ='Crop Revenue (2022-2024)'!J20 -> 12.556453 | ... U4: ='Crop Revenue (2022-2024)'!V20 -> 23.66662 | V4: =SUM(B4:U4) -> 447.85987
A5: Kale Revenue (2.5 x 1 m) - WHOLESALE | B5: ='Crop Revenue (2022-2024)'!C32 -> 1.7873614 | C5: ='Crop Revenue (2022-2024)'!D32 -> 5.8808777 | D5: ='Crop Revenue (2022-2024)'!E32 -> 2.8455538 | E5: ='Crop Revenue (2022-2024)'!F32 -> 3.1878711 | F5: ='Crop Revenue (2022-2024)'!G32 -> 6.2451299 | G5: ='Crop Revenue (2022-2024)'!H32 -> 2.4965896 | H5: ='Crop Revenue (2022-2024)'!I32 -> 6.3415104 | I5: ='Crop Revenue (2022-2024)'!J32 -> 4.995838 | ... U5: ='Crop Revenue (2022-2024)'!V32 -> 7.5918341 | V5: =SUM(B5:U5) -> 105.76631
A6: Bean Revenue (2.5 x 1 m) - DIRECT MARKETING | B6: ='Crop Revenue (2022-2024)'!C44 -> 37.259939 | C6: ='Crop Revenue (2022-2024)'!D44 -> 44.96674 | D6: ='Crop Revenue (2022-2024)'!E44 -> 63.02492 | E6: ='Crop Revenue (2022-2024)'!F44 -> 40.073096 | F6: ='Crop Revenue (2022-2024)'!G44 -> 35.19485 | G6: ='Crop Revenue (2022-2024)'!H44 -> 58.818558 | H6: ='Crop Revenue (2022-2024)'!I44 -> 50.761632 | I6: ='Crop Revenue (2022-2024)'!J44 -> 56.300414 | ... U6: ='Crop Revenue (2022-2024)'!V44 -> 100.71881 | V6: =SUM(B6:U6) -> 1376.4506 | X6: =6666.69-1754.04 -> 4912.65
A7: Carrot Revenue (2.5 x 1 m) - DIRECT MARKETING | B7: ='Crop Revenue (2022-2024)'!C56 -> 13.520682 | C7: ='Crop Revenue (2022-2024)'!D56 -> 23.083258 | D7: ='Crop Revenue (2022-2024)'!E56 -> 24.518516 | E7: ='Crop Revenue (2022-2024)'!F56 -> 20.306802 | F7: ='Crop Revenue (2022-2024)'!G56 -> 21.537222 | G7: ='Crop Revenue (2022-2024)'!H56 -> 17.379504 | H7: ='Crop Revenue (2022-2024)'!I56 -> 14.505854 | I7: ='Crop Revenue (2022-2024)'!J56 -> 21.34597 | ... U7: ='Crop Revenue (2022-2024)'!V56 -> 42.599917 | V7: =SUM(B7:U7) -> 796.95965 | X7: 1754.04
A8: Kale Revenue (2.5 x 1 m) - DIRECT MARKETING | B8: ='Crop Revenue (2022-2024)'!C68 -> 3.0385144 | C8: ='Crop Revenue (2022-2024)'!D68 -> 9.9974921 | D8: ='Crop Revenue (2022-2024)'!E68 -> 4.8374415 | E8: ='Crop Revenue (2022-2024)'!F68 -> 5.4193808 | F8: ='Crop Revenue (2022-2024)'!G68 -> 10.616721 | G8: ='Crop Revenue (2022-2024)'!H68 -> 4.2442023 | H8: ='Crop Revenue (2022-2024)'!I68 -> 10.780568 | I8: ='Crop Revenue (2022-2024)'!J68 -> 8.4929246 | ... U8: ='Crop Revenue (2022-2024)'!V68 -> 13.665301 | V8: =SUM(B8:U8) -> 187.00128 | X8: =X7/X6 -> 0.35704559
A9: Livestock Revenue | B9: 0 | C9: 0 | D9: 0 | E9: 0 | F9: 0 | G9: 0 | H9: 0 | I9: 0 | J9: 0 | K9: 0 | L9: 0 | M9: 0 | N9: 0 | O9: 0 | P9: 0 | Q9: 0 | R9: 0 | S9: 0 | T9: 0 | U9: 0 | V9: =SUM(B9:U9) -> 0
A10: TOTAL REVENUE - WHOLESALE | B10: =SUM(B3:B5,B9) -> 31.658315 | C10: =SUM(C3:C5,C9) -> 45.910289 | D10: =SUM(D3:D5,D9) -> 54.341693 | E10: =SUM(E3:E5,E9) -> 38.705458 | F10: =SUM(F3:F5,F9) -> 39.616937 | G10: =SUM(G3:G5,G9) -> 47.318979 | H10: =SUM(H3:H5,H9) -> 44.734149 | I10: =SUM(I3:I5,I9) -> 50.670182 | ... U10: =SUM(U3:U5,U9) -> 87.213347 | V10: =SUM(B10:U10) -> 1330.9484
A11: TOTAL REVENUE - DIRECT MARKETING | B11: =SUM(B6:B9) -> 53.819136 | C11: =SUM(C6:C9) -> 78.047491 | D11: =SUM(D6:D9) -> 92.380877 | E11: =SUM(E6:E9) -> 65.799279 | F11: =SUM(F6:F9) -> 67.348793 | G11: =SUM(G6:G9) -> 80.442264 | H11: =SUM(H6:H9) -> 76.048054 | I11: =SUM(I6:I9) -> 86.139309 | ... U11: =SUM(U6:U9) -> 156.98403 | V11: =SUM(B11:U11) -> 2360.4116
A12: TOTAL REVENUE - WHOLESALE WITH 33% SORT-OUTS | B12: =(2/3)*B10 -> 21.105543 | C12: =(2/3)*C10 -> 30.606859 | D12: =(2/3)*D10 -> 36.227795 | E12: =(2/3)*E10 -> 25.803639 | F12: =(2/3)*F10 -> 26.411291 | G12: =(2/3)*G10 -> 31.545986 | H12: =(2/3)*H10 -> 29.822766 | I12: =(2/3)*I10 -> 33.780121 | ... U12: =(2/3)*U10 -> 58.142232 | V12: =SUM(B12:U12) -> 887.29895
A13: TOTAL REVENUE - DIRECT MARKETING WITH 20% UNSOLD | B13: =0.8*B11 -> 43.055308 | C13: =0.8*C11 -> 62.437993 | D13: =0.8*D11 -> 73.904702 | E13: =0.8*E11 -> 52.639423 | F13: =0.8*F11 -> 53.879034 | G13: =0.8*G11 -> 64.353811 | H13: =0.8*H11 -> 60.838443 | I13: =0.8*I11 -> 68.911447 | ... U13: =0.8*U11 -> 125.58722 | V13: =SUM(B13:U13) -> 1888.3293
A15: ANNUAL VARIABLE COST
A16: TOTAL LAND PREPARATION COST
A17: Machine Cost - Land Preparation | B17: ='Land Prep Costs (2022-2024)'!$I$11 -> 5.8658854 | C17: ='Land Prep Costs (2022-2024)'!$I$11 -> 5.8658854 | D17: ='Land Prep Costs (2022-2024)'!$I$11 -> 5.8658854 | E17: ='Land Prep Costs (2022-2024)'!$I$11 -> 5.8658854 | F17: ='Land Prep Costs (2022-2024)'!$I$11 -> 5.8658854 | G17: ='Land Prep Costs (2022-2024)'!$I$11 -> 5.8658854 | H17: ='Land Prep Costs (2022-2024)'!$I$11 -> 5.8658854 | I17: ='Land Prep Costs (2022-2024)'!$I$11 -> 5.8658854 | ... Q17: ='Land Prep Costs (2022-2024)'!$I$11 -> 5.8658854 | R17: 0 | S17: 0 | T17: 0 | U17: 0 | V17: =SUM(B17:U17) -> 93.854167 | X17: Questions
A18: Labour Cost - Land Preparation | B18: ='Land Prep Costs (2022-2024)'!$I$31 -> 5.1907552 | C18: ='Land Prep Costs (2022-2024)'!$I$31 -> 5.1907552 | D18: ='Land Prep Costs (2022-2024)'!$I$31 -> 5.1907552 | E18: ='Land Prep Costs (2022-2024)'!$I$31 -> 5.1907552 | F18: ='Land Prep Costs (2022-2024)'!$I$31 -> 5.1907552 | G18: ='Land Prep Costs (2022-2024)'!$I$31 -> 5.1907552 | H18: ='Land Prep Costs (2022-2024)'!$I$31 -> 5.1907552 | I18: ='Land Prep Costs (2022-2024)'!$I$31 -> 5.1907552 | J18: ='Land Prep Costs (2022-2024)'!$I$32 -> 6.5865885 | K18: ='Land Prep Costs (2022-2024)'!$I$32 -> 6.5865885 | L18: ='Land Prep Costs (2022-2024)'!$I$32 -> 6.5865885 | M18: ='Land Prep Costs (2022-2024)'!$I$32 -> 6.5865885 | N18: ='Land Prep Costs (2022-2024)'!$I$33 -> 7.6334635 | O18: ='Land Prep Costs (2022-2024)'!$I$33 -> 7.6334635 | P18: ='Land Prep Costs (2022-2024)'!$I$33 -> 7.6334635 | Q18: ='Land Prep Costs (2022-2024)'!$I$33 -> 7.6334635 | R18: ='Land Prep Costs (2022-2024)'!$I$34 -> 13.522135 | S18: ='Land Prep Costs (2022-2024)'!$I$34 -> 13.522135 | T18: ='Land Prep Costs (2022-2024)'!$I$34 -> 13.522135 | U18: ='Land Prep Costs (2022-2024)'!$I$34 -> 13.522135 | V18: =SUM(B18:U18) -> 152.49479 | X18: 1. What about weed whacking and mower use? Also for carrying crops
A19: Fuel | B19: ='Costs (2022-2024)'!$I$16 -> 1 | C19: ='Costs (2022-2024)'!$I$16 -> 1 | D19: ='Costs (2022-2024)'!$I$16 -> 1 | E19: ='Costs (2022-2024)'!$I$16 -> 1 | F19: ='Costs (2022-2024)'!$I$16 -> 1 | G19: ='Costs (2022-2024)'!$I$16 -> 1 | H19: ='Costs (2022-2024)'!$I$16 -> 1 | I19: ='Costs (2022-2024)'!$I$16 -> 1 | ... U19: ='Costs (2022-2024)'!$I$16 -> 1 | V19: =SUM(B19:U19) -> 20 | X19: 2. How do I quantify sheep revenue?
A20: TOTAL FERTILITY & NUTRIENT COST | X20: 3. What about fuel costs?
A21: Inorganic Fertilizer | B21: ='Costs (2022-2024)'!$I$9 -> 1.67875 | C21: ='Costs (2022-2024)'!$I$9 -> 1.67875 | D21: ='Costs (2022-2024)'!$I$9 -> 1.67875 | E21: ='Costs (2022-2024)'!$I$9 -> 1.67875 | F21: ='Costs (2022-2024)'!$I$9 -> 1.67875 | G21: ='Costs (2022-2024)'!$I$9 -> 1.67875 | H21: ='Costs (2022-2024)'!$I$9 -> 1.67875 | I21: ='Costs (2022-2024)'!$I$9 -> 1.67875 | J21: 0 | K21: 0 | L21: 0 | M21: 0 | N21: 0 | O21: 0 | P21: 0 | Q21: 0 | R21: 0 | S21: 0 | T21: 0 | U21: 0 | V21: =SUM(B21:U21) -> 13.43 | X21: 4. What about post-harvest?
A22: Compost | B22: 0 | C22: 0 | D22: 0 | E22: 0 | F22: 0 | G22: 0 | H22: 0 | I22: 0 | J22: ='Costs (2022-2024)'!$I$13 -> 29.5 | K22: ='Costs (2022-2024)'!$I$13 -> 29.5 | L22: ='Costs (2022-2024)'!$I$13 -> 29.5 | M22: ='Costs (2022-2024)'!$I$13 -> 29.5 | N22: ='Costs (2022-2024)'!$I$13 -> 29.5 | O22: ='Costs (2022-2024)'!$I$13 -> 29.5 | P22: ='Costs (2022-2024)'!$I$13 -> 29.5 | Q22: ='Costs (2022-2024)'!$I$13 -> 29.5 | ... U22: ='Costs (2022-2024)'!$I$13 -> 29.5 | V22: =SUM(B22:U22) -> 354
A23: TOTAL SEED COST
A24: Cover Crop Seeds | B24: 0 | C24: 0 | D24: 0 | E24: 0 | F24: ='Costs (2022-2024)'!$I$7 -> 2.885 | G24: ='Costs (2022-2024)'!$I$7 -> 2.885 | H24: ='Costs (2022-2024)'!$I$7 -> 2.885 | I24: ='Costs (2022-2024)'!$I$7 -> 2.885 | J24: ='Costs (2022-2024)'!$I$7 -> 2.885 | K24: ='Costs (2022-2024)'!$I$7 -> 2.885 | L24: ='Costs (2022-2024)'!$I$7 -> 2.885 | M24: ='Costs (2022-2024)'!$I$7 -> 2.885 | ... U24: ='Costs (2022-2024)'!$I$7 -> 2.885 | V24: =SUM(B24:U24) -> 46.16
A25: TOTAL PLANTING COST
A26: Labour Cost - Planting | B26: ='Labour Costs (2022-2024)'!C6 -> 0 | C26: ='Labour Costs (2022-2024)'!D6 -> 0 | D26: ='Labour Costs (2022-2024)'!E6 -> 0 | E26: ='Labour Costs (2022-2024)'!F6 -> 0 | F26: ='Labour Costs (2022-2024)'!G6 -> 0.41875 | G26: ='Labour Costs (2022-2024)'!H6 -> 0.41875 | H26: ='Labour Costs (2022-2024)'!I6 -> 0.41875 | I26: ='Labour Costs (2022-2024)'!J6 -> 0.41875 | ... U26: ='Labour Costs (2022-2024)'!V6 -> 0.41875 | V26: =SUM(B26:U26) -> 6.7
A27: TOTAL WEEDING & PEST MANAGEMENT COST
A28: Labour Cost - Weeding | B28: ='Labour Costs (2022-2024)'!C13 -> 34.477083 | C28: ='Labour Costs (2022-2024)'!D13 -> 26.218403 | D28: ='Labour Costs (2022-2024)'!E13 -> 22.19375 | E28: ='Labour Costs (2022-2024)'!F13 -> 30.170938 | F28: ='Labour Costs (2022-2024)'!G13 -> 21.792448 | G28: ='Labour Costs (2022-2024)'!H13 -> 24.783021 | H28: ='Labour Costs (2022-2024)'!I13 -> 28.684375 | I28: ='Labour Costs (2022-2024)'!J13 -> 24.566667 | ... U28: ='Labour Costs (2022-2024)'!V13 -> 11.585417 | V28: =SUM(B28:U28) -> 505.74299
A29: TOTAL HARVEST COST
A30: Labour Cost - Bean Harvest | B30: ='Labour Costs (2022-2024)'!C26 -> 13.4 | C30: ='Labour Costs (2022-2024)'!D26 -> 12.283333 | D30: ='Labour Costs (2022-2024)'!E26 -> 15.005208 | E30: ='Labour Costs (2022-2024)'!F26 -> 11.096875 | F30: ='Labour Costs (2022-2024)'!G26 -> 9.4916667 | G30: ='Labour Costs (2022-2024)'!H26 -> 15.772917 | H30: ='Labour Costs (2022-2024)'!I26 -> 13.609375 | I30: ='Labour Costs (2022-2024)'!J26 -> 14.028125 | ... U30: ='Labour Costs (2022-2024)'!V26 -> 17.727083 | V30: =SUM(B30:U30) -> 270.86146 | AJ30: ='Crop Prices (2022-2024)'!I15/'Crop Prices (2022-2024)'!D15 -> 3.27
A31: Labour Cost - Carrot Harvest | B31: ='Labour Costs (2022-2024)'!C27 -> 4.3270833 | C31: ='Labour Costs (2022-2024)'!D27 -> 6.8395833 | D31: ='Labour Costs (2022-2024)'!E27 -> 4.6760417 | E31: ='Labour Costs (2022-2024)'!F27 -> 6.0020833 | F31: ='Labour Costs (2022-2024)'!G27 -> 5.5833333 | G31: ='Labour Costs (2022-2024)'!H27 -> 3.978125 | H31: ='Labour Costs (2022-2024)'!I27 -> 4.3270833 | I31: ='Labour Costs (2022-2024)'!J27 -> 7.3979167 | ... U31: ='Labour Costs (2022-2024)'!V27 -> 2.7916667 | V31: =SUM(B31:U31) -> 97.9875
A32: Labour Cost - Kale Harvest | B32: ='Labour Costs (2022-2024)'!C28 -> 3.0708333 | C32: ='Labour Costs (2022-2024)'!D28 -> 5.234375 | D32: ='Labour Costs (2022-2024)'!E28 -> 4.1177083 | E32: ='Labour Costs (2022-2024)'!F28 -> 4.3270833 | F32: ='Labour Costs (2022-2024)'!G28 -> 5.1645833 | G32: ='Labour Costs (2022-2024)'!H28 -> 4.5364583 | H32: ='Labour Costs (2022-2024)'!I28 -> 5.3739583 | I32: ='Labour Costs (2022-2024)'!J28 -> 4.0479167 | ... U32: ='Labour Costs (2022-2024)'!V28 -> 4.2572917 | V32: =SUM(B32:U32) -> 79.911458
A33: TOTAL LIVESTOCK COST
A34: Labour Cost - Livestock Management | B34: ='Labour Costs (2022-2024)'!C39 -> 0 | C34: ='Labour Costs (2022-2024)'!D39 -> 0 | D34: ='Labour Costs (2022-2024)'!E39 -> 0 | E34: ='Labour Costs (2022-2024)'!F39 -> 0 | F34: ='Labour Costs (2022-2024)'!G39 -> 0 | G34: ='Labour Costs (2022-2024)'!H39 -> 0 | H34: ='Labour Costs (2022-2024)'!I39 -> 0 | I34: ='Labour Costs (2022-2024)'!J39 -> 0 | ... U34: ='Labour Costs (2022-2024)'!V39 -> 10.46875 | V34: =SUM(B34:U34) -> 83.75
A35: Equipment - Livestock | B35: 0 | C35: 0 | D35: 0 | E35: 0 | F35: 0 | G35: 0 | H35: 0 | I35: 0 | J35: 0 | K35: 0 | L35: 0 | M35: 0 | N35: 0 | O35: 0 | P35: 0 | Q35: 0 | R35: 0 | S35: 0 | T35: 0 | U35: 0 | V35: =SUM(B35:U35) -> 0
A36: Livestock Cost | B36: 0 | C36: 0 | D36: 0 | E36: 0 | F36: 0 | G36: 0 | H36: 0 | I36: 0 | J36: 0 | K36: 0 | L36: 0 | M36: 0 | N36: 0 | O36: 0 | P36: 0 | Q36: 0 | R36: 0 | S36: 0 | T36: 0 | U36: 0 | V36: =SUM(B36:U36) -> 0
A37: TOTAL MARKETING COST
A38: Associated Marketing Costs - Wholesale (25% of Total Revenue) | B38: =B10*0.25 -> 7.9145788 | C38: =C10*0.25 -> 11.477572 | D38: =D10*0.25 -> 13.585423 | E38: =E10*0.25 -> 9.6763645 | F38: =F10*0.25 -> 9.9042342 | G38: =G10*0.25 -> 11.829745 | H38: =H10*0.25 -> 11.183537 | I38: =I10*0.25 -> 12.667545 | ... U38: =U10*0.25 -> 21.803337 | V38: =SUM(B38:U38) -> 332.73711
A39: Associated Marketing Costs - Direct Marketing (35% of Total Revenue) | B39: =B11*0.35 -> 18.836697 | C39: =C11*0.35 -> 27.316622 | D39: =D11*0.35 -> 32.333307 | E39: =E11*0.35 -> 23.029747 | F39: =F11*0.35 -> 23.572077 | G39: =G11*0.35 -> 28.154792 | H39: =H11*0.35 -> 26.616819 | I39: =I11*0.35 -> 30.148758 | ... U39: =U11*0.35 -> 54.944409 | V39: =SUM(B39:U39) -> 826.14405
A40: TOTAL INPUT COST | B40: =SUM(B21,B22,B24) -> 1.67875 | C40: =SUM(C21,C22,C24) -> 1.67875 | D40: =SUM(D21,D22,D24) -> 1.67875 | E40: =SUM(E21,E22,E24) -> 1.67875 | F40: =SUM(F21,F22,F24) -> 4.56375 | G40: =SUM(G21,G22,G24) -> 4.56375 | H40: =SUM(H21,H22,H24) -> 4.56375 | I40: =SUM(I21,I22,I24) -> 4.56375 | ... U40: =SUM(U21,U22,U24) -> 32.385 | V40: =SUM(B40:U40) -> 413.59
A41: TOTAL ANNUAL LABOUR COST - WHOLESALE | B41: =SUM(B18+B26+B28+B30+B31+B32+B34) -> 60.465755 | C41: =SUM(C18+C26+C28+C30+C31+C32+C34) -> 55.76645 | D41: =SUM(D18+D26+D28+D30+D31+D32+D34) -> 51.183464 | E41: =SUM(E18+E26+E28+E30+E31+E32+E34) -> 56.787734 | F41: =SUM(F18+F26+F28+F30+F31+F32+F34) -> 47.641536 | G41: =SUM(G18+G26+G28+G30+G31+G32+G34) -> 54.680026 | H41: =SUM(H18+H26+H28+H30+H31+H32+H34) -> 57.604297 | I41: =SUM(I18+I26+I28+I30+I31+I32+I34) -> 55.65013 | ... U41: =SUM(U18+U26+U28+U30+U31+U32+U34) -> 60.771094 | V41: =SUM(B41:U41) -> 1197.4482
A42: TOTAL ANNUAL LABOUR COST - DIRECT MARKETING | B42: =SUM(B18+B26+B28+B30+B31+B32+B34) -> 60.465755 | C42: =SUM(C18+C26+C28+C30+C31+C32+C34) -> 55.76645 | D42: =SUM(D18+D26+D28+D30+D31+D32+D34) -> 51.183464 | E42: =SUM(E18+E26+E28+E30+E31+E32+E34) -> 56.787734 | F42: =SUM(F18+F26+F28+F30+F31+F32+F34) -> 47.641536 | G42: =SUM(G18+G26+G28+G30+G31+G32+G34) -> 54.680026 | H42: =SUM(H18+H26+H28+H30+H31+H32+H34) -> 57.604297 | I42: =SUM(I18+I26+I28+I30+I31+I32+I34) -> 55.65013 | ... U42: =SUM(U18+U26+U28+U30+U31+U32+U34) -> 60.771094 | V42: =SUM(B42:U42) -> 1197.4482
A43: TOTAL ANNUAL VARIABLE COST - WHOLESALE | B43: =SUM(B16:B36,B38) -> 76.924969 | C43: =SUM(C16:C36,C38) -> 75.788657 | D43: =SUM(D16:D36,D38) -> 73.313522 | E43: =SUM(E16:E36,E38) -> 75.008734 | F43: =SUM(F16:F36,F38) -> 68.975406 | G43: =SUM(G16:G36,G38) -> 77.939406 | H43: =SUM(H16:H36,H38) -> 80.21747 | I43: =SUM(I16:I36,I38) -> 79.747311 | ... U43: =SUM(U16:U36,U38) -> 115.95943 | V43: =SUM(B43:U43) -> 2057.6295
A44: TOTAL ANNUAL VARIABLE COST - DIRECT MARKETING | B44: =SUM(B16:B36,B39) -> 87.847088 | C44: =SUM(C16:C36,C39) -> 91.627707 | D44: =SUM(D16:D36,D39) -> 92.061406 | E44: =SUM(E16:E36,E39) -> 88.362117 | F44: =SUM(F16:F36,F39) -> 82.643249 | G44: =SUM(G16:G36,G39) -> 94.264454 | H44: =SUM(H16:H36,H39) -> 95.650751 | I44: =SUM(I16:I36,I39) -> 97.228524 | ... U44: =SUM(U16:U36,U39) -> 149.1005 | V44: =SUM(B44:U44) -> 2551.0364
A46: NET RETURNS
A47: RETURNS OVER VARIABLE COST - WHOLESALE | B47: =B10-B43 -> -45.266654 | C47: =C10-C43 -> -29.878369 | D47: =D10-D43 -> -18.971829 | E47: =E10-E43 -> -36.303276 | F47: =F10-F43 -> -29.358469 | G47: =G10-G43 -> -30.620427 | H47: =H10-H43 -> -35.48332 | I47: =I10-I43 -> -29.077129 | ... U47: =U10-U43 -> -28.746083 | V47: =AVERAGE(B47:U47) -> -36.334052
A48: RETURNS OVER VARIABLE COST - DIRECT MARKETING | B48: =B11-B44 -> -34.027953 | C48: =C11-C44 -> -13.580216 | D48: =D11-D44 -> 0.3194714 | E48: =E11-E44 -> -22.562839 | F48: =F11-F44 -> -15.294457 | G48: =G11-G44 -> -13.82219 | H48: =H11-H44 -> -19.602697 | I48: =I11-I44 -> -11.089215 | ... U48: =U11-U44 -> 7.8835226 | V48: =AVERAGE(B48:U48) -> -9.5312422
A49: RETURNS OVER VARIABLE COST - WHOLESALE WITH 33% SORT OUTS | B49: =B12-B43 -> -55.819426 | C49: =C12-C43 -> -45.181798 | D49: =D12-D43 -> -37.085727 | E49: =E12-E43 -> -49.205096 | F49: =F12-F43 -> -42.564115 | G49: =G12-G43 -> -46.39342 | H49: =H12-H43 -> -50.394703 | I49: =I12-I43 -> -45.96719 | ... U49: =U12-U43 -> -57.817199 | V49: =AVERAGE(B49:U49) -> -58.516526
A50: RETURNS OVER VARIABLE COST - DIRECT MARKETING WITH 20% UNSOLD | B50: =B13-B44 -> -44.79178 | C50: =C13-C44 -> -29.189714 | D50: =D13-D44 -> -18.156704 | E50: =E13-E44 -> -35.722694 | F50: =F13-F44 -> -28.764215 | G50: =G13-G44 -> -29.910643 | H50: =H13-H44 -> -34.812308 | I50: =I13-I44 -> -28.317077 | ... U50: =U13-U44 -> -23.513282 | V50: =AVERAGE(B50:U50) -> -33.135358
B52: =B47/B10 -> -1.4298504 | C52: =C47/C10 -> -0.65079897 | D52: =D47/D10 -> -0.34912106 | E52: =E47/E10 -> -0.93793688 | F52: =F47/F10 -> -0.74105853 | G52: =G47/G10 -> -0.64710668 | H52: =H47/H10 -> -0.79320432 | I52: =I47/I10 -> -0.5738509 | ... P52: =P47/P10 -> -0.38279715

Sheet Cost-Benefit Analysis 2024
B1: Treatment 1-1 | C1: Treatment 1-2 | D1: Treatment 1-3 | E1: Treatment 1-4 | F1: Treatment 2-1 | G1: Treatment 2-2 | H1: Treatment 2-3 | I1: Treatment 2-4 | J1: Treatment 3-1 | K1: Treatment 3-2 | L1: Treatment 3-3 | M1: Treatment 3-4 | N1: Treatment 4-1 | O1: Treatment 4-2 | P1: Treatment 4-3 | Q1: Treatment 4-4 | R1: Treatment 5-1 | S1: Treatment 5-2 | T1: Treatment 5-3 | U1: Treatment 5-4 | V1: TOTAL
A2: REVENUE
A3: Bean Revenue (2.5 x 1 m) - WHOLESALE | B3: ='Crop Revenue (2022-2024)'!C11 -> 4.4736202 | C3: ='Crop Revenue (2022-2024)'!D11 -> 13.017646 | D3: ='Crop Revenue (2022-2024)'!E11 -> 26.395831 | E3: ='Crop Revenue (2022-2024)'!F11 -> 20.405496 | F3: ='Crop Revenue (2022-2024)'!G11 -> 18.188798 | G3: ='Crop Revenue (2022-2024)'!H11 -> 18.859351 | H3: ='Crop Revenue (2022-2024)'!I11 -> 15.59243 | I3: ='Crop Revenue (2022-2024)'!J11 -> 31.845603 | ... U3: ='Crop Revenue (2022-2024)'!V11 -> 37.162713 | V3: =SUM(B3:U3) -> 509.88338
A4: Carrot Revenue (2.5 x 1 m) - WHOLESALE | B4: ='Crop Revenue (2022-2024)'!C23 -> 9.6100775 | C4: ='Crop Revenue (2022-2024)'!D23 -> 7.8466722 | D4: ='Crop Revenue (2022-2024)'!E23 -> 8.9377468 | E4: ='Crop Revenue (2022-2024)'!F23 -> 6.6073263 | F4: ='Crop Revenue (2022-2024)'!G23 -> 9.6428127 | G4: ='Crop Revenue (2022-2024)'!H23 -> 6.3544802 | H4: ='Crop Revenue (2022-2024)'!I23 -> 9.213552 | I4: ='Crop Revenue (2022-2024)'!J23 -> 14.976577 | ... U4: ='Crop Revenue (2022-2024)'!V23 -> 19.810179 | V4: =SUM(B4:U4) -> 324.11937
A5: Kale Revenue (2.5 x 1 m) - WHOLESALE | B5: ='Crop Revenue (2022-2024)'!C35 -> 1.6373953 | C5: ='Crop Revenue (2022-2024)'!D35 -> 3.1230519 | D5: ='Crop Revenue (2022-2024)'!E35 -> 6.1782455 | E5: ='Crop Revenue (2022-2024)'!F35 -> 4.5006379 | F5: ='Crop Revenue (2022-2024)'!G35 -> 3.1626359 | G5: ='Crop Revenue (2022-2024)'!H35 -> 2.5808139 | H5: ='Crop Revenue (2022-2024)'!I35 -> 3.3128037 | I5: ='Crop Revenue (2022-2024)'!J35 -> 3.3036931 | ... U5: ='Crop Revenue (2022-2024)'!V35 -> 3.8026786 | V5: =SUM(B5:U5) -> 113.35419
A6: Bean Revenue (2.5 x 1 m) - DIRECT MARKETING | B6: ='Crop Revenue (2022-2024)'!C47 -> 7.6051544 | C6: ='Crop Revenue (2022-2024)'!D47 -> 22.129999 | D6: ='Crop Revenue (2022-2024)'!E47 -> 44.872913 | E6: ='Crop Revenue (2022-2024)'!F47 -> 34.689344 | F6: ='Crop Revenue (2022-2024)'!G47 -> 30.920957 | G6: ='Crop Revenue (2022-2024)'!H47 -> 32.060896 | H6: ='Crop Revenue (2022-2024)'!I47 -> 26.507132 | I6: ='Crop Revenue (2022-2024)'!J47 -> 54.137525 | ... U6: ='Crop Revenue (2022-2024)'!V47 -> 66.892883 | V6: =SUM(B6:U6) -> 902.91221
A7: Carrot Revenue (2.5 x 1 m) - DIRECT MARKETING | B7: ='Crop Revenue (2022-2024)'!C59 -> 16.337132 | C7: ='Crop Revenue (2022-2024)'!D59 -> 13.339343 | D7: ='Crop Revenue (2022-2024)'!E59 -> 15.19417 | E7: ='Crop Revenue (2022-2024)'!F59 -> 11.232455 | F7: ='Crop Revenue (2022-2024)'!G59 -> 16.392782 | G7: ='Crop Revenue (2022-2024)'!H59 -> 10.802616 | H7: ='Crop Revenue (2022-2024)'!I59 -> 15.663038 | I7: ='Crop Revenue (2022-2024)'!J59 -> 25.46018 | ... U7: ='Crop Revenue (2022-2024)'!V59 -> 35.658322 | V7: =SUM(B7:U7) -> 576.09595
A8: Kale Revenue (2.5 x 1 m) - DIRECT MARKETING | B8: ='Crop Revenue (2022-2024)'!C71 -> 2.783572 | C8: ='Crop Revenue (2022-2024)'!D71 -> 5.3091882 | D8: ='Crop Revenue (2022-2024)'!E71 -> 10.503017 | E8: ='Crop Revenue (2022-2024)'!F71 -> 7.6510844 | F8: ='Crop Revenue (2022-2024)'!G71 -> 5.376481 | G8: ='Crop Revenue (2022-2024)'!H71 -> 4.3873837 | H8: ='Crop Revenue (2022-2024)'!I71 -> 5.6317664 | I8: ='Crop Revenue (2022-2024)'!J71 -> 5.6162783 | ... U8: ='Crop Revenue (2022-2024)'!V71 -> 6.8448215 | V8: =SUM(B8:U8) -> 201.25761
A9: Livestock Revenue | B9: 0 | C9: 0 | D9: 0 | E9: 0 | F9: 0 | G9: 0 | H9: 0 | I9: 0 | J9: 0 | K9: 0 | L9: 0 | M9: 0 | N9: 0 | O9: 0 | P9: 0 | Q9: 0 | R9: 0 | S9: 0 | T9: 0 | U9: 0 | V9: =SUM(B9:U9) -> 0
A10: TOTAL REVENUE - WHOLESALE | B10: =SUM(B3:B5,B9) -> 15.721093 | C10: =SUM(C3:C5,C9) -> 23.98737 | D10: =SUM(D3:D5,D9) -> 41.511823 | E10: =SUM(E3:E5,E9) -> 31.513461 | F10: =SUM(F3:F5,F9) -> 30.994247 | G10: =SUM(G3:G5,G9) -> 27.794645 | H10: =SUM(H3:H5,H9) -> 28.118786 | I10: =SUM(I3:I5,I9) -> 50.125873 | ... U10: =SUM(U3:U5,U9) -> 60.77557 | V10: =SUM(B10:U10) -> 947.35694 | X10: =AVERAGE(R10:U10) -> 59.409757
A11: TOTAL REVENUE - DIRECT MARKETING | B11: =SUM(B6:B9) -> 26.725858 | C11: =SUM(C6:C9) -> 40.778529 | D11: =SUM(D6:D9) -> 70.570099 | E11: =SUM(E6:E9) -> 53.572883 | F11: =SUM(F6:F9) -> 52.690219 | G11: =SUM(G6:G9) -> 47.250896 | H11: =SUM(H6:H9) -> 47.801937 | I11: =SUM(I6:I9) -> 85.213984 | ... U11: =SUM(U6:U9) -> 109.39603 | V11: =SUM(B11:U11) -> 1680.2658 | X11: =AVERAGE(R11:U11) -> 106.93756
A12: TOTAL REVENUE - WHOLESALE WITH 33% SORT-OUTS | B12: =(2/3)*B10 -> 10.480729 | C12: =(2/3)*C10 -> 15.99158 | D12: =(2/3)*D10 -> 27.674549 | E12: =(2/3)*E10 -> 21.008974 | F12: =(2/3)*F10 -> 20.662831 | G12: =(2/3)*G10 -> 18.529763 | H12: =(2/3)*H10 -> 18.745857 | I12: =(2/3)*I10 -> 33.417249 | ... U12: =(2/3)*U10 -> 40.517047 | V12: =SUM(B12:U12) -> 631.57129
A13: TOTAL REVENUE - DIRECT MARKETING WITH 20% UNSOLD | B13: =0.8*B11 -> 21.380686 | C13: =0.8*C11 -> 32.622824 | D13: =0.8*D11 -> 56.456079 | E13: =0.8*E11 -> 42.858307 | F13: =0.8*F11 -> 42.152175 | G13: =0.8*G11 -> 37.800717 | H13: =0.8*H11 -> 38.241549 | I13: =0.8*I11 -> 68.171187 | ... U13: =0.8*U11 -> 87.516821 | V13: =SUM(B13:U13) -> 1344.2126
A15: ANNUAL VARIABLE COST
A16: TOTAL LAND PREPARATION COST
A17: Machine Cost - Land Preparation | B17: ='Land Prep Costs (2022-2024)'!$I$12 -> 6.3351562 | C17: ='Land Prep Costs (2022-2024)'!$I$12 -> 6.3351562 | D17: ='Land Prep Costs (2022-2024)'!$I$12 -> 6.3351562 | E17: ='Land Prep Costs (2022-2024)'!$I$12 -> 6.3351562 | F17: ='Land Prep Costs (2022-2024)'!$I$12 -> 6.3351562 | G17: ='Land Prep Costs (2022-2024)'!$I$12 -> 6.3351562 | H17: ='Land Prep Costs (2022-2024)'!$I$12 -> 6.3351562 | I17: ='Land Prep Costs (2022-2024)'!$I$12 -> 6.3351562 | ... Q17: ='Land Prep Costs (2022-2024)'!$I$12 -> 6.3351562 | R17: 0 | S17: 0 | T17: 0 | U17: 0 | V17: =SUM(B17:U17) -> 101.3625 | X17: Questions
A18: Labour Cost - Land Preparation | B18: ='Land Prep Costs (2022-2024)'!$I$35 -> 5.3921875 | C18: ='Land Prep Costs (2022-2024)'!$I$35 -> 5.3921875 | D18: ='Land Prep Costs (2022-2024)'!$I$35 -> 5.3921875 | E18: ='Land Prep Costs (2022-2024)'!$I$35 -> 5.3921875 | F18: ='Land Prep Costs (2022-2024)'!$I$35 -> 5.3921875 | G18: ='Land Prep Costs (2022-2024)'!$I$35 -> 5.3921875 | H18: ='Land Prep Costs (2022-2024)'!$I$35 -> 5.3921875 | I18: ='Land Prep Costs (2022-2024)'!$I$35 -> 5.3921875 | J18: ='Land Prep Costs (2022-2024)'!$I$36 -> 7.6880208 | K18: ='Land Prep Costs (2022-2024)'!$I$36 -> 7.6880208 | L18: ='Land Prep Costs (2022-2024)'!$I$36 -> 7.6880208 | M18: ='Land Prep Costs (2022-2024)'!$I$36 -> 7.6880208 | N18: ='Land Prep Costs (2022-2024)'!$I$37 -> 8.7755208 | O18: ='Land Prep Costs (2022-2024)'!$I$37 -> 8.7755208 | P18: ='Land Prep Costs (2022-2024)'!$I$37 -> 8.7755208 | Q18: ='Land Prep Costs (2022-2024)'!$I$37 -> 8.7755208 | R18: ='Land Prep Costs (2022-2024)'!$I$38 -> 14.892708 | S18: ='Land Prep Costs (2022-2024)'!$I$38 -> 14.892708 | T18: ='Land Prep Costs (2022-2024)'!$I$38 -> 14.892708 | U18: ='Land Prep Costs (2022-2024)'!$I$38 -> 14.892708 | V18: =SUM(B18:U18) -> 168.5625 | X18: 1. What about weed whacking and mower use? Also for carrying crops
A19: Fuel | B19: ='Costs (2022-2024)'!$I$16 -> 1 | C19: ='Costs (2022-2024)'!$I$16 -> 1 | D19: ='Costs (2022-2024)'!$I$16 -> 1 | E19: ='Costs (2022-2024)'!$I$16 -> 1 | F19: ='Costs (2022-2024)'!$I$16 -> 1 | G19: ='Costs (2022-2024)'!$I$16 -> 1 | H19: ='Costs (2022-2024)'!$I$16 -> 1 | I19: ='Costs (2022-2024)'!$I$16 -> 1 | ... U19: ='Costs (2022-2024)'!$I$16 -> 1 | V19: =SUM(B19:U19) -> 20 | X19: 2. How do I quantify sheep revenue?
A20: TOTAL FERTILITY & NUTRIENT COST | X20: 3. What about fuel costs?
A21: Inorganic Fertilizer | B21: ='Costs (2022-2024)'!$I$11 -> 1.67875 | C21: ='Costs (2022-2024)'!$I$11 -> 1.67875 | D21: ='Costs (2022-2024)'!$I$11 -> 1.67875 | E21: ='Costs (2022-2024)'!$I$11 -> 1.67875 | F21: ='Costs (2022-2024)'!$I$11 -> 1.67875 | G21: ='Costs (2022-2024)'!$I$11 -> 1.67875 | H21: ='Costs (2022-2024)'!$I$11 -> 1.67875 | I21: ='Costs (2022-2024)'!$I$11 -> 1.67875 | J21: 0 | K21: 0 | L21: 0 | M21: 0 | N21: 0 | O21: 0 | P21: 0 | Q21: 0 | R21: 0 | S21: 0 | T21: 0 | U21: 0 | V21: =SUM(B21:U21) -> 13.43 | X21: 4. What about post-harvest?
A22: Compost | B22: 0 | C22: 0 | D22: 0 | E22: 0 | F22: 0 | G22: 0 | H22: 0 | I22: 0 | J22: ='Costs (2022-2024)'!$I$14 -> 25.75 | K22: ='Costs (2022-2024)'!$I$14 -> 25.75 | L22: ='Costs (2022-2024)'!$I$14 -> 25.75 | M22: ='Costs (2022-2024)'!$I$14 -> 25.75 | N22: ='Costs (2022-2024)'!$I$14 -> 25.75 | O22: ='Costs (2022-2024)'!$I$14 -> 25.75 | P22: ='Costs (2022-2024)'!$I$14 -> 25.75 | Q22: ='Costs (2022-2024)'!$I$14 -> 25.75 | ... U22: ='Costs (2022-2024)'!$I$14 -> 25.75 | V22: =SUM(B22:U22) -> 309
A23: TOTAL SEED COST
A24: Cover Crop Seeds | B24: 0 | C24: 0 | D24: 0 | E24: 0 | F24: ='Costs (2022-2024)'!$I$8 -> 2.4 | G24: ='Costs (2022-2024)'!$I$8 -> 2.4 | H24: ='Costs (2022-2024)'!$I$8 -> 2.4 | I24: ='Costs (2022-2024)'!$I$8 -> 2.4 | J24: ='Costs (2022-2024)'!$I$8 -> 2.4 | K24: ='Costs (2022-2024)'!$I$8 -> 2.4 | L24: ='Costs (2022-2024)'!$I$8 -> 2.4 | M24: ='Costs (2022-2024)'!$I$8 -> 2.4 | ... U24: ='Costs (2022-2024)'!$I$8 -> 2.4 | V24: =SUM(B24:U24) -> 38.4
A25: TOTAL PLANTING COST
A26: Labour Cost - Planting | B26: ='Labour Costs (2022-2024)'!C8 -> 0 | C26: ='Labour Costs (2022-2024)'!D8 -> 0 | D26: ='Labour Costs (2022-2024)'!E8 -> 0 | E26: ='Labour Costs (2022-2024)'!F8 -> 0 | F26: ='Labour Costs (2022-2024)'!G8 -> 0.435 | G26: ='Labour Costs (2022-2024)'!H8 -> 0.435 | H26: ='Labour Costs (2022-2024)'!I8 -> 0.435 | I26: ='Labour Costs (2022-2024)'!J8 -> 0.435 | ... U26: ='Labour Costs (2022-2024)'!V8 -> 0.435 | V26: =SUM(B26:U26) -> 6.96
A27: TOTAL WEEDING & PEST MANAGEMENT COST
A28: Labour Cost - Weeding | B28: ='Labour Costs (2022-2024)'!C15 -> 65.9025 | C28: ='Labour Costs (2022-2024)'!D15 -> 44.95 | D28: ='Labour Costs (2022-2024)'!E15 -> 41.8325 | E28: ='Labour Costs (2022-2024)'!F15 -> 55.4625 | F28: ='Labour Costs (2022-2024)'!G15 -> 44.2975 | G28: ='Labour Costs (2022-2024)'!H15 -> 39.295 | H28: ='Labour Costs (2022-2024)'!I15 -> 45.7475 | I28: ='Labour Costs (2022-2024)'!J15 -> 45.1675 | ... U28: ='Labour Costs (2022-2024)'!V15 -> 32.915 | V28: =SUM(B28:U28) -> 944.2835
A29: TOTAL HARVEST COST
A30: Labour Cost - Bean Harvest | B30: ='Labour Costs (2022-2024)'!C32 -> 5.51 | C30: ='Labour Costs (2022-2024)'!D32 -> 9.425 | D30: ='Labour Costs (2022-2024)'!E32 -> 15.4425 | E30: ='Labour Costs (2022-2024)'!F32 -> 14.471 | F30: ='Labour Costs (2022-2024)'!G32 -> 11.0925 | G30: ='Labour Costs (2022-2024)'!H32 -> 12.47 | H30: ='Labour Costs (2022-2024)'!I32 -> 11.02 | I30: ='Labour Costs (2022-2024)'!J32 -> 19.575 | ... U30: ='Labour Costs (2022-2024)'!V32 -> 17.11 | V30: =SUM(B30:U30) -> 264.886 | AJ30: ='Crop Prices (2022-2024)'!I15/'Crop Prices (2022-2024)'!D15 -> 3.27
A31: Labour Cost - Carrot Harvest | B31: ='Labour Costs (2022-2024)'!C33 -> 7.6125 | C31: ='Labour Costs (2022-2024)'!D33 -> 9.135 | D31: ='Labour Costs (2022-2024)'!E33 -> 7.83 | E31: ='Labour Costs (2022-2024)'!F33 -> 6.3075 | F31: ='Labour Costs (2022-2024)'!G33 -> 8.0475 | G31: ='Labour Costs (2022-2024)'!H33 -> 4.785 | H31: ='Labour Costs (2022-2024)'!I33 -> 6.96 | I31: ='Labour Costs (2022-2024)'!J33 -> 9.135 | ... U31: ='Labour Costs (2022-2024)'!V33 -> 2.03 | V31: =SUM(B31:U31) -> 101.5725
A32: Labour Cost - Kale Harvest | B32: ='Labour Costs (2022-2024)'!C34 -> 7.105 | C32: ='Labour Costs (2022-2024)'!D34 -> 7.1775 | D32: ='Labour Costs (2022-2024)'!E34 -> 8.1925 | E32: ='Labour Costs (2022-2024)'!F34 -> 7.685 | F32: ='Labour Costs (2022-2024)'!G34 -> 7.3225 | G32: ='Labour Costs (2022-2024)'!H34 -> 6.09 | H32: ='Labour Costs (2022-2024)'!I34 -> 6.96 | I32: ='Labour Costs (2022-2024)'!J34 -> 5.8725 | ... U32: ='Labour Costs (2022-2024)'!V34 -> 6.3075 | V32: =SUM(B32:U32) -> 141.665
A33: TOTAL LIVESTOCK COST
A34: Labour Cost - Livestock Management | B34: ='Labour Costs (2022-2024)'!C41 -> 0 | C34: ='Labour Costs (2022-2024)'!D41 -> 0 | D34: ='Labour Costs (2022-2024)'!E41 -> 0 | E34: ='Labour Costs (2022-2024)'!F41 -> 0 | F34: ='Labour Costs (2022-2024)'!G41 -> 0 | G34: ='Labour Costs (2022-2024)'!H41 -> 0 | H34: ='Labour Costs (2022-2024)'!I41 -> 0 | I34: ='Labour Costs (2022-2024)'!J41 -> 0 | ... U34: ='Labour Costs (2022-2024)'!V41 -> 10.875 | V34: =SUM(B34:U34) -> 87
A35: Equipment - Livestock | B35: 0 | C35: 0 | D35: 0 | E35: 0 | F35: 0 | G35: 0 | H35: 0 | I35: 0 | J35: 0 | K35: 0 | L35: 0 | M35: 0 | N35: 0 | O35: 0 | P35: 0 | Q35: 0 | R35: 0 | S35: 0 | T35: 0 | U35: 0 | V35: =SUM(B35:U35) -> 0
A36: Livestock Cost | B36: 0 | C36: 0 | D36: 0 | E36: 0 | F36: 0 | G36: 0 | H36: 0 | I36: 0 | J36: 0 | K36: 0 | L36: 0 | M36: 0 | N36: 0 | O36: 0 | P36: 0 | Q36: 0 | R36: 0 | S36: 0 | T36: 0 | U36: 0 | V36: =SUM(B36:U36) -> 0
A37: TOTAL MARKETING COST
A38: Associated Marketing Costs - Wholesale (25% of Total Revenue) | B38: =B10*0.25 -> 3.9302732 | C38: =C10*0.25 -> 5.9968426 | D38: =D10*0.25 -> 10.377956 | E38: =E10*0.25 -> 7.8783652 | F38: =F10*0.25 -> 7.7485616 | G38: =G10*0.25 -> 6.9486612 | H38: =H10*0.25 -> 7.0296966 | I38: =I10*0.25 -> 12.531468 | ... U38: =U10*0.25 -> 15.193893 | V38: =SUM(B38:U38) -> 236.83923
A39: Associated Marketing Costs - Direct Marketing (35% of Total Revenue) | B39: =B11*0.35 -> 9.3540503 | C39: =C11*0.35 -> 14.272485 | D39: =D11*0.35 -> 24.699535 | E39: =E11*0.35 -> 18.750509 | F39: =F11*0.35 -> 18.441577 | G39: =G11*0.35 -> 16.537814 | H39: =H11*0.35 -> 16.730678 | I39: =I11*0.35 -> 29.824894 | ... U39: =U11*0.35 -> 38.288609 | V39: =SUM(B39:U39) -> 588.09302
A40: TOTAL INPUT COST | B40: =SUM(B21, B22,B24) -> 1.67875 | C40: =SUM(C21, C22,C24) -> 1.67875 | D40: =SUM(D21, D22,D24) -> 1.67875 | E40: =SUM(E21, E22,E24) -> 1.67875 | F40: =SUM(F21, F22,F24) -> 4.07875 | G40: =SUM(G21, G22,G24) -> 4.07875 | H40: =SUM(H21, H22,H24) -> 4.07875 | I40: =SUM(I21, I22,I24) -> 4.07875 | ... U40: =SUM(U21, U22,U24) -> 28.15 | V40: =SUM(B40:U40) -> 360.83
A41: TOTAL ANNUAL LABOUR COST - WHOLESALE | B41: =SUM(B18+B26+B28+B30+B31+B32+B34) -> 91.522188 | C41: =SUM(C18+C26+C28+C30+C31+C32+C34) -> 76.079687 | D41: =SUM(D18+D26+D28+D30+D31+D32+D34) -> 78.689687 | E41: =SUM(E18+E26+E28+E30+E31+E32+E34) -> 89.318188 | F41: =SUM(F18+F26+F28+F30+F31+F32+F34) -> 76.587188 | G41: =SUM(G18+G26+G28+G30+G31+G32+G34) -> 68.467187 | H41: =SUM(H18+H26+H28+H30+H31+H32+H34) -> 76.514687 | I41: =SUM(I18+I26+I28+I30+I31+I32+I34) -> 85.577188 | ... U41: =SUM(U18+U26+U28+U30+U31+U32+U34) -> 84.565208 | V41: =SUM(B41:U41) -> 1714.9295 | W41: Interesting - this number increased as I worked with a RA for most of the season
A42: TOTAL ANNUAL LABOUR COST - DIRECT MARKETING | B42: =SUM(B18+B26+B28+B30+B31+B32+B34) -> 91.522188 | C42: =SUM(C18+C26+C28+C30+C31+C32+C34) -> 76.079687 | D42: =SUM(D18+D26+D28+D30+D31+D32+D34) -> 78.689687 | E42: =SUM(E18+E26+E28+E30+E31+E32+E34) -> 89.318188 | F42: =SUM(F18+F26+F28+F30+F31+F32+F34) -> 76.587188 | G42: =SUM(G18+G26+G28+G30+G31+G32+G34) -> 68.467187 | H42: =SUM(H18+H26+H28+H30+H31+H32+H34) -> 76.514687 | I42: =SUM(I18+I26+I28+I30+I31+I32+I34) -> 85.577188 | ... U42: =SUM(U18+U26+U28+U30+U31+U32+U34) -> 84.565208 | V42: =SUM(B42:U42) -> 1714.9295
A43: TOTAL ANNUAL VARIABLE COST - WHOLESALE | B43: =SUM(B17:B36,B38) -> 104.46637 | C43: =SUM(C17:C36,C38) -> 91.090436 | D43: =SUM(D17:D36,D38) -> 98.08155 | E43: =SUM(E17:E36,E38) -> 106.21046 | F43: =SUM(F17:F36,F38) -> 95.749655 | G43: =SUM(G17:G36,G38) -> 86.829755 | H43: =SUM(H17:H36,H38) -> 94.95829 | I43: =SUM(I17:I36,I38) -> 109.52256 | ... U43: =SUM(U17:U36,U38) -> 128.9091 | V43: =SUM(B43:U43) -> 2433.9612
A44: TOTAL ANNUAL VARIABLE COST - DIRECT MARKETING | B44: =SUM(B17:B36,B39) -> 109.89014 | C44: =SUM(C17:C36,C39) -> 99.366079 | D44: =SUM(D17:D36,D39) -> 112.40313 | E44: =SUM(E17:E36,E39) -> 117.0826 | F44: =SUM(F17:F36,F39) -> 106.44267 | G44: =SUM(G17:G36,G39) -> 96.418907 | H44: =SUM(H17:H36,H39) -> 104.65927 | I44: =SUM(I17:I36,I39) -> 126.81599 | ... U44: =SUM(U17:U36,U39) -> 152.00382 | V44: =SUM(B44:U44) -> 2785.215
A46: NET RETURNS
A47: RETURNS OVER VARIABLE COST - WHOLESALE | B47: =B10-B43 -> -88.745274 | C47: =C10-C43 -> -67.103066 | D47: =D10-D43 -> -56.569726 | E47: =E10-E43 -> -74.696998 | F47: =F10-F43 -> -64.755409 | G47: =G10-G43 -> -59.03511 | H47: =H10-H43 -> -66.839504 | I47: =I10-I43 -> -59.396689 | ... U47: =U10-U43 -> -68.133531 | V47: =AVERAGE(B47:U47) -> -74.330215
A48: RETURNS OVER VARIABLE COST - DIRECT MARKETING | B48: =B11-B44 -> -83.164286 | C48: =C11-C44 -> -58.58755 | D48: =D11-D44 -> -41.833029 | E48: =E11-E44 -> -63.50972 | F48: =F11-F44 -> -53.752451 | G48: =G11-G44 -> -49.168011 | H48: =H11-H44 -> -56.857335 | I48: =I11-I44 -> -41.602004 | ... U48: =U11-U44 -> -42.607791 | V48: =AVERAGE(B48:U48) -> -55.247463
A49: RETURNS OVER VARIABLE COST - WHOLESALE WITH 33% SORT OUTS | B49: =B12-B43 -> -93.985638 | C49: =C12-C43 -> -75.098856 | D49: =D12-D43 -> -70.407001 | E49: =E12-E43 -> -85.201485 | F49: =F12-F43 -> -75.086824 | G49: =G12-G43 -> -68.299992 | H49: =H12-H43 -> -76.212433 | I49: =I12-I43 -> -76.105313 | ... U49: =U12-U43 -> -88.392054 | V49: =AVERAGE(B49:U49) -> -90.119497
A50: RETURNS OVER VARIABLE COST - DIRECT MARKETING WITH 20% UNSOLD | B50: =B13-B44 -> -88.509458 | C50: =C13-C44 -> -66.743256 | D50: =D13-D44 -> -55.947049 | E50: =E13-E44 -> -74.224296 | F50: =F13-F44 -> -64.290495 | G50: =G13-G44 -> -58.618191 | H50: =H13-H44 -> -66.417722 | I50: =I13-I44 -> -58.644801 | ... U50: =U13-U44 -> -64.486996 | V50: =AVERAGE(B50:U50) -> -72.05012
B52: =B41/B10 -> 5.8216173 | C52: =C41/C10 -> 3.171656 | D52: =D41/D10 -> 1.895597 | E52: =E41/E10 -> 2.8342869
D54: =AVERAGE(B52:E52) -> 3.4307893

Sheet Crop Revenue (2022-2024)
C1: Treatment 1-1 | D1: Treatment 1-2 | E1: Treatment 1-3 | F1: Treatment 1-4 | G1: Treatment 2-1 | H1: Treatment 2-2 | I1: Treatment 2-3 | J1: Treatment 2-4 | K1: Treatment 3-1 | L1: Treatment 3-2 | M1: Treatment 3-3 | N1: Treatment 3-4 | O1: Treatment 4-1 | P1: Treatment 4-2 | Q1: Treatment 4-3 | R1: Treatment 4-4 | S1: Treatment 5-1 | T1: Treatment 5-2 | U1: Treatment 5-3 | V1: Treatment 5-4
A2: Year | B2: BEANS - WHOLESALE
A3: 2022 | B3: Bean Harvest Yield (g) | C3: 3247.3 | D3: 3715.1 | E3: 3278.9 | F3: 3817.4 | G3: 2610.8 | H3: 2854.6 | I3: 2594.8 | J3: 3891.4 | K3: 2536.2 | L3: 2176 | M3: 4021.8 | N3: 3052.1 | O3: 3237.7 | P3: 1689 | Q3: 2599.9 | R3: 1565 | S3: 1553.8 | T3: 3377.8 | U3: 1437.6 | V3: 3500.6 | X3: =C3*(4046.86/2.5)/1000 -> 5256.5474 | Y3: =C3*1.618744 -> 5256.5474
A4: 2022 | B4: Bean Wholesale Price ($/g) | C4: ='Crop Prices (2022-2024)'!J3 -> 0.0045029417 | D4: ='Crop Prices (2022-2024)'!J3 -> 0.0045029417 | E4: ='Crop Prices (2022-2024)'!J3 -> 0.0045029417 | F4: ='Crop Prices (2022-2024)'!J3 -> 0.0045029417 | G4: ='Crop Prices (2022-2024)'!J3 -> 0.0045029417 | H4: ='Crop Prices (2022-2024)'!J3 -> 0.0045029417 | I4: ='Crop Prices (2022-2024)'!J3 -> 0.0045029417 | J4: ='Crop Prices (2022-2024)'!J3 -> 0.0045029417 | K4: ='Crop Prices (2022-2024)'!J15 -> 0.007209116 | L4: ='Crop Prices (2022-2024)'!J15 -> 0.007209116 | M4: ='Crop Prices (2022-2024)'!J15 -> 0.007209116 | N4: ='Crop Prices (2022-2024)'!J15 -> 0.007209116 | O4: ='Crop Prices (2022-2024)'!J15 -> 0.007209116 | P4: ='Crop Prices (2022-2024)'!J15 -> 0.007209116 | Q4: ='Crop Prices (2022-2024)'!J15 -> 0.007209116 | R4: ='Crop Prices (2022-2024)'!J15 -> 0.007209116 | S4: ='Crop Prices (2022-2024)'!J15 -> 0.007209116 | T4: ='Crop Prices (2022-2024)'!J15 -> 0.007209116 | U4: ='Crop Prices (2022-2024)'!J15 -> 0.007209116 | V4: ='Crop Prices (2022-2024)'!J15 -> 0.007209116
A5: 2022 | B5: Bean Revenue ($) | C5: =C3*C4 -> 14.622403 | D5: =D3*D4 -> 16.728879 | E5: =E3*E4 -> 14.764696 | F5: =F3*F4 -> 17.18953 | G5: =G3*G4 -> 11.75628 | H5: =H3*H4 -> 12.854097 | I5: =I3*I4 -> 11.684233 | J5: =J3*J4 -> 17.522747 | ... V5: =V3*V4 -> 25.236231
A6: 2023 | B6: Bean Harvest Yield (g) | C6: 4597.3 | D6: 5548.2 | E6: 7776.3 | F6: 4944.4 | G6: 4342.5 | H6: 7257.3 | I6: 6263.2 | J6: 6946.6 | K6: 4710.9 | L6: 4455.5 | M6: 6886.8 | N6: 5338.5 | O6: 7562.5 | P6: 5322.6 | Q6: 6259 | R6: 5300.6 | S6: 5099.8 | T6: 5608.4 | U6: 6142.9 | V6: 7099.5
A7: 2023 | B7: Bean Wholesale Price ($/g) | C7: ='Crop Prices (2022-2024)'!J4 -> 0.0047674964 | D7: ='Crop Prices (2022-2024)'!J4 -> 0.0047674964 | E7: ='Crop Prices (2022-2024)'!J4 -> 0.0047674964 | F7: ='Crop Prices (2022-2024)'!J4 -> 0.0047674964 | G7: ='Crop Prices (2022-2024)'!J4 -> 0.0047674964 | H7: ='Crop Prices (2022-2024)'!J4 -> 0.0047674964 | I7: ='Crop Prices (2022-2024)'!J4 -> 0.0047674964 | J7: ='Crop Prices (2022-2024)'!J4 -> 0.0047674964 | K7: ='Crop Prices (2022-2024)'!J16 -> 0.0078815259 | L7: ='Crop Prices (2022-2024)'!J16 -> 0.0078815259 | M7: ='Crop Prices (2022-2024)'!J16 -> 0.0078815259 | N7: ='Crop Prices (2022-2024)'!J16 -> 0.0078815259 | O7: ='Crop Prices (2022-2024)'!J16 -> 0.0078815259 | P7: ='Crop Prices (2022-2024)'!J16 -> 0.0078815259 | Q7: ='Crop Prices (2022-2024)'!J16 -> 0.0078815259 | R7: ='Crop Prices (2022-2024)'!J16 -> 0.0078815259 | S7: ='Crop Prices (2022-2024)'!J16 -> 0.0078815259 | T7: ='Crop Prices (2022-2024)'!J16 -> 0.0078815259 | U7: ='Crop Prices (2022-2024)'!J16 -> 0.0078815259 | V7: ='Crop Prices (2022-2024)'!J16 -> 0.0078815259
A8: 2023 | B8: Bean Revenue ($) | C8: =C6*C7 -> 21.917611 | D8: =D6*D7 -> 26.451024 | E8: =E6*E7 -> 37.073482 | F8: =F6*F7 -> 23.572409 | G8: =G6*G7 -> 20.702853 | H8: =H6*H7 -> 34.599152 | I8: =I6*I7 -> 29.859784 | J8: =J6*J7 -> 33.117891 | ... V8: =V6*V7 -> 55.954893
A9: 2024 | B9: Bean Harvest Yield (g) | C9: 912 | D9: 2653.8 | E9: 5381.1 | F9: 4159.9 | G9: 3708 | H9: 3844.7 | I9: 3178.7 | J9: 6492.1 | K9: 1802.8 | L9: 2525 | M9: 5394.5 | N9: 5439.1 | O9: 5200.8 | P9: 3831.4 | Q9: 5913.1 | R9: 6022.8 | S9: 3564.5 | T9: 5283.4 | U9: 4165.6 | V9: 5637.7
A10: 2024 | B10: Bean Wholesale Price ($/g) | C10: ='Crop Prices (2022-2024)'!J5 -> 0.0049052853 | D10: ='Crop Prices (2022-2024)'!J5 -> 0.0049052853 | E10: ='Crop Prices (2022-2024)'!J5 -> 0.0049052853 | F10: ='Crop Prices (2022-2024)'!J5 -> 0.0049052853 | G10: ='Crop Prices (2022-2024)'!J5 -> 0.0049052853 | H10: ='Crop Prices (2022-2024)'!J5 -> 0.0049052853 | I10: ='Crop Prices (2022-2024)'!J5 -> 0.0049052853 | J10: ='Crop Prices (2022-2024)'!J5 -> 0.0049052853 | K10: ='Crop Prices (2022-2024)'!J17 -> 0.0065918216 | L10: ='Crop Prices (2022-2024)'!J17 -> 0.0065918216 | M10: ='Crop Prices (2022-2024)'!J17 -> 0.0065918216 | N10: ='Crop Prices (2022-2024)'!J17 -> 0.0065918216 | O10: ='Crop Prices (2022-2024)'!J17 -> 0.0065918216 | P10: ='Crop Prices (2022-2024)'!J17 -> 0.0065918216 | Q10: ='Crop Prices (2022-2024)'!J17 -> 0.0065918216 | R10: ='Crop Prices (2022-2024)'!J17 -> 0.0065918216 | S10: ='Crop Prices (2022-2024)'!J17 -> 0.0065918216 | T10: ='Crop Prices (2022-2024)'!J17 -> 0.0065918216 | U10: ='Crop Prices (2022-2024)'!J17 -> 0.0065918216 | V10: ='Crop Prices (2022-2024)'!J17 -> 0.0065918216
A11: 2024 | B11: Bean Revenue ($) | C11: =C9*C10 -> 4.4736202 | D11: =D9*D10 -> 13.017646 | E11: =E9*E10 -> 26.395831 | F11: =F9*F10 -> 20.405496 | G11: =G9*G10 -> 18.188798 | H11: =H9*H10 -> 18.859351 | I11: =I9*I10 -> 15.59243 | J11: =J9*J10 -> 31.845603 | ... V11: =V9*V10 -> 37.162713
B12: BEANS TOTAL | C12: =C5+C8+C11 -> 41.013634 | D12: =D5+D8+D11 -> 56.197549 | E12: =E5+E8+E11 -> 78.234009 | F12: =F5+F8+F11 -> 61.167435 | G12: =G5+G8+G11 -> 50.647931 | H12: =H5+H8+H11 -> 66.3126 | I12: =I5+I8+I11 -> 57.136447 | J12: =J5+J8+J11 -> 82.486241 | ... V12: =V5+V8+V11 -> 118.35384
A14: Year | B14: CARROTS - WHOLESALE
A15: 2022 | B15: Carrot Harvest Yield (g) | C15: 1689.2 | D15: 4814.5 | E15: 1862.1 | F15: 4125.3 | G15: 3185.6 | H15: 2558.5 | I15: 4424.3 | J15: 2473.9 | K15: 1919.2 | L15: 2085.2 | M15: 3142.1 | N15: 1884.5 | O15: 2724.2 | P15: 2435.9 | Q15: 2611.2 | R15: 1262 | S15: 1445.7 | T15: 2696.2 | U15: 1995.2 | V15: 3023.3
A16: 2022 | B16: Carrot Wholesale Price ($/g) | C16: ='Crop Prices (2022-2024)'!$J$6 -> 0.0017802328 | D16: ='Crop Prices (2022-2024)'!$J$6 -> 0.0017802328 | E16: ='Crop Prices (2022-2024)'!$J$6 -> 0.0017802328 | F16: ='Crop Prices (2022-2024)'!$J$6 -> 0.0017802328 | G16: ='Crop Prices (2022-2024)'!$J$6 -> 0.0017802328 | H16: ='Crop Prices (2022-2024)'!$J$6 -> 0.0017802328 | I16: ='Crop Prices (2022-2024)'!$J$6 -> 0.0017802328 | J16: ='Crop Prices (2022-2024)'!$J$6 -> 0.0017802328 | K16: ='Crop Prices (2022-2024)'!$J$18 -> 0.0045944335 | L16: ='Crop Prices (2022-2024)'!$J$18 -> 0.0045944335 | M16: ='Crop Prices (2022-2024)'!$J$18 -> 0.0045944335 | N16: ='Crop Prices (2022-2024)'!$J$18 -> 0.0045944335 | O16: ='Crop Prices (2022-2024)'!$J$18 -> 0.0045944335 | P16: ='Crop Prices (2022-2024)'!$J$18 -> 0.0045944335 | Q16: ='Crop Prices (2022-2024)'!$J$18 -> 0.0045944335 | R16: ='Crop Prices (2022-2024)'!$J$18 -> 0.0045944335 | ... V16: ='Crop Prices (2022-2024)'!$J$18 -> 0.0045944335
A17: 2022 | B17: Carrot Revenue ($) | C17: =C15*C16 -> 3.0071692 | D17: =D15*D16 -> 8.5709307 | E17: =E15*E16 -> 3.3149714 | F17: =F15*F16 -> 7.3439942 | G17: =G15*G16 -> 5.6711095 | H17: =H15*H16 -> 4.5547255 | I17: =I15*I16 -> 7.8762838 | J17: =J15*J16 -> 4.4041178 | ... V17: =V15*V16 -> 13.890351
A18: 2023 | B18: Carrot Harvest Yield (g) | C18: 3881.2 | D18: 6626.2 | E18: 7038.2 | F18: 5829.2 | G18: 6182.4 | H18: 4988.9 | I18: 4164 | J18: 6127.5 | K18: 5154.3 | L18: 3988.8 | M18: 7913 | N18: 6661.4 | O18: 5642.2 | P18: 4229 | Q18: 7467.5 | R18: 6915.1 | S18: 5475.3 | T18: 5296.8 | U18: 5344.3 | V18: 4564.2
A19: 2023 | B19: Carrot Wholesale Price ($/g) | C19: ='Crop Prices (2022-2024)'!$J$7 -> 0.0020491967 | D19: ='Crop Prices (2022-2024)'!$J$7 -> 0.0020491967 | E19: ='Crop Prices (2022-2024)'!$J$7 -> 0.0020491967 | F19: ='Crop Prices (2022-2024)'!$J$7 -> 0.0020491967 | G19: ='Crop Prices (2022-2024)'!$J$7 -> 0.0020491967 | H19: ='Crop Prices (2022-2024)'!$J$7 -> 0.0020491967 | I19: ='Crop Prices (2022-2024)'!$J$7 -> 0.0020491967 | J19: ='Crop Prices (2022-2024)'!$J$7 -> 0.0020491967 | K19: ='Crop Prices (2022-2024)'!$J$19 -> 0.0051852724 | L19: ='Crop Prices (2022-2024)'!$J$19 -> 0.0051852724 | M19: ='Crop Prices (2022-2024)'!$J$19 -> 0.0051852724 | N19: ='Crop Prices (2022-2024)'!$J$19 -> 0.0051852724 | O19: ='Crop Prices (2022-2024)'!$J$19 -> 0.0051852724 | P19: ='Crop Prices (2022-2024)'!$J$19 -> 0.0051852724 | Q19: ='Crop Prices (2022-2024)'!$J$19 -> 0.0051852724 | R19: ='Crop Prices (2022-2024)'!$J$19 -> 0.0051852724 | ... V19: ='Crop Prices (2022-2024)'!$J$19 -> 0.0051852724
A20: 2023 | B20: Carrot Revenue ($) | C20: =C18*C19 -> 7.9533423 | D20: =D18*D19 -> 13.578387 | E20: =E18*E19 -> 14.422656 | F20: =F18*F19 -> 11.945178 | G20: =G18*G19 -> 12.668954 | H20: =H18*H19 -> 10.223238 | I20: =I18*I19 -> 8.5328552 | J20: =J18*J19 -> 12.556453 | ... V20: =V18*V19 -> 23.66662
A21: 2024 | B21: Carrot Harvest Yield (g) | C21: 6487.9 | D21: 5297.4 | E21: 6034 | F21: 4460.7 | G21: 6510 | H21: 4290 | I21: 6220.2 | J21: 10110.9 | K21: 5757.4 | L21: 2891.7 | M21: 1942.5 | N21: 6867.5 | O21: 2142.5 | P21: 749.1 | Q21: 3494.9 | R21: 6069.5 | S21: 3765.3 | T21: 6629.2 | U21: 4799.8 | V21: 3866.5
A22: 2024 | B22: Carrot Wholesale Price ($/g) | C22: ='Crop Prices (2022-2024)'!$J$8 -> 0.0014812308 | D22: ='Crop Prices (2022-2024)'!$J$8 -> 0.0014812308 | E22: ='Crop Prices (2022-2024)'!$J$8 -> 0.0014812308 | F22: ='Crop Prices (2022-2024)'!$J$8 -> 0.0014812308 | G22: ='Crop Prices (2022-2024)'!$J$8 -> 0.0014812308 | H22: ='Crop Prices (2022-2024)'!$J$8 -> 0.0014812308 | I22: ='Crop Prices (2022-2024)'!$J$8 -> 0.0014812308 | J22: ='Crop Prices (2022-2024)'!$J$8 -> 0.0014812308 | K22: ='Crop Prices (2022-2024)'!$J$20 -> 0.005123543 | L22: ='Crop Prices (2022-2024)'!$J$20 -> 0.005123543 | M22: ='Crop Prices (2022-2024)'!$J$20 -> 0.005123543 | N22: ='Crop Prices (2022-2024)'!$J$20 -> 0.005123543 | O22: ='Crop Prices (2022-2024)'!$J$20 -> 0.005123543 | P22: ='Crop Prices (2022-2024)'!$J$20 -> 0.005123543 | Q22: ='Crop Prices (2022-2024)'!$J$20 -> 0.005123543 | R22: ='Crop Prices (2022-2024)'!$J$20 -> 0.005123543 | ... V22: ='Crop Prices (2022-2024)'!$J$20 -> 0.005123543
A23: 2024 | B23: Carrot Revenue ($) | C23: =C21*C22 -> 9.6100775 | D23: =D21*D22 -> 7.8466722 | E23: =E21*E22 -> 8.9377468 | F23: =F21*F22 -> 6.6073263 | G23: =G21*G22 -> 9.6428127 | H23: =H21*H22 -> 6.3544802 | I23: =I21*I22 -> 9.213552 | J23: =J21*J22 -> 14.976577 | ... V23: =V21*V22 -> 19.810179
B24: CARROTS TOTAL | C24: =C17+C20+C23 -> 20.570589 | D24: =D17+D20+D23 -> 29.99599 | E24: =E17+E20+E23 -> 26.675375 | F24: =F17+F20+F23 -> 25.896498 | G24: =G17+G20+G23 -> 27.982876 | H24: =H17+H20+H23 -> 21.132443 | I24: =I17+I20+I23 -> 25.622691 | J24: =J17+J20+J23 -> 31.937148 | ... V24: =V17+V20+V23 -> 57.36715
A26: Year | B26: KALE
A27: 2022 | B27: Kale Harvest Yield (g) | C27: 30.2 | D27: 49.8 | E27: 48.5 | F27: 56.7 | G27: 62.5 | H27: 25.5 | I27: 54.2 | J27: 30.4 | K27: 42.1 | L27: 38.2 | M27: 58.1 | N27: 58.2 | O27: 47.8 | P27: 36.4 | Q27: 58.9 | R27: 48.2 | S27: 79.8 | T27: 51.5 | U27: 58 | V27: 73.4
A28: 2022 | B28: Kale Wholesale Price ($/g) | C28: ='Crop Prices (2022-2024)'!J9 -> 0.0029597059 | D28: ='Crop Prices (2022-2024)'!J9 -> 0.0029597059 | E28: ='Crop Prices (2022-2024)'!J9 -> 0.0029597059 | F28: ='Crop Prices (2022-2024)'!J9 -> 0.0029597059 | G28: ='Crop Prices (2022-2024)'!J9 -> 0.0029597059 | H28: ='Crop Prices (2022-2024)'!J9 -> 0.0029597059 | I28: ='Crop Prices (2022-2024)'!J9 -> 0.0029597059 | J28: ='Crop Prices (2022-2024)'!J9 -> 0.0029597059 | K28: ='Crop Prices (2022-2024)'!J21 -> 0.0070768386 | L28: ='Crop Prices (2022-2024)'!J21 -> 0.0070768386 | M28: ='Crop Prices (2022-2024)'!J21 -> 0.0070768386 | N28: ='Crop Prices (2022-2024)'!J21 -> 0.0070768386 | O28: ='Crop Prices (2022-2024)'!J21 -> 0.0070768386 | P28: ='Crop Prices (2022-2024)'!J21 -> 0.0070768386 | Q28: ='Crop Prices (2022-2024)'!J21 -> 0.0070768386 | R28: ='Crop Prices (2022-2024)'!J21 -> 0.0070768386 | S28: ='Crop Prices (2022-2024)'!J21 -> 0.0070768386 | T28: ='Crop Prices (2022-2024)'!J21 -> 0.0070768386 | U28: ='Crop Prices (2022-2024)'!J21 -> 0.0070768386 | V28: ='Crop Prices (2022-2024)'!J21 -> 0.0070768386
A29: 2022 | B29: Kale Revenue ($) | C29: =C27*C28 -> 0.089383117 | D29: =D27*D28 -> 0.14739335 | E29: =E27*E28 -> 0.14354573 | F29: =F27*F28 -> 0.16781532 | G29: =G27*G28 -> 0.18498162 | H29: =H27*H28 -> 0.0754725 | I29: =I27*I28 -> 0.16041606 | J29: =J27*J28 -> 0.089975058 | ... V29: =V27*V28 -> 0.51943995
A30: 2023 | B30: Kale Harvest Yield (g) | C30: 537.8 | D30: 1769.5 | E30: 856.2 | F30: 959.2 | G30: 1879.1 | H30: 751.2 | I30: 1908.1 | J30: 1503.2 | K30: 327.3 | L30: 1206.7 | M30: 1344.7 | N30: 191.2 | O30: 982 | P30: 1136.9 | Q30: 748.5 | R30: 1421.4 | S30: 128.5 | T30: 117.5 | U30: 935.8 | V30: 1006.9
A31: 2023 | B31: Kale Wholesale Price ($/g) | C31: ='Crop Prices (2022-2024)'!J10 -> 0.0033234686 | D31: ='Crop Prices (2022-2024)'!J10 -> 0.0033234686 | E31: ='Crop Prices (2022-2024)'!J10 -> 0.0033234686 | F31: ='Crop Prices (2022-2024)'!J10 -> 0.0033234686 | G31: ='Crop Prices (2022-2024)'!J10 -> 0.0033234686 | H31: ='Crop Prices (2022-2024)'!J10 -> 0.0033234686 | I31: ='Crop Prices (2022-2024)'!J10 -> 0.0033234686 | J31: ='Crop Prices (2022-2024)'!J10 -> 0.0033234686 | K31: ='Crop Prices (2022-2024)'!J22 -> 0.0075398094 | L31: ='Crop Prices (2022-2024)'!J22 -> 0.0075398094 | M31: ='Crop Prices (2022-2024)'!J22 -> 0.0075398094 | N31: ='Crop Prices (2022-2024)'!J22 -> 0.0075398094 | O31: ='Crop Prices (2022-2024)'!J22 -> 0.0075398094 | P31: ='Crop Prices (2022-2024)'!J22 -> 0.0075398094 | Q31: ='Crop Prices (2022-2024)'!J22 -> 0.0075398094 | R31: ='Crop Prices (2022-2024)'!J22 -> 0.0075398094 | S31: ='Crop Prices (2022-2024)'!J22 -> 0.0075398094 | T31: ='Crop Prices (2022-2024)'!J22 -> 0.0075398094 | U31: ='Crop Prices (2022-2024)'!J22 -> 0.0075398094 | V31: ='Crop Prices (2022-2024)'!J22 -> 0.0075398094
A32: 2023 | B32: Kale Revenue ($) | C32: =C30*C31 -> 1.7873614 | D32: =D30*D31 -> 5.8808777 | E32: =E30*E31 -> 2.8455538 | F32: =F30*F31 -> 3.1878711 | G32: =G30*G31 -> 6.2451299 | H32: =H30*H31 -> 2.4965896 | I32: =I30*I31 -> 6.3415104 | J32: =J30*J31 -> 4.995838 | ... V32: =V30*V31 -> 7.5918341
A33: 2024 | B33: Kale Harvest Yield (g) | C33: 521.2 | D33: 994.1 | E33: 1966.6 | F33: 1432.6 | G33: 1006.7 | H33: 821.5 | I33: 1054.5 | J33: 1051.6 | K33: 728.3 | L33: 1496 | M33: 2180.2 | N33: 2762 | O33: 816.8 | P33: 902.8 | Q33: 1297.3 | R33: 683.8 | S33: 598.5 | T33: 646.5 | U33: 853.6 | V33: 603.1
A34: 2024 | B34: Kale Wholesale Price ($/g) | C34: ='Crop Prices (2022-2024)'!J11 -> 0.0031415872 | D34: ='Crop Prices (2022-2024)'!J11 -> 0.0031415872 | E34: ='Crop Prices (2022-2024)'!J11 -> 0.0031415872 | F34: ='Crop Prices (2022-2024)'!J11 -> 0.0031415872 | G34: ='Crop Prices (2022-2024)'!J11 -> 0.0031415872 | H34: ='Crop Prices (2022-2024)'!J11 -> 0.0031415872 | I34: ='Crop Prices (2022-2024)'!J11 -> 0.0031415872 | J34: ='Crop Prices (2022-2024)'!J11 -> 0.0031415872 | K34: ='Crop Prices (2022-2024)'!J23 -> 0.0063052207 | L34: ='Crop Prices (2022-2024)'!J23 -> 0.0063052207 | M34: ='Crop Prices (2022-2024)'!J23 -> 0.0063052207 | N34: ='Crop Prices (2022-2024)'!J23 -> 0.0063052207 | O34: ='Crop Prices (2022-2024)'!J23 -> 0.0063052207 | P34: ='Crop Prices (2022-2024)'!J23 -> 0.0063052207 | Q34: ='Crop Prices (2022-2024)'!J23 -> 0.0063052207 | R34: ='Crop Prices (2022-2024)'!J23 -> 0.0063052207 | S34: ='Crop Prices (2022-2024)'!J23 -> 0.0063052207 | T34: ='Crop Prices (2022-2024)'!J23 -> 0.0063052207 | U34: ='Crop Prices (2022-2024)'!J23 -> 0.0063052207 | V34: ='Crop Prices (2022-2024)'!J23 -> 0.0063052207
A35: 2024 | B35: Kale Revenue ($) | C35: =C33*C34 -> 1.6373953 | D35: =D33*D34 -> 3.1230519 | E35: =E33*E34 -> 6.1782455 | F35: =F33*F34 -> 4.5006379 | G35: =G33*G34 -> 3.1626359 | H35: =H33*H34 -> 2.5808139 | I35: =I33*I34 -> 3.3128037 | J35: =J33*J34 -> 3.3036931 | ... V35: =V33*V34 -> 3.8026786
B36: KALE TOTAL | C36: =C29+C32+C35 -> 3.5141398 | D36: =D29+D32+D35 -> 9.1513229 | E36: =E29+E32+E35 -> 9.167345 | F36: =F29+F32+F35 -> 7.8563243 | G36: =G29+G32+G35 -> 9.5927473 | H36: =H29+H32+H35 -> 5.152876 | I36: =I29+I32+I35 -> 9.8147302 | J36: =J29+J32+J35 -> 8.3895062 | ... V36: =V29+V32+V35 -> 11.913953
A38: Year | B38: BEANS - DIRECT MARKETING
A39: 2022 | B39: Bean Harvest Yield (g) | C39: 3247.3 | D39: 3715.1 | E39: 3278.9 | F39: 3817.4 | G39: 2610.8 | H39: 2854.6 | I39: 2594.8 | J39: 3891.4 | K39: 2536.2 | L39: 2176 | M39: 4021.8 | N39: 3052.1 | O39: 3237.7 | P39: 1689 | Q39: 2599.9 | R39: 1565 | S39: 1553.8 | T39: 3377.8 | U39: 1437.6 | V39: 3500.6
A40: 2022 | B40: Bean Wholesale Price ($/g) | C40: ='Crop Prices (2022-2024)'!$J$27 -> 0.0076550009 | D40: ='Crop Prices (2022-2024)'!$J$27 -> 0.0076550009 | E40: ='Crop Prices (2022-2024)'!$J$27 -> 0.0076550009 | F40: ='Crop Prices (2022-2024)'!$J$27 -> 0.0076550009 | G40: ='Crop Prices (2022-2024)'!$J$27 -> 0.0076550009 | H40: ='Crop Prices (2022-2024)'!$J$27 -> 0.0076550009 | I40: ='Crop Prices (2022-2024)'!$J$27 -> 0.0076550009 | J40: ='Crop Prices (2022-2024)'!$J$27 -> 0.0076550009 | K40: ='Crop Prices (2022-2024)'!$J$39 -> 0.012976409 | L40: ='Crop Prices (2022-2024)'!$J$39 -> 0.012976409 | M40: ='Crop Prices (2022-2024)'!$J$39 -> 0.012976409 | N40: ='Crop Prices (2022-2024)'!$J$39 -> 0.012976409 | O40: ='Crop Prices (2022-2024)'!$J$39 -> 0.012976409 | P40: ='Crop Prices (2022-2024)'!$J$39 -> 0.012976409 | Q40: ='Crop Prices (2022-2024)'!$J$39 -> 0.012976409 | R40: ='Crop Prices (2022-2024)'!$J$39 -> 0.012976409 | ... V40: ='Crop Prices (2022-2024)'!$J$39 -> 0.012976409
A41: 2022 | B41: Bean Revenue ($) | C41: =C39*C40 -> 24.858084 | D41: =D39*D40 -> 28.439094 | E41: =E39*E40 -> 25.099982 | F41: =F39*F40 -> 29.2222 | G41: =G39*G40 -> 19.985676 | H41: =H39*H40 -> 21.851966 | I41: =I39*I40 -> 19.863196 | J41: =J39*J40 -> 29.78867 | ... V41: =V39*V40 -> 45.425216
A42: 2023 | B42: Bean Harvest Yield (g) | C42: 4597.3 | D42: 5548.2 | E42: 7776.3 | F42: 4944.4 | G42: 4342.5 | H42: 7257.3 | I42: 6263.2 | J42: 6946.6 | K42: 4710.9 | L42: 4455.5 | M42: 6886.8 | N42: 5338.5 | O42: 7562.5 | P42: 5322.6 | Q42: 6259 | R42: 5300.6 | S42: 5099.8 | T42: 5608.4 | U42: 6142.9 | V42: 7099.5
A43: 2023 | B43: Bean Wholesale Price ($/g) | C43: ='Crop Prices (2022-2024)'!$J$28 -> 0.0081047439 | D43: ='Crop Prices (2022-2024)'!$J$28 -> 0.0081047439 | E43: ='Crop Prices (2022-2024)'!$J$28 -> 0.0081047439 | F43: ='Crop Prices (2022-2024)'!$J$28 -> 0.0081047439 | G43: ='Crop Prices (2022-2024)'!$J$28 -> 0.0081047439 | H43: ='Crop Prices (2022-2024)'!$J$28 -> 0.0081047439 | I43: ='Crop Prices (2022-2024)'!$J$28 -> 0.0081047439 | J43: ='Crop Prices (2022-2024)'!$J$28 -> 0.0081047439 | K43: ='Crop Prices (2022-2024)'!$J$40 -> 0.014186747 | L43: ='Crop Prices (2022-2024)'!$J$40 -> 0.014186747 | M43: ='Crop Prices (2022-2024)'!$J$40 -> 0.014186747 | N43: ='Crop Prices (2022-2024)'!$J$40 -> 0.014186747 | O43: ='Crop Prices (2022-2024)'!$J$40 -> 0.014186747 | P43: ='Crop Prices (2022-2024)'!$J$40 -> 0.014186747 | Q43: ='Crop Prices (2022-2024)'!$J$40 -> 0.014186747 | R43: ='Crop Prices (2022-2024)'!$J$40 -> 0.014186747 | ... V43: ='Crop Prices (2022-2024)'!$J$40 -> 0.014186747
A44: 2023 | B44: Bean Revenue ($) | C44: =C42*C43 -> 37.259939 | D44: =D42*D43 -> 44.96674 | E44: =E42*E43 -> 63.02492 | F44: =F42*F43 -> 40.073096 | G44: =G42*G43 -> 35.19485 | H44: =H42*H43 -> 58.818558 | I44: =I42*I43 -> 50.761632 | J44: =J42*J43 -> 56.300414 | ... V44: =V42*V43 -> 100.71881
A45: 2024 | B45: Bean Harvest Yield (g) | C45: 912 | D45: 2653.8 | E45: 5381.1 | F45: 4159.9 | G45: 3708 | H45: 3844.7 | I45: 3178.7 | J45: 6492.1 | K45: 1802.8 | L45: 2525 | M45: 5394.5 | N45: 5439.1 | O45: 5200.8 | P45: 3831.4 | Q45: 5913.1 | R45: 6022.8 | S45: 3564.5 | T45: 5283.4 | U45: 4165.6 | V45: 5637.7
A46: 2024 | B46: Bean Wholesale Price ($/g) | C46: ='Crop Prices (2022-2024)'!$J$29 -> 0.0083389851 | D46: ='Crop Prices (2022-2024)'!$J$29 -> 0.0083389851 | E46: ='Crop Prices (2022-2024)'!$J$29 -> 0.0083389851 | F46: ='Crop Prices (2022-2024)'!$J$29 -> 0.0083389851 | G46: ='Crop Prices (2022-2024)'!$J$29 -> 0.0083389851 | H46: ='Crop Prices (2022-2024)'!$J$29 -> 0.0083389851 | I46: ='Crop Prices (2022-2024)'!$J$29 -> 0.0083389851 | J46: ='Crop Prices (2022-2024)'!$J$29 -> 0.0083389851 | K46: ='Crop Prices (2022-2024)'!$J$41 -> 0.011865279 | L46: ='Crop Prices (2022-2024)'!$J$41 -> 0.011865279 | M46: ='Crop Prices (2022-2024)'!$J$41 -> 0.011865279 | N46: ='Crop Prices (2022-2024)'!$J$41 -> 0.011865279 | O46: ='Crop Prices (2022-2024)'!$J$41 -> 0.011865279 | P46: ='Crop Prices (2022-2024)'!$J$41 -> 0.011865279 | Q46: ='Crop Prices (2022-2024)'!$J$41 -> 0.011865279 | R46: ='Crop Prices (2022-2024)'!$J$41 -> 0.011865279 | ... V46: ='Crop Prices (2022-2024)'!$J$41 -> 0.011865279
A47: 2024 | B47: Bean Revenue ($) | C47: =C45*C46 -> 7.6051544 | D47: =D45*D46 -> 22.129999 | E47: =E45*E46 -> 44.872913 | F47: =F45*F46 -> 34.689344 | G47: =G45*G46 -> 30.920957 | H47: =H45*H46 -> 32.060896 | I47: =I45*I46 -> 26.507132 | J47: =J45*J46 -> 54.137525 | ... V47: =V45*V46 -> 66.892883
B48: BEANS TOTAL | C48: =C41+C44+C47 -> 69.723178 | D48: =D41+D44+D47 -> 95.535833 | E48: =E41+E44+E47 -> 132.99782 | F48: =F41+F44+F47 -> 103.98464 | G48: =G41+G44+G47 -> 86.101483 | H48: =H41+H44+H47 -> 112.73142 | I48: =I41+I44+I47 -> 97.13196 | J48: =J41+J44+J47 -> 140.22661 | ... V48: =V41+V44+V47 -> 213.03691
A50: Year | B50: CARROTS - DIRECT MARKETING
A51: 2022 | B51: Carrot Harvest Yield (g) | C51: 1689.2 | D51: 4814.5 | E51: 1862.1 | F51: 4125.3 | G51: 3185.6 | H51: 2558.5 | I51: 4424.3 | J51: 2473.9 | K51: 1919.2 | L51: 2085.2 | M51: 3142.1 | N51: 1884.5 | O51: 2724.2 | P51: 2435.9 | Q51: 2611.2 | R51: 1262 | S51: 1445.7 | T51: 2696.2 | U51: 1995.2 | V51: 3023.3
A52: 2022 | B52: Carrot Wholesale Price ($/g) | C52: ='Crop Prices (2022-2024)'!$J$30 -> 0.0030263957 | D52: ='Crop Prices (2022-2024)'!$J$30 -> 0.0030263957 | E52: ='Crop Prices (2022-2024)'!$J$30 -> 0.0030263957 | F52: ='Crop Prices (2022-2024)'!$J$30 -> 0.0030263957 | G52: ='Crop Prices (2022-2024)'!$J$30 -> 0.0030263957 | H52: ='Crop Prices (2022-2024)'!$J$30 -> 0.0030263957 | I52: ='Crop Prices (2022-2024)'!$J$30 -> 0.0030263957 | J52: ='Crop Prices (2022-2024)'!$J$30 -> 0.0030263957 | K52: ='Crop Prices (2022-2024)'!$J$42 -> 0.0082699804 | L52: ='Crop Prices (2022-2024)'!$J$42 -> 0.0082699804 | M52: ='Crop Prices (2022-2024)'!$J$42 -> 0.0082699804 | N52: ='Crop Prices (2022-2024)'!$J$42 -> 0.0082699804 | O52: ='Crop Prices (2022-2024)'!$J$42 -> 0.0082699804 | P52: ='Crop Prices (2022-2024)'!$J$42 -> 0.0082699804 | Q52: ='Crop Prices (2022-2024)'!$J$42 -> 0.0082699804 | R52: ='Crop Prices (2022-2024)'!$J$42 -> 0.0082699804 | ... V52: ='Crop Prices (2022-2024)'!$J$42 -> 0.0082699804
A53: 2022 | B53: Carrot Revenue ($) | C53: =C51*C52 -> 5.1121876 | D53: =D51*D52 -> 14.570582 | E53: =E51*E52 -> 5.6354514 | F53: =F51*F52 -> 12.48479 | G53: =G51*G52 -> 9.6408862 | H53: =H51*H52 -> 7.7430334 | I53: =I51*I52 -> 13.389683 | J53: =J51*J52 -> 7.4870003 | ... V53: =V51*V52 -> 25.002632
A54: 2023 | B54: Carrot Harvest Yield (g) | C54: 3881.2 | D54: 6626.2 | E54: 7038.2 | F54: 5829.2 | G54: 6182.4 | H54: 4988.9 | I54: 4164 | J54: 6127.5 | K54: 5154.3 | L54: 3988.8 | M54: 7913 | N54: 6661.4 | O54: 5642.2 | P54: 4229 | Q54: 7467.5 | R54: 6915.1 | S54: 5475.3 | T54: 5296.8 | U54: 5344.3 | V54: 4564.2
A55: 2023 | B55: Carrot Wholesale Price ($/g) | C55: ='Crop Prices (2022-2024)'!$J$31 -> 0.0034836344 | D55: ='Crop Prices (2022-2024)'!$J$31 -> 0.0034836344 | E55: ='Crop Prices (2022-2024)'!$J$31 -> 0.0034836344 | F55: ='Crop Prices (2022-2024)'!$J$31 -> 0.0034836344 | G55: ='Crop Prices (2022-2024)'!$J$31 -> 0.0034836344 | H55: ='Crop Prices (2022-2024)'!$J$31 -> 0.0034836344 | I55: ='Crop Prices (2022-2024)'!$J$31 -> 0.0034836344 | J55: ='Crop Prices (2022-2024)'!$J$31 -> 0.0034836344 | K55: ='Crop Prices (2022-2024)'!$J$43 -> 0.0093334903 | L55: ='Crop Prices (2022-2024)'!$J$43 -> 0.0093334903 | M55: ='Crop Prices (2022-2024)'!$J$43 -> 0.0093334903 | N55: ='Crop Prices (2022-2024)'!$J$43 -> 0.0093334903 | O55: ='Crop Prices (2022-2024)'!$J$43 -> 0.0093334903 | P55: ='Crop Prices (2022-2024)'!$J$43 -> 0.0093334903 | Q55: ='Crop Prices (2022-2024)'!$J$43 -> 0.0093334903 | R55: ='Crop Prices (2022-2024)'!$J$43 -> 0.0093334903 | ... V55: ='Crop Prices (2022-2024)'!$J$43 -> 0.0093334903
A56: 2023 | B56: Carrot Revenue ($) | C56: =C54*C55 -> 13.520682 | D56: =D54*D55 -> 23.083258 | E56: =E54*E55 -> 24.518516 | F56: =F54*F55 -> 20.306802 | G56: =G54*G55 -> 21.537222 | H56: =H54*H55 -> 17.379504 | I56: =I54*I55 -> 14.505854 | J56: =J54*J55 -> 21.34597 | ... V56: =V54*V55 -> 42.599917
A57: 2024 | B57: Carrot Harvest Yield (g) | C57: 6487.9 | D57: 5297.4 | E57: 6034 | F57: 4460.7 | G57: 6510 | H57: 4290 | I57: 6220.2 | J57: 10110.9 | K57: 5757.4 | L57: 2891.7 | M57: 1942.5 | N57: 6867.5 | O57: 2142.5 | P57: 749.1 | Q57: 3494.9 | R57: 6069.5 | S57: 3765.3 | T57: 6629.2 | U57: 4799.8 | V57: 3866.5
A58: 2024 | B58: Carrot Wholesale Price ($/g) | C58: ='Crop Prices (2022-2024)'!$J$32 -> 0.0025180924 | D58: ='Crop Prices (2022-2024)'!$J$32 -> 0.0025180924 | E58: ='Crop Prices (2022-2024)'!$J$32 -> 0.0025180924 | F58: ='Crop Prices (2022-2024)'!$J$32 -> 0.0025180924 | G58: ='Crop Prices (2022-2024)'!$J$32 -> 0.0025180924 | H58: ='Crop Prices (2022-2024)'!$J$32 -> 0.0025180924 | I58: ='Crop Prices (2022-2024)'!$J$32 -> 0.0025180924 | J58: ='Crop Prices (2022-2024)'!$J$32 -> 0.0025180924 | K58: ='Crop Prices (2022-2024)'!$J$44 -> 0.0092223774 | L58: ='Crop Prices (2022-2024)'!$J$44 -> 0.0092223774 | M58: ='Crop Prices (2022-2024)'!$J$44 -> 0.0092223774 | N58: ='Crop Prices (2022-2024)'!$J$44 -> 0.0092223774 | O58: ='Crop Prices (2022-2024)'!$J$44 -> 0.0092223774 | P58: ='Crop Prices (2022-2024)'!$J$44 -> 0.0092223774 | Q58: ='Crop Prices (2022-2024)'!$J$44 -> 0.0092223774 | R58: ='Crop Prices (2022-2024)'!$J$44 -> 0.0092223774 | ... V58: ='Crop Prices (2022-2024)'!$J$44 -> 0.0092223774
A59: 2024 | B59: Carrot Revenue ($) | C59: =C57*C58 -> 16.337132 | D59: =D57*D58 -> 13.339343 | E59: =E57*E58 -> 15.19417 | F59: =F57*F58 -> 11.232455 | G59: =G57*G58 -> 16.392782 | H59: =H57*H58 -> 10.802616 | I59: =I57*I58 -> 15.663038 | J59: =J57*J58 -> 25.46018 | ... V59: =V57*V58 -> 35.658322
B60: CARROTS TOTAL | C60: =C53+C56+C59 -> 34.970001 | D60: =D53+D56+D59 -> 50.993183 | E60: =E53+E56+E59 -> 45.348137 | F60: =F53+F56+F59 -> 44.024047 | G60: =G53+G56+G59 -> 47.570889 | H60: =H53+H56+H59 -> 35.925154 | I60: =I53+I56+I59 -> 43.558575 | J60: =J53+J56+J59 -> 54.293151 | ... V60: =V53+V56+V59 -> 103.26087
A62: Year | B62: KALE - DIRECT MARKETING
A63: 2022 | B63: Kale Harvest Yield (g) | C63: 30.2 | D63: 49.8 | E63: 48.5 | F63: 56.7 | G63: 62.5 | H63: 25.5 | I63: 54.2 | J63: 30.4 | K63: 42.1 | L63: 38.2 | M63: 58.1 | N63: 58.2 | O63: 47.8 | P63: 36.4 | Q63: 58.9 | R63: 48.2 | S63: 79.8 | T63: 51.5 | U63: 58 | V63: 73.4
A64: 2022 | B64: Kale Wholesale Price ($/g) | C64: ='Crop Prices (2022-2024)'!$J$33 -> 0.0050315 | D64: ='Crop Prices (2022-2024)'!$J$33 -> 0.0050315 | E64: ='Crop Prices (2022-2024)'!$J$33 -> 0.0050315 | F64: ='Crop Prices (2022-2024)'!$J$33 -> 0.0050315 | G64: ='Crop Prices (2022-2024)'!$J$33 -> 0.0050315 | H64: ='Crop Prices (2022-2024)'!$J$33 -> 0.0050315 | I64: ='Crop Prices (2022-2024)'!$J$33 -> 0.0050315 | J64: ='Crop Prices (2022-2024)'!$J$33 -> 0.0050315 | K64: ='Crop Prices (2022-2024)'!$J$45 -> 0.01273831 | L64: ='Crop Prices (2022-2024)'!$J$45 -> 0.01273831 | M64: ='Crop Prices (2022-2024)'!$J$45 -> 0.01273831 | N64: ='Crop Prices (2022-2024)'!$J$45 -> 0.01273831 | O64: ='Crop Prices (2022-2024)'!$J$45 -> 0.01273831 | P64: ='Crop Prices (2022-2024)'!$J$45 -> 0.01273831 | Q64: ='Crop Prices (2022-2024)'!$J$45 -> 0.01273831 | R64: ='Crop Prices (2022-2024)'!$J$45 -> 0.01273831 | ... V64: ='Crop Prices (2022-2024)'!$J$45 -> 0.01273831
A65: 2022 | B65: Kale Revenue ($) | C65: =C63*C64 -> 0.1519513 | D65: =D63*D64 -> 0.2505687 | E65: =E63*E64 -> 0.24402775 | F65: =F63*F64 -> 0.28528605 | G65: =G63*G64 -> 0.31446875 | H65: =H63*H64 -> 0.12830325 | I65: =I63*I64 -> 0.2727073 | J65: =J63*J64 -> 0.1529576 | ... V65: =V63*V64 -> 0.93499192
A66: 2023 | B66: Kale Harvest Yield (g) | C66: 537.8 | D66: 1769.5 | E66: 856.2 | F66: 959.2 | G66: 1879.1 | H66: 751.2 | I66: 1908.1 | J66: 1503.2 | K66: 327.3 | L66: 1206.7 | M66: 1344.7 | N66: 191.2 | O66: 982 | P66: 1136.9 | Q66: 748.5 | R66: 1421.4 | S66: 128.5 | T66: 117.5 | U66: 935.8 | V66: 1006.9
A67: 2023 | B67: Kale Wholesale Price ($/g) | C67: ='Crop Prices (2022-2024)'!$J$34 -> 0.0056498966 | D67: ='Crop Prices (2022-2024)'!$J$34 -> 0.0056498966 | E67: ='Crop Prices (2022-2024)'!$J$34 -> 0.0056498966 | F67: ='Crop Prices (2022-2024)'!$J$34 -> 0.0056498966 | G67: ='Crop Prices (2022-2024)'!$J$34 -> 0.0056498966 | H67: ='Crop Prices (2022-2024)'!$J$34 -> 0.0056498966 | I67: ='Crop Prices (2022-2024)'!$J$34 -> 0.0056498966 | J67: ='Crop Prices (2022-2024)'!$J$34 -> 0.0056498966 | K67: ='Crop Prices (2022-2024)'!$J$46 -> 0.013571657 | L67: ='Crop Prices (2022-2024)'!$J$46 -> 0.013571657 | M67: ='Crop Prices (2022-2024)'!$J$46 -> 0.013571657 | N67: ='Crop Prices (2022-2024)'!$J$46 -> 0.013571657 | O67: ='Crop Prices (2022-2024)'!$J$46 -> 0.013571657 | P67: ='Crop Prices (2022-2024)'!$J$46 -> 0.013571657 | Q67: ='Crop Prices (2022-2024)'!$J$46 -> 0.013571657 | R67: ='Crop Prices (2022-2024)'!$J$46 -> 0.013571657 | ... V67: ='Crop Prices (2022-2024)'!$J$46 -> 0.013571657
A68: 2023 | B68: Kale Revenue ($) | C68: =C66*C67 -> 3.0385144 | D68: =D66*D67 -> 9.9974921 | E68: =E66*E67 -> 4.8374415 | F68: =F66*F67 -> 5.4193808 | G68: =G66*G67 -> 10.616721 | H68: =H66*H67 -> 4.2442023 | I68: =I66*I67 -> 10.780568 | J68: =J66*J67 -> 8.4929246 | ... V68: =V66*V67 -> 13.665301
A69: 2024 | B69: Kale Harvest Yield (g) | C69: 521.2 | D69: 994.1 | E69: 1966.6 | F69: 1432.6 | G69: 1006.7 | H69: 821.5 | I69: 1054.5 | J69: 1051.6 | K69: 728.3 | L69: 1496 | M69: 2180.2 | N69: 2762 | O69: 816.8 | P69: 902.8 | Q69: 1297.3 | R69: 683.8 | S69: 598.5 | T69: 646.5 | U69: 853.6 | V69: 603.1
A70: 2024 | B70: Kale Wholesale Price ($/g) | C70: ='Crop Prices (2022-2024)'!$J$35 -> 0.0053406983 | D70: ='Crop Prices (2022-2024)'!$J$35 -> 0.0053406983 | E70: ='Crop Prices (2022-2024)'!$J$35 -> 0.0053406983 | F70: ='Crop Prices (2022-2024)'!$J$35 -> 0.0053406983 | G70: ='Crop Prices (2022-2024)'!$J$35 -> 0.0053406983 | H70: ='Crop Prices (2022-2024)'!$J$35 -> 0.0053406983 | I70: ='Crop Prices (2022-2024)'!$J$35 -> 0.0053406983 | J70: ='Crop Prices (2022-2024)'!$J$35 -> 0.0053406983 | K70: ='Crop Prices (2022-2024)'!$J$47 -> 0.011349397 | L70: ='Crop Prices (2022-2024)'!$J$47 -> 0.011349397 | M70: ='Crop Prices (2022-2024)'!$J$47 -> 0.011349397 | N70: ='Crop Prices (2022-2024)'!$J$47 -> 0.011349397 | O70: ='Crop Prices (2022-2024)'!$J$47 -> 0.011349397 | P70: ='Crop Prices (2022-2024)'!$J$47 -> 0.011349397 | Q70: ='Crop Prices (2022-2024)'!$J$47 -> 0.011349397 | R70: ='Crop Prices (2022-2024)'!$J$47 -> 0.011349397 | ... V70: ='Crop Prices (2022-2024)'!$J$47 -> 0.011349397
A71: 2024 | B71: Kale Revenue ($) | C71: =C69*C70 -> 2.783572 | D71: =D69*D70 -> 5.3091882 | E71: =E69*E70 -> 10.503017 | F71: =F69*F70 -> 7.6510844 | G71: =G69*G70 -> 5.376481 | H71: =H69*H70 -> 4.3873837 | I71: =I69*I70 -> 5.6317664 | J71: =J69*J70 -> 5.6162783 | ... V71: =V69*V70 -> 6.8448215
B72: KALE TOTAL | C72: =C65+C68+C71 -> 5.9740377 | D72: =D65+D68+D71 -> 15.557249 | E72: =E65+E68+E71 -> 15.584487 | F72: =F65+F68+F71 -> 13.355751 | G72: =G65+G68+G71 -> 16.30767 | H72: =H65+H68+H71 -> 8.7598892 | I72: =I65+I68+I71 -> 16.685041 | J72: =J65+J68+J71 -> 14.262161 | ... V72: =V65+V68+V71 -> 21.445115

Sheet Costs (2022-2024)
A1: Category | B1: Supplier | C1: Year | D1: Cost | E1: Amount Used | F1: Adjusted Cost | G1: Treatments Used | H1: Treatments | I1: Cost Per Treatment | J1: Note
A2: Seeds - Beans | B2: Saanich Organics | C2: 2022/2023 | D2: 121.05 | E2: 0.5 | F2: =D2*E2 -> 60.525 | G2: All | H2: 20 | I2: =F2/H2 -> 3.02625
A3: Seeds - Carrots & Kale | B3: Johnny's Selected Seeds | C3: 2022 | D3: =116.1*1.2919 -> 149.98959 | E3: 0.5 | F3: =D3*E3 -> 74.994795 | G3: All | H3: 20 | I3: =F3/H3 -> 3.7497397 | J3: Multiplied the order by the USD-CAD conversion for June 21, 2022 (*1.2919)
A4: Seeds - Carrots & Kale | B4: Johnny's Selected Seeds | C4: 2023 | D4: =118.62*1.3369 -> 158.58308 | E4: 0.5 | F4: =D4*E4 -> 79.291539 | G4: All | H4: 20 | I4: =F4/H4 -> 3.964577 | J4: Multiplied the order by the USD-CAD conversion for May 8, 2023 (*1.3369)
A5: Seeds - Beans, Carrots, & Kale | B5: Johnny's Selected Seeds | C5: 2024 | D5: =(114.4*1.3527) + (32.9*1.3682) -> 199.76266 | E5: 0.75 | F5: =D5*E5 -> 149.822 | G5: All | H5: 20 | I5: =F5/H5 -> 7.4910998 | J5: I multiplied the order by the USD-CAD conversion for April 3 (*1.3527) and 28 (*1.3682), 2024.
A6: Seeds - Cover Crops | B6: Integrity Sales & Distributors | C6: 2022 | D6: =23.08*2 -> 46.16 | E6: 1 | F6: =D6*E6 -> 46.16 | G6: Treatments 2-5 | H6: 16 | I6: =F6/H6 -> 2.885 | J6: Note: I used a free bag of cover crop for my first season. Kept it consistent afterwards.
A7: Seeds - Cover Crops | B7: Integrity Sales & Distributors | C7: 2023 | D7: =23.08*2 -> 46.16 | E7: 1 | F7: =D7*E7 -> 46.16 | G7: Treatments 2-6 | H7: 16 | I7: =F7/H7 -> 2.885
A8: Seeds - Cover Crops | B8: Integrity Sales & Distributors | C8: 2024 | D8: 38.4 | E8: 1 | F8: =D8*E8 -> 38.4 | G8: Treatments 2-7 | H8: 16 | I8: =F8/H8 -> 2.4
A9: Fertility - Fertilizer | B9: Integrity Sales & Distributors | C9: 2022 | D9: 13.43 | E9: 1 | F9: =D9*E9 -> 13.43 | G9: Treatments 1-2 | H9: 8 | I9: =F9/H9 -> 1.67875 | J9: $11.99 + GST/PST. Price remained stable.
A10: Fertility - Fertilizer | B10: Integrity Sales & Distributors | C10: 2023 | D10: 13.43 | E10: 1 | F10: =D10*E10 -> 13.43 | G10: Treatments 1-3 | H10: 8 | I10: =F10/H10 -> 1.67875 | J10: $11.99 + GST/PST. Price remained stable.
A11: Fertility - Fertilizer | B11: Integrity Sales & Distributors | C11: 2024 | D11: 13.43 | E11: 1 | F11: =D11*E11 -> 13.43 | G11: Treatments 1-4 | H11: 8 | I11: =F11/H11 -> 1.67875 | J11: $11.99 + GST/PST. Price remained stable.
A12: Fertility - Compost | B12: Farm to Garden Organics | C12: 2022 | D12: 243 | E12: 1 | F12: =D12*E12 -> 243 | G12: Treatments 3-5 | H12: 12 | I12: =F12/H12 -> 20.25 | J12: 3 yards ultrafine compost
A13: Fertility - Compost | B13: Farm to Garden Organics | C13: 2023 | D13: 354 | E13: 1 | F13: =D13*E13 -> 354 | G13: Treatments 3-5 | H13: 12 | I13: =F13/H13 -> 29.5 | J13: 3 yards ultrafine compost
A14: Fertility - Compost | B14: Farm to Garden Organics | C14: 2024 | D14: 309 | E14: 1 | F14: =D14*E14 -> 309 | G14: Treatments 3-5 | H14: 12 | I14: =F14/H14 -> 25.75 | J14: 3 yards ultrafine compost
A15: Pest Management - Rabbit Fence | B15: Integrity Sales & Distributors | C15: 2024 | D15: 120 | E15: 1 | F15: =D15*E15 -> 120 | G15: All | H15: 20 | I15: =F15/H15/3 -> 2 | J15: Note: orange cells are estimates and must be verified at Integrity
A16: Fuel | B16: Various Gas Stations | C16: Every year | D16: 60 | E16: 1 | F16: =D16*E16 -> 60 | G16: All | H16: 20 | I16: =F16/H16/3 -> 1 | J16: Note: this is a big assumption. Can't remember how much I paid, but I filled jugs roughly once a year for my research.

Sheet Land Prep Costs (2022-2024)
A1: MACHINERY USE - LAND PREPARATION | L1: Year | M1: BC Minimum Wage ($/hr) | N1: BC Minimum Wage ($/min)
A2: Category | B2: Year | C2: Cost ($/hr) | D2: Cost ($/min) | E2: Time Used (min) | F2: Cost ($) | G2: Treatments Used | H2: Treatments | I2: Cost Per Treatment ($) | J2: Note | L2: 2022 | M2: 15.65 | N2: =M2/60 -> 0.26083333
A3: Rotary plow | B3: 2022 | C3: 23 | D3: =C3/60 -> 0.38333333 | E3: 65 | F3: =E3*D3 -> 24.916667 | G3: All | H3: 20 | I3: =F3/H3 -> 1.2458333 | J3: These numbers were created by understanding capital costs | L3: 2023 | M3: 16.75 | N3: =M3/60 -> 0.27916667
A4: Flail mower | B4: 2023 | C4: 25 | D4: =C4/60 -> 0.41666667 | E4: 43.5 | F4: =E4*D4 -> 18.125 | G4: Treatments 1-4 | H4: 16 | I4: =F4/H4 -> 1.1328125 | J4: and annual operating costs over the ten year life cycle of the | L4: 2024 | M4: 17.4 | N4: =M4/60 -> 0.29
A5: Rotary plow | B5: 2023 | C5: 25 | D5: =C5/60 -> 0.41666667 | E5: =77.25+44.5 -> 121.75 | F5: =E5*D5 -> 50.729167 | G5: Treatments 1-4 | H5: 16 | I5: =F5/H5 -> 3.1705729 | J5: machine, and then taking the annual usage into
A6: Power harrow | B6: 2023 | C6: 25 | D6: =C6/60 -> 0.41666667 | E6: 60 | F6: =E6*D6 -> 25 | G6: Treatments 1-4 | H6: 16 | I6: =F6/H6 -> 1.5625 | J6: consideration. The numbers of $23, $25, and $27/hr reflect
A7: Flail mower | B7: 2024 | C7: 27 | D7: =C7/60 -> 0.45 | E7: 43.5 | F7: =E7*D7 -> 19.575 | G7: Treatments 1-4 | H7: 16 | I7: =F7/H7 -> 1.2234375 | J7: inflation.
A8: Rotary plow | B8: 2024 | C8: 27 | D8: =C8/60 -> 0.45 | E8: =77.25+44.5 -> 121.75 | F8: =E8*D8 -> 54.7875 | G8: Treatments 1-4 | H8: 16 | I8: =F8/H8 -> 3.4242188
A9: Power harrow | B9: 2024 | C9: 27 | D9: =C9/60 -> 0.45 | E9: 60 | F9: =E9*D9 -> 27 | G9: Treatments 1-4 | H9: 16 | I9: =F9/H9 -> 1.6875 | J9: The 2024 time numbers were used for 2023 as well.
A10: TOTAL 2022 | B10: 2022 | C10: 23 | D10: =C10/60 -> 0.38333333 | E10: =E3 -> 65 | F10: =E10*D10 -> 24.916667 | G10: =G3 -> All | H10: =H3 -> 20 | I10: =I3 -> 1.2458333
A11: TOTAL 2023 | B11: 2023 | C11: 25 | D11: =C11/60 -> 0.41666667 | E11: =SUM(E4:E6) -> 225.25 | F11: =E11*D11 -> 93.854167 | G11: Treatments 1-4 | H11: 16 | I11: =SUM(I4:I6) -> 5.8658854
A12: TOTAL 2024 | B12: 2024 | C12: 27 | D12: =C12/60 -> 0.45 | E12: =SUM(E7:E9) -> 225.25 | F12: =E12*D12 -> 101.3625 | G12: Treatments 1-4 | H12: 16 | I12: =SUM(I7:I9) -> 6.3351562
M13: =16.75/15.65 -> 1.0702875
A14: LABOUR - LAND PREPARATION | M14: =17.4/16.75 -> 1.038806
A15: Category | B15: Year | C15: Cost ($/hr) | D15: Cost ($/min) | E15: Time Used (min) | F15: Cost ($) | G15: Treatments Used | H15: Treatments | I15: Cost Per Treatment ($) | J15: Note
A16: Labour Costs - Machinery | B16: 2022 | C16: =$M$2 -> 15.65 | D16: =C16/60 -> 0.26083333 | E16: =E10 -> 65 | F16: =D16*E16 -> 16.954167 | G16: All | H16: 20 | I16: =F16/H16 -> 0.84770833
A17: Labour Costs - Raking and Bed Preparation | B17: 2022 | C17: =$M$2 -> 15.65 | D17: =C17/60 -> 0.26083333 | E17: =8*60 -> 480 | F17: =D17*E17 -> 125.2 | G17: All | H17: 20 | I17: =F17/H17 -> 6.26
A18: Labour Costs - Compost Spreading | B18: 2022 | C18: =$M$2 -> 15.65 | D18: =C18/60 -> 0.26083333 | E18: 60 | F18: =D18*E18 -> 15.65 | G18: Treatments 3-5 | H18: 12 | I18: =F18/H18 -> 1.3041667
A19: Labour Costs - Machinery | B19: 2023 | C19: =$M$3 -> 16.75 | D19: =C19/60 -> 0.27916667 | E19: =E11 -> 225.25 | F19: =D19*E19 -> 62.882292 | G19: Treatments 1-4 | H19: 16 | I19: =F19/H19 -> 3.9301432 | J19: These values are the same as 2024 - they weren't measured
A20: Labour Costs - Raking and Bed Preparation | B20: 2023 | C20: =$M$3 -> 16.75 | D20: =C20/60 -> 0.27916667 | E20: 72.25 | F20: =D20*E20 -> 20.169792 | G20: Treatments 1-4 | H20: 16 | I20: =F20/H20 -> 1.260612 | J20: These values are the same as 2024 - they weren't measured
A21: Labour Costs - Compost Spreading | B21: 2023 | C21: =$M$3 -> 16.75 | D21: =C21/60 -> 0.27916667 | E21: 60 | F21: =D21*E21 -> 16.75 | G21: Treatments 3-5 | H21: 12 | I21: =F21/H21 -> 1.3958333 | J21: These values are the same as 2024 - they weren't measured
A22: Labour Costs - Weed Whacking Post Grazing | B22: 2023 | C22: =$M$3 -> 16.75 | D22: =C22/60 -> 0.27916667 | E22: 30 | F22: =D22*E22 -> 8.375 | G22: Treatments 4-5 | H22: 8 | I22: =F22/H22 -> 1.046875
A23: Labour Costs - No-Till Bed Preparation | B23: 2023 | C23: =$M$3 -> 16.75 | D23: =C23/60 -> 0.27916667 | E23: 158.75 | F23: =D23*E23 -> 44.317708 | G23: Treatment 5 | H23: 4 | I23: =F23/H23 -> 11.079427 | J23: These values are the same as 2024 - they weren't measured
A24: Labour Costs - Machinery | B24: 2024 | C24: =$M$4 -> 17.4 | D24: =C24/60 -> 0.29 | E24: =E12 -> 225.25 | F24: =D24*E24 -> 65.3225 | G24: Treatments 1-4 | H24: 16 | I24: =F24/H24 -> 4.0826562
A25: Labour Costs - Raking and Bed Preparation | B25: 2024 | C25: =$M$4 -> 17.4 | D25: =C25/60 -> 0.29 | E25: =28+24.25+20 -> 72.25 | F25: =D25*E25 -> 20.9525 | G25: Treatments 1-4 | H25: 16 | I25: =F25/H25 -> 1.3095312
A26: Labour Costs - Compost Spreading | B26: 2024 | C26: =$M$4 -> 17.4 | D26: =C26/60 -> 0.29 | E26: 95 | F26: =D26*E26 -> 27.55 | G26: Treatments 3-5 | H26: 12 | I26: =F26/H26 -> 2.2958333
A27: Labour Costs - Weed Whacking Post Grazing | B27: 2024 | C27: =$M$4 -> 17.4 | D27: =C27/60 -> 0.29 | E27: 30 | F27: =D27*E27 -> 8.7 | G27: Treatments 4-5 | H27: 8 | I27: =F27/H27 -> 1.0875
A28: Labour Costs - No-Till Bed Preparation | B28: 2024 | C28: =$M$4 -> 17.4 | D28: =C28/60 -> 0.29 | E28: 158.75 | F28: =D28*E28 -> 46.0375 | G28: Treatment 5 | H28: 4 | I28: =F28/H28 -> 11.509375
A29: TOTAL 2022 (Treatments 1-2) | B29: 2022 | C29: =$M$2 -> 15.65 | D29: =C29/60 -> 0.26083333 | E29: =SUM(E16:E17) -> 545 | F29: =D29*E29 -> 142.15417 | G29: Treatments 1-2 | I29: =SUM(I16:I17) -> 7.1077083
A30: TOTAL 2022 (Treatments 3-5) | B30: 2022 | C30: =$M$2 -> 15.65 | D30: =C30/60 -> 0.26083333 | E30: =SUM(E16:E18) -> 605 | F30: =D30*E30 -> 157.80417 | G30: Treatments 3-5 | I30: =SUM(I16:I18) -> 8.411875
A31: TOTAL 2023 (Treatments 1-2) | B31: 2023 | C31: =$M$3 -> 16.75 | D31: =C31/60 -> 0.27916667 | E31: =SUM(E20,E19) -> 297.5 | F31: =D31*E31 -> 83.052083 | G31: Treatments 1-2 | I31: =SUM(I19,I20) -> 5.1907552
A32: TOTAL 2023 (Treatment 3) | B32: 2023 | C32: =$M$3 -> 16.75 | D32: =C32/60 -> 0.27916667 | E32: =SUM(E19:E21) -> 357.5 | F32: =D32*E32 -> 99.802083 | G32: Treatments 3 | I32: =SUM(I19:I21) -> 6.5865885
A33: TOTAL 2023 (Treatment 4) | B33: 2023 | C33: =$M$3 -> 16.75 | D33: =C33/60 -> 0.27916667 | E33: =SUM(E19:E22) -> 387.5 | F33: =SUM(F19:F22) -> 108.17708 | G33: Treatment 4 | I33: =SUM(I19:I22) -> 7.6334635
A34: TOTAL 2023 (Treatment 5) | B34: 2023 | C34: =$M$3 -> 16.75 | D34: =C34/60 -> 0.27916667 | E34: =SUM(E22:E23) -> 188.75 | F34: =D34*E34 -> 52.692708 | G34: Treatment 5 | I34: =SUM(I21:I23) -> 13.522135
A35: TOTAL 2024 (Treatments 1-2) | B35: 2024 | C35: =$M$4 -> 17.4 | D35: =C35/60 -> 0.29 | E35: =E25+E24 -> 297.5 | F35: =D35*E35 -> 86.275 | G35: Treatments 1-2 | I35: =SUM(I24:I25) -> 5.3921875
A36: TOTAL 2024 (Treatment 3) | B36: 2024 | C36: =$M$4 -> 17.4 | D36: =C36/60 -> 0.29 | E36: =SUM(E24:E26) -> 392.5 | F36: =D36*E36 -> 113.825 | G36: Treatment 3 | I36: =SUM(I24:I25,I26) -> 7.6880208
A37: TOTAL 2024 (Treatment 4) | B37: 2024 | C37: =$M$4 -> 17.4 | D37: =C37/60 -> 0.29 | E37: =SUM(E24:E27) -> 422.5 | F37: =SUM(F24:F27) -> 122.525 | G37: Treatment 4 | I37: =SUM(I24:I27) -> 8.7755208
A38: TOTAL 2024 (Treatment 5) | B38: 2024 | C38: =$M$4 -> 17.4 | D38: =C38/60 -> 0.29 | E38: =SUM(E26:E28) -> 283.75 | F38: =D38*E38 -> 82.2875 | G38: Treatment 5 | I38: =SUM(I26:I28) -> 14.892708

Sheet Labour Costs (2022-2024)
A1: Year | B1: Item | C1: Treatment 1-1 | D1: Treatment 1-2 | E1: Treatment 1-3 | F1: Treatment 1-4 | G1: Treatment 2-1 | H1: Treatment 2-2 | I1: Treatment 2-3 | J1: Treatment 2-4 | K1: Treatment 3-1 | L1: Treatment 3-2 | M1: Treatment 3-3 | N1: Treatment 3-4 | O1: Treatment 4-1 | P1: Treatment 4-2 | Q1: Treatment 4-3 | R1: Treatment 4-4 | S1: Treatment 5-1 | T1: Treatment 5-2 | U1: Treatment 5-3 | V1: Treatment 5-4
A2: PLANTING LABOUR COSTS
A3: 2022 | B3: Labour Time - Cover Crop Planting (min) | C3: 0 | D3: 0 | E3: 0 | F3: 0 | G3: =30/20 -> 1.5 | H3: =30/20 -> 1.5 | I3: =30/20 -> 1.5 | J3: =30/20 -> 1.5 | K3: =30/20 -> 1.5 | L3: =30/20 -> 1.5 | M3: =30/20 -> 1.5 | N3: =30/20 -> 1.5 | ... V3: =30/20 -> 1.5 | X3: Year | Y3: BC Minimum Wage ($/hr) | Z3: BC Minimum Wage ($/min)
A4: 2022 | B4: Labour Cost - Planting ($) | C4: =SUM(C3:C3)*$Z$4 -> 0 | D4: =SUM(D3:D3)*$Z$4 -> 0 | E4: =SUM(E3:E3)*$Z$4 -> 0 | F4: =SUM(F3:F3)*$Z$4 -> 0 | G4: =SUM(G3:G3)*$Z$4 -> 0.39125 | H4: =SUM(H3:H3)*$Z$4 -> 0.39125 | I4: =SUM(I3:I3)*$Z$4 -> 0.39125 | J4: =SUM(J3:J3)*$Z$4 -> 0.39125 | ... V4: =SUM(V3:V3)*$Z$4 -> 0.39125 | X4: 2022 | Y4: 15.65 | Z4: =Y4/60 -> 0.26083333
A5: 2023 | B5: Labour Time - Cover Crop Planting (min) | C5: 0 | D5: 0 | E5: 0 | F5: 0 | G5: =30/20 -> 1.5 | H5: =30/20 -> 1.5 | I5: =30/20 -> 1.5 | J5: =30/20 -> 1.5 | K5: =30/20 -> 1.5 | L5: =30/20 -> 1.5 | M5: =30/20 -> 1.5 | N5: =30/20 -> 1.5 | ... V5: =30/20 -> 1.5 | X5: 2023 | Y5: 16.75 | Z5: =Y5/60 -> 0.27916667
A6: 2023 | B6: Labour Cost - Planting ($) | C6: =SUM(C5:C5)*$Z$5 -> 0 | D6: =SUM(D5:D5)*$Z$5 -> 0 | E6: =SUM(E5:E5)*$Z$5 -> 0 | F6: =SUM(F5:F5)*$Z$5 -> 0 | G6: =SUM(G5:G5)*$Z$5 -> 0.41875 | H6: =SUM(H5:H5)*$Z$5 -> 0.41875 | I6: =SUM(I5:I5)*$Z$5 -> 0.41875 | J6: =SUM(J5:J5)*$Z$5 -> 0.41875 | ... V6: =SUM(V5:V5)*$Z$5 -> 0.41875 | X6: 2024 | Y6: 17.4 | Z6: =Y6/60 -> 0.29
A7: 2024 | B7: Labour Time - Cover Crop Planting (min) | C7: 0 | D7: 0 | E7: 0 | F7: 0 | G7: =30/20 -> 1.5 | H7: =30/20 -> 1.5 | I7: =30/20 -> 1.5 | J7: =30/20 -> 1.5 | K7: =30/20 -> 1.5 | L7: =30/20 -> 1.5 | M7: =30/20 -> 1.5 | N7: =30/20 -> 1.5 | ... V7: =30/20 -> 1.5
A8: 2024 | B8: Labour Cost - Planting ($) | C8: =SUM(C7:C7)*$Z$6 -> 0 | D8: =SUM(D7:D7)*$Z$6 -> 0 | E8: =SUM(E7:E7)*$Z$6 -> 0 | F8: =SUM(F7:F7)*$Z$6 -> 0 | G8: =SUM(G7:G7)*$Z$6 -> 0.435 | H8: =SUM(H7:H7)*$Z$6 -> 0.435 | I8: =SUM(I7:I7)*$Z$6 -> 0.435 | J8: =SUM(J7:J7)*$Z$6 -> 0.435 | ... V8: =SUM(V7:V7)*$Z$6 -> 0.435
A9: WEEDING LABOUR COSTS
A10: 2022 | B10: Labour Time - Weeding (min) | C10: 46 | D10: 39 | E10: 50 | F10: 71 | G10: 46 | H10: 70 | I10: 65 | J10: 45 | K10: 68 | L10: 81 | M10: 36 | N10: 75 | O10: 42 | P10: 103 | Q10: 30 | R10: 132 | S10: 81 | T10: 35 | U10: 106 | V10: 34
A11: 2022 | B11: Labour Cost - Weeding ($) | C11: =C10*$Z$4 -> 11.998333 | D11: =D10*$Z$4 -> 10.1725 | E11: =E10*$Z$4 -> 13.041667 | F11: =F10*$Z$4 -> 18.519167 | G11: =G10*$Z$4 -> 11.998333 | H11: =H10*$Z$4 -> 18.258333 | I11: =I10*$Z$4 -> 16.954167 | J11: =J10*$Z$4 -> 11.7375 | ... V11: =V10*$Z$4 -> 8.8683333
A12: 2023 | B12: Labour Time - Weeding (min) | C12: 123.5 | D12: 93.916667 | E12: 79.5 | F12: 108.075 | G12: 78.0625 | H12: 88.775 | I12: 102.75 | J12: 88 | K12: 93.2625 | L12: 75.5 | M12: 56.25 | N12: 86.9 | O12: 74.6875 | P12: 114.325 | Q12: 74 | R12: 154.5875 | S12: 97.5 | T12: 63.375 | U12: 117.15 | V12: 41.5
A13: 2023 | B13: Labour Cost - Weeding ($) | C13: =C12*$Z$5 -> 34.477083 | D13: =D12*$Z$5 -> 26.218403 | E13: =E12*$Z$5 -> 22.19375 | F13: =F12*$Z$5 -> 30.170938 | G13: =G12*$Z$5 -> 21.792448 | H13: =H12*$Z$5 -> 24.783021 | I13: =I12*$Z$5 -> 28.684375 | J13: =J12*$Z$5 -> 24.566667 | ... V13: =V12*$Z$5 -> 11.585417
A14: 2024 | B14: Labour Time - Weeding (min) | C14: 227.25 | D14: 155 | E14: 144.25 | F14: 191.25 | G14: 152.75 | H14: 135.5 | I14: 157.75 | J14: 155.75 | K14: 177.5 | L14: 126.25 | M14: 128.75 | N14: 188.65 | O14: 151.5 | P14: 177.5 | Q14: 132.75 | R14: 249.25 | S14: 164.5 | T14: 140.25 | U14: 186.25 | V14: 113.5
A15: 2024 | B15: Labour Cost - Weeding ($) | C15: =C14*$Z$6 -> 65.9025 | D15: =D14*$Z$6 -> 44.95 | E15: =E14*$Z$6 -> 41.8325 | F15: =F14*$Z$6 -> 55.4625 | G15: =G14*$Z$6 -> 44.2975 | H15: =H14*$Z$6 -> 39.295 | I15: =I14*$Z$6 -> 45.7475 | J15: =J14*$Z$6 -> 45.1675 | ... V15: =V14*$Z$6 -> 32.915
A16: HARVEST LABOUR COSTS
A17: 2022 | B17: Labour Time - Bean Harvest (min) | C17: 19 | D17: 21 | E17: 18 | F17: 21 | G17: 15 | H17: 17 | I17: 16 | J17: 24 | K17: 15 | L17: 13 | M17: 24 | N17: 16 | O17: 19 | P17: 10 | Q17: 15 | R17: 9 | S17: 9 | T17: 19 | U17: 8 | V17: 20
A18: 2022 | B18: Labour Time - Carrot Harvest (min) | C18: 4 | D18: 17 | E18: 13 | F18: 14 | G18: 9 | H18: 8 | I18: 10 | J18: 7 | K18: 5 | L18: 5 | M18: 7 | N18: 4 | O18: 5 | P18: 6 | Q18: 4 | R18: 4 | S18: 6 | T18: 5 | U18: 5 | V18: 5
A19: 2022 | B19: Labour Time - Kale Harvest (min) | C19: 1.75 | D19: 2 | E19: 1.5 | F19: 1.75 | G19: 1.5 | H19: 1.75 | I19: 1.25 | J19: 1.75 | K19: 1.75 | L19: 2 | M19: 2 | N19: 1.75 | O19: 1.5 | P19: 2 | Q19: 1.5 | R19: 1.5 | S19: 2 | T19: 2 | U19: 2 | V19: 3
A20: 2022 | B20: Labour Cost - Bean Harvest ($) | C20: =C17*$Z$4 -> 4.9558333 | D20: =D17*$Z$4 -> 5.4775 | E20: =E17*$Z$4 -> 4.695 | F20: =F17*$Z$4 -> 5.4775 | G20: =G17*$Z$4 -> 3.9125 | H20: =H17*$Z$4 -> 4.4341667 | I20: =I17*$Z$4 -> 4.1733333 | J20: =J17*$Z$4 -> 6.26 | ... V20: =V17*$Z$4 -> 5.2166667
A21: 2022 | B21: Labour Cost - Carrot Harvest ($) | C21: =C18*$Z$4 -> 1.0433333 | D21: =D18*$Z$4 -> 4.4341667 | E21: =E18*$Z$4 -> 3.3908333 | F21: =F18*$Z$4 -> 3.6516667 | G21: =G18*$Z$4 -> 2.3475 | H21: =H18*$Z$4 -> 2.0866667 | I21: =I18*$Z$4 -> 2.6083333 | J21: =J18*$Z$4 -> 1.8258333 | ... V21: =V18*$Z$4 -> 1.3041667
A22: 2022 | B22: Labour Cost - Kale Harvest ($) | C22: =C19*$Z$4 -> 0.45645833 | D22: =D19*$Z$4 -> 0.52166667 | E22: =E19*$Z$4 -> 0.39125 | F22: =F19*$Z$4 -> 0.45645833 | G22: =G19*$Z$4 -> 0.39125 | H22: =H19*$Z$4 -> 0.45645833 | I22: =I19*$Z$4 -> 0.32604167 | J22: =J19*$Z$4 -> 0.45645833 | ... V22: =V19*$Z$4 -> 0.7825
A23: 2023 | B23: Labour Time - Bean Harvest (min) | C23: 48 | D23: 44 | E23: 53.75 | F23: 39.75 | G23: 34 | H23: 56.5 | I23: 48.75 | J23: 50.25 | K23: 36.75 | L23: 35.5 | M23: 53 | N23: 44 | O23: 68.5 | P23: 40.5 | Q23: 63.5 | R23: 42.5 | S23: 44.75 | T23: 52 | U23: 50.75 | V23: 63.5
A24: 2023 | B24: Labour Time - Carrot Harvest (min) | C24: 15.5 | D24: 24.5 | E24: 16.75 | F24: 21.5 | G24: 20 | H24: 14.25 | I24: 15.5 | J24: 26.5 | K24: 11.75 | L24: 20 | M24: 16.75 | N24: 17 | O24: 19 | P24: 17 | Q24: 21 | R24: 24 | S24: 13 | T24: 14 | U24: 13 | V24: 10
A25: 2023 | B25: Labour Time - Kale Harvest (min) | C25: 11 | D25: 18.75 | E25: 14.75 | F25: 15.5 | G25: 18.5 | H25: 16.25 | I25: 19.25 | J25: 14.5 | K25: 11.5 | L25: 16 | M25: 15.5 | N25: 9.5 | O25: 13 | P25: 15 | Q25: 14.75 | R25: 15 | S25: 4 | T25: 9.25 | U25: 19 | V25: 15.25
A26: 2023 | B26: Labour Cost - Bean Harvest ($) | C26: =C23*$Z$5 -> 13.4 | D26: =D23*$Z$5 -> 12.283333 | E26: =E23*$Z$5 -> 15.005208 | F26: =F23*$Z$5 -> 11.096875 | G26: =G23*$Z$5 -> 9.4916667 | H26: =H23*$Z$5 -> 15.772917 | I26: =I23*$Z$5 -> 13.609375 | J26: =J23*$Z$5 -> 14.028125 | ... V26: =V23*$Z$5 -> 17.727083
A27: 2023 | B27: Labour Cost - Carrot Harvest ($) | C27: =C24*$Z$5 -> 4.3270833 | D27: =D24*$Z$5 -> 6.8395833 | E27: =E24*$Z$5 -> 4.6760417 | F27: =F24*$Z$5 -> 6.0020833 | G27: =G24*$Z$5 -> 5.5833333 | H27: =H24*$Z$5 -> 3.978125 | I27: =I24*$Z$5 -> 4.3270833 | J27: =J24*$Z$5 -> 7.3979167 | ... V27: =V24*$Z$5 -> 2.7916667
A28: 2023 | B28: Labour Cost - Kale Harvest ($) | C28: =C25*$Z$5 -> 3.0708333 | D28: =D25*$Z$5 -> 5.234375 | E28: =E25*$Z$5 -> 4.1177083 | F28: =F25*$Z$5 -> 4.3270833 | G28: =G25*$Z$5 -> 5.1645833 | H28: =H25*$Z$5 -> 4.5364583 | I28: =I25*$Z$5 -> 5.3739583 | J28: =J25*$Z$5 -> 4.0479167 | ... V28: =V25*$Z$5 -> 4.2572917
A29: 2024 | B29: Labour Time - Bean Harvest (min) | C29: 19 | D29: 32.5 | E29: 53.25 | F29: 49.9 | G29: 38.25 | H29: 43 | I29: 38 | J29: 67.5 | K29: 25.5 | L29: 32.25 | M29: 56 | N29: 54.5 | O29: 49 | P29: 43 | Q29: 56 | R29: 57.5 | S29: 41.5 | T29: 50.5 | U29: 47.25 | V29: 59
A30: 2024 | B30: Labour Time - Carrot Harvest (min) | C30: 26.25 | D30: 31.5 | E30: 27 | F30: 21.75 | G30: 27.75 | H30: 16.5 | I30: 24 | J30: 31.5 | K30: 24 | L30: 12 | M30: 6 | N30: 21.75 | O30: 6 | P30: 4 | Q30: 10 | R30: 20 | S30: 8 | T30: 12.25 | U30: 13 | V30: 7
A31: 2024 | B31: Labour Time - Kale Harvest (min) | C31: 24.5 | D31: 24.75 | E31: 28.25 | F31: 26.5 | G31: 25.25 | H31: 21 | I31: 24 | J31: 20.25 | K31: 24.5 | L31: 26.5 | M31: 29.75 | N31: 26.5 | O31: 23.25 | P31: 24 | Q31: 28.25 | R31: 28.75 | S31: 17.75 | T31: 21.75 | U31: 21.25 | V31: 21.75
A32: 2024 | B32: Labour Cost - Bean Harvest ($) | C32: =C29*$Z$6 -> 5.51 | D32: =D29*$Z$6 -> 9.425 | E32: =E29*$Z$6 -> 15.4425 | F32: =F29*$Z$6 -> 14.471 | G32: =G29*$Z$6 -> 11.0925 | H32: =H29*$Z$6 -> 12.47 | I32: =I29*$Z$6 -> 11.02 | J32: =J29*$Z$6 -> 19.575 | ... V32: =V29*$Z$6 -> 17.11
A33: 2024 | B33: Labour Cost - Carrot Harvest ($) | C33: =C30*$Z$6 -> 7.6125 | D33: =D30*$Z$6 -> 9.135 | E33: =E30*$Z$6 -> 7.83 | F33: =F30*$Z$6 -> 6.3075 | G33: =G30*$Z$6 -> 8.0475 | H33: =H30*$Z$6 -> 4.785 | I33: =I30*$Z$6 -> 6.96 | J33: =J30*$Z$6 -> 9.135 | ... V33: =V30*$Z$6 -> 2.03
A34: 2024 | B34: Labour Cost - Kale Harvest ($) | C34: =C31*$Z$6 -> 7.105 | D34: =D31*$Z$6 -> 7.1775 | E34: =E31*$Z$6 -> 8.1925 | F34: =F31*$Z$6 -> 7.685 | G34: =G31*$Z$6 -> 7.3225 | H34: =H31*$Z$6 -> 6.09 | I34: =I31*$Z$6 -> 6.96 | J34: =J31*$Z$6 -> 5.8725 | ... V34: =V31*$Z$6 -> 6.3075
A35: LIVESTOCK MANAGEMENT LABOUR COSTS
A36: 2022 | B36: Labour Time - Livestock Management (min) | C36: 0 | D36: 0 | E36: 0 | F36: 0 | G36: 0 | H36: 0 | I36: 0 | J36: 0 | K36: 0 | L36: 0 | M36: 0 | N36: 0 | O36: 0 | P36: 0 | Q36: 0 | R36: 0 | S36: 0 | T36: 0 | U36: 0 | V36: 0
A37: 2022 | B37: Labour Cost - Livestock Management ($) | C37: =C36*$Z$4 -> 0 | D37: =D36*$Z$4 -> 0 | E37: =E36*$Z$4 -> 0 | F37: =F36*$Z$4 -> 0 | G37: =G36*$Z$4 -> 0 | H37: =H36*$Z$4 -> 0 | I37: =I36*$Z$4 -> 0 | J37: =J36*$Z$4 -> 0 | ... V37: =V36*$Z$4 -> 0
A38: 2023 | B38: Labour Time - Livestock Management (min) | C38: 0 | D38: 0 | E38: 0 | F38: 0 | G38: 0 | H38: 0 | I38: 0 | J38: 0 | K38: 0 | L38: 0 | M38: 0 | N38: 0 | O38: =(5*60)/8 -> 37.5 | P38: =(5*60)/8 -> 37.5 | Q38: =(5*60)/8 -> 37.5 | R38: =(5*60)/8 -> 37.5 | S38: =(5*60)/8 -> 37.5 | T38: =(5*60)/8 -> 37.5 | U38: =(5*60)/8 -> 37.5 | V38: =(5*60)/8 -> 37.5 | W38: This is an approximate number.
A39: 2023 | B39: Labour Cost - Livestock Management ($) | C39: =C38*$Z$5 -> 0 | D39: =D38*$Z$5 -> 0 | E39: =E38*$Z$5 -> 0 | F39: =F38*$Z$5 -> 0 | G39: =G38*$Z$5 -> 0 | H39: =H38*$Z$5 -> 0 | I39: =I38*$Z$5 -> 0 | J39: =J38*$Z$5 -> 0 | ... V39: =V38*$Z$5 -> 10.46875
A40: 2024 | B40: Labour Time - Livestock Management (min) | O40: =(5*60)/8 -> 37.5 | P40: =(5*60)/8 -> 37.5 | Q40: =(5*60)/8 -> 37.5 | R40: =(5*60)/8 -> 37.5 | S40: =(5*60)/8 -> 37.5 | T40: =(5*60)/8 -> 37.5 | U40: =(5*60)/8 -> 37.5 | V40: =(5*60)/8 -> 37.5
A41: 2024 | B41: Labour Cost - Livestock Management ($) | C41: =C40*$Z$6 -> 0 | D41: =D40*$Z$6 -> 0 | E41: =E40*$Z$6 -> 0 | F41: =F40*$Z$6 -> 0 | G41: =G40*$Z$6 -> 0 | H41: =H40*$Z$6 -> 0 | I41: =I40*$Z$6 -> 0 | J41: =J40*$Z$6 -> 0 | ... V41: =V40*$Z$6 -> 10.875

Sheet Crop Prices (2022-2024)
A1: WHOLESALE PRICES - CONVENTIONAL
A2: Crop | B2: Type | C2: Year | D2: Unit | E2: Unit type | F2: Unit to g | G2: Low Price ($) | H2: High Price ($) | I2: Average Price ($) | J2: Average price ($/g) | K2: Average price ($/kg) | L2: Source | M2: Notes
A3: Green beans (Vancouver) | B3: Conventional Wholesale - CTN 20 LBS | C3: 2022 | D3: 20 | E3: lbs | F3: =D3*453.59237 -> 9071.8474 | G3: 20 | H3: 61.7 | I3: =AVERAGE(G3:H3) -> 40.85 | J3: =I3/F3 -> 0.0045029417 | K3: =J3*1000 -> 4.5029417 | L3: Agriculture & Agri-Food Canada | M3: Used green bean prices as proxy for purple beans
A4: Green beans (Vancouver) | B4: Conventional Wholesale - CTN 20 LBS | C4: 2023 | D4: 20 | E4: lbs | F4: =D4*453.59237 -> 9071.8474 | G4: 28 | H4: 58.5 | I4: =AVERAGE(G4:H4) -> 43.25 | J4: =I4/F4 -> 0.0047674964 | K4: =J4*1000 -> 4.7674964 | L4: Agriculture & Agri-Food Canada
A5: Green beans (Vancouver) | B5: Conventional Wholesale - CTN 20 LBS | C5: 2024 | D5: 20 | E5: lbs | F5: =D5*453.59237 -> 9071.8474 | G5: 32 | H5: 57 | I5: =AVERAGE(G5:H5) -> 44.5 | J5: =I5/F5 -> 0.0049052853 | K5: =J5*1000 -> 4.9052853 | L5: Agriculture & Agri-Food Canada
A6: Carrots (Vancouver) | B6: Conventional Wholesale - unspecified Ctn 10x5 lbs BC | C6: 2022 | D6: 50 | E6: lbs | F6: =D6*453.59237 -> 22679.619 | G6: 35.75 | H6: 45 | I6: =AVERAGE(G6:H6) -> 40.375 | J6: =I6/F6 -> 0.0017802328 | K6: =J6*1000 -> 1.7802328 | L6: Agriculture & Agri-Food Canada | M6: Used the unspecified prices as the tops were removed. Used 10x5 lbs line - not available for 2024
A7: Carrots (Vancouver) | B7: Conventional Wholesale - unspecified Ctn 10x5 lbs BC | C7: 2023 | D7: 50 | E7: lbs | F7: =D7*453.59237 -> 22679.619 | G7: 43.5 | H7: 49.45 | I7: =AVERAGE(G7:H7) -> 46.475 | J7: =I7/F7 -> 0.0020491967 | K7: =J7*1000 -> 2.0491967 | L7: Agriculture & Agri-Food Canada | M7: Used the unspecified prices as the tops were removed. Used 10x5 lbs line - doesn't cover all three years
A8: Carrots (Vancouver) | B8: Conventional Wholesale - unspecified Bag 24x2 lbs BC | C8: 2024 | D8: 48 | E8: lbs | F8: =D8*453.59237 -> 21772.434 | G8: 28 | H8: 36.5 | I8: =AVERAGE(G8:H8) -> 32.25 | J8: =I8/F8 -> 0.0014812308 | K8: =J8*1000 -> 1.4812308 | L8: Agriculture & Agri-Food Canada | M8: Used the unspecified prices as the tops were removed. Used 24 x 2 lbs bag line - not available for 2022
A9: Kale (Vancouver) | B9: Conventional Wholesale - 24 CT | C9: 2022 | D9: 20 | E9: lbs | F9: =D9*453.59237 -> 9071.8474 | G9: 23.75 | H9: 29.95 | I9: =AVERAGE(G9:H9) -> 26.85 | J9: =I9/F9 -> 0.0029597059 | K9: =J9*1000 -> 2.9597059 | L9: Agriculture & Agri-Food Canada | M9: Used conventional green kale prices (no Red Russian). Assumed that 24CT = 20# (based on Organic BC reporting)
A10: Kale (Vancouver) | B10: Conventional Wholesale - 24 CT | C10: 2023 | D10: 20 | E10: lbs | F10: =D10*453.59237 -> 9071.8474 | G10: 24 | H10: 36.3 | I10: =AVERAGE(G10:H10) -> 30.15 | J10: =I10/F10 -> 0.0033234686 | K10: =J10*1000 -> 3.3234686 | L10: Agriculture & Agri-Food Canada
A11: Kale (Vancouver) | B11: Conventional Wholesale - 24 CT | C11: 2024 | D11: 20 | E11: lbs | F11: =D11*453.59237 -> 9071.8474 | G11: =AVERAGE(G9:G10) -> 23.875 | H11: =AVERAGE(H9:H10) -> 33.125 | I11: =AVERAGE(G11:H11) -> 28.5 | J11: =I11/F11 -> 0.0031415872 | K11: =J11*1000 -> 3.1415872 | L11: Agriculture & Agri-Food Canada
A13: WHOLESALE PRICES - ORGANIC
A14: Organic Crops | B14: Type | C14: Year | D14: Unit | E14: Unit type | F14: Unit to g | G14: Low Price ($) | H14: High Price ($) | I14: Average Price ($) | J14: Average price ($/g)
A15: Green beans (BC) | B15: Organic Wholesale - green bulk 20# BC | C15: 2022 | D15: 20 | E15: lbs | F15: =D15*453.59237 -> 9071.8474 | G15: na | H15: na | I15: 65.4 | J15: =I15/F15 -> 0.007209116 | K15: =J15*1000 -> 7.209116 | L15: Organic BC - SEP 2022 | M15: Used September data as this was when most of the crops were harvested. Used green instead of purple beans.
A16: Green beans (BC) | B16: Organic Wholesale - green bulk 20# BC | C16: 2023 | D16: 20 | E16: lbs | F16: =D16*453.59237 -> 9071.8474 | G16: na | H16: na | I16: 71.5 | J16: =I16/F16 -> 0.0078815259 | K16: =J16*1000 -> 7.8815259 | L16: Organic BC - AUG 2023 | M16: Used August data - no September available. Used green instead of purple beans.
A17: Green beans (BC) | B17: Organic Wholesale - green bulk 20# BC | C17: 2024 | D17: 20 | E17: lbs | F17: =D17*453.59237 -> 9071.8474 | G17: na | H17: na | I17: 59.8 | J17: =I17/F17 -> 0.0065918216 | K17: =J17*1000 -> 6.5918216 | L17: Organic BC - SEP 2024 | M17: Used September data as this was when most of the crops were harvested. Used green instead of purple beans.
A18: Carrots (BC) | B18: Organic Wholesale - table 25# BC | C18: 2022 | D18: 25 | E18: lbs | F18: =D18*453.59237 -> 11339.809 | G18: na | H18: na | I18: 52.1 | J18: =I18/F18 -> 0.0045944335 | K18: =J18*1000 -> 4.5944335 | L18: Organic BC - SEP 2022 | M18: Used September data as this was when most of the crops were harvested. Looked at table carrots.
A19: Carrots (BC) | B19: Organic Wholesale - table 25# BC | C19: 2023 | D19: 25 | E19: lbs | F19: =D19*453.59237 -> 11339.809 | G19: na | H19: na | I19: 58.8 | J19: =I19/F19 -> 0.0051852724 | K19: =J19*1000 -> 5.1852724 | L19: Organic BC - AUG 2023 | M19: Used August data - no September available. Looked at table carrots.
A20: Carrots (BC) | B20: Organic Wholesale - table 25# CA | C20: 2024 | D20: 25 | E20: lbs | F20: =D20*453.59237 -> 11339.809 | G20: na | H20: na | I20: 58.1 | J20: =I20/F20 -> 0.005123543 | K20: =J20*1000 -> 5.123543 | L20: Organic BC - SEP 2024 | M20: Used September data as this was when most of the crops were harvested. Looked at table carrots - no BC.
A21: Kale (BC) | B21: Organic Wholesale - green curly 24CT BC | C21: 2022 | D21: 20 | E21: lbs | F21: =D21*453.59237 -> 9071.8474 | G21: na | H21: na | I21: 64.2 | J21: =I21/F21 -> 0.0070768386 | K21: =J21*1000 -> 7.0768386 | L21: Organic BC - SEP 2022 | M21: Used September data for green curly kale (no red Russian).
A22: Kale (BC) | B22: Organic Wholesale - green curly 24CT BC | C22: 2023 | D22: 20 | E22: lbs | F22: =D22*453.59237 -> 9071.8474 | G22: na | H22: na | I22: 68.4 | J22: =I22/F22 -> 0.0075398094 | K22: =J22*1000 -> 7.5398094 | L22: Organic BC - AUG 2023 | M22: Used August data for green curly kale (no red Russian).
A23: Kale (BC) | B23: Organic Wholesale - green curly 24CT BC | C23: 2024 | D23: 20 | E23: lbs | F23: =D23*453.59237 -> 9071.8474 | G23: na | H23: na | I23: 57.2 | J23: =I23/F23 -> 0.0063052207 | K23: =J23*1000 -> 6.3052207 | L23: Organic BC - SEP 2024 | M23: Used September data for green curly kale (no red Russian).
A25: DIRECT MARKETING PRICES - CONVENTIONAL
A26: Crop | B26: Type | C26: Year | D26: Unit | E26: Unit type | F26: Unit to g | G26: Low Price ($) | H26: High Price ($) | I26: Average Price ($) | J26: Average price ($/g) | L26: Source | M26: Notes
A27: Green beans | B27: Conventional Direct Marketing | C27: 2022 | D27: 1 | E27: lbs | F27: =D27*453.59237 -> 453.59237 | I27: =(I3*1.7)/20 -> 3.47225 | J27: =I27/F27 -> 0.0076550009 | K27: =J27*1000 -> 7.6550009 | L27: =K3*1.7 -> 7.6550009 | M27: I multiplied the wholesale average price by 1.7 and divided by the unit number to get this price.
A28: Green beans | B28: Conventional Direct Marketing | C28: 2023 | D28: 1 | E28: lbs | F28: =D28*453.59237 -> 453.59237 | I28: =(I4*1.7)/20 -> 3.67625 | J28: =I28/F28 -> 0.0081047439 | K28: =J28*1000 -> 8.1047439 | L28: =K4*1.7 -> 8.1047439
A29: Green beans | B29: Conventional Direct Marketing | C29: 2024 | D29: 1 | E29: lbs | F29: =D29*453.59237 -> 453.59237 | I29: =(I5*1.7)/20 -> 3.7825 | J29: =I29/F29 -> 0.0083389851 | K29: =J29*1000 -> 8.3389851 | L29: =K5*1.7 -> 8.3389851
A30: Carrots | B30: Conventional Direct Marketing | C30: 2022 | D30: 1 | E30: lbs | F30: =D30*453.59237 -> 453.59237 | I30: =(I6*1.7)/50 -> 1.37275 | J30: =I30/F30 -> 0.0030263957 | K30: =J30*1000 -> 3.0263957 | L30: =K6*1.7 -> 3.0263957
A31: Carrots | B31: Conventional Direct Marketing | C31: 2023 | D31: 1 | E31: lbs | F31: =D31*453.59237 -> 453.59237 | I31: =(I7*1.7)/50 -> 1.58015 | J31: =I31/F31 -> 0.0034836344 | K31: =J31*1000 -> 3.4836344 | L31: =K7*1.7 -> 3.4836344
A32: Carrots | B32: Conventional Direct Marketing | C32: 2024 | D32: 1 | E32: lbs | F32: =D32*453.59237 -> 453.59237 | I32: =(I8*1.7)/48 -> 1.1421875 | J32: =I32/F32 -> 0.0025180924 | K32: =J32*1000 -> 2.5180924 | L32: =K8*1.7 -> 2.5180924
A33: Kale | B33: Conventional Direct Marketing | C33: 2022 | D33: 1 | E33: lbs | F33: =D33*453.59237 -> 453.59237 | I33: =(I9*1.7)/20 -> 2.28225 | J33: =I33/F33 -> 0.0050315 | K33: =J33*1000 -> 5.0315 | L33: =K9*1.7 -> 5.0315
A34: Kale | B34: Conventional Direct Marketing | C34: 2023 | D34: 1 | E34: lbs | F34: =D34*453.59237 -> 453.59237 | I34: =(I10*1.7)/20 -> 2.56275 | J34: =I34/F34 -> 0.0056498966 | K34: =J34*1000 -> 5.6498966 | L34: =K10*1.7 -> 5.6498966
A35: Kale | B35: Conventional Direct Marketing | C35: 2024 | D35: 1 | E35: lbs | F35: =D35*453.59237 -> 453.59237 | I35: =(I11*1.7)/20 -> 2.4225 | J35: =I35/F35 -> 0.0053406983 | K35: =J35*1000 -> 5.3406983 | L35: =K11*1.7 -> 5.3406983
A37: DIRECT MARKETING PRICES - ORGANIC
A38: Organic Crop | B38: Type | C38: Year | D38: Unit | E38: Unit type | F38: Unit to g | G38: Low Price ($) | H38: High Price ($) | I38: Average Price ($) | J38: Average price ($/g) | L38: Source | M38: Notes
A39: Green beans | B39: Organic Direct Marketing | C39: 2022 | D39: 1 | E39: lbs | F39: =D39*453.59237 -> 453.59237 | I39: =(I15*1.8)/D15 -> 5.886 | J39: =I39/F39 -> 0.012976409 | K39: =J39*1000 -> 12.976409 | L39: =K15*1.8 -> 12.976409 | M39: I multiplied the wholesale average price by 1.8 and divided by the unit number to get this price.
A40: Green beans | B40: Organic Direct Marketing | C40: 2023 | D40: 1 | E40: lbs | F40: =D40*453.59237 -> 453.59237 | I40: =(I16*1.8)/D16 -> 6.435 | J40: =I40/F40 -> 0.014186747 | K40: =J40*1000 -> 14.186747 | L40: =K16*1.8 -> 14.186747
A41: Green beans | B41: Organic Direct Marketing | C41: 2024 | D41: 1 | E41: lbs | F41: =D41*453.59237 -> 453.59237 | I41: =(I17*1.8)/D17 -> 5.382 | J41: =I41/F41 -> 0.011865279 | K41: =J41*1000 -> 11.865279 | L41: =K17*1.8 -> 11.865279
A42: Carrots | B42: Organic Direct Marketing | C42: 2022 | D42: 1 | E42: lbs | F42: =D42*453.59237 -> 453.59237 | I42: =(I18*1.8)/D18 -> 3.7512 | J42: =I42/F42 -> 0.0082699804 | K42: =J42*1000 -> 8.2699804 | L42: =K18*1.8 -> 8.2699804
A43: Carrots | B43: Organic Direct Marketing | C43: 2023 | D43: 1 | E43: lbs | F43: =D43*453.59237 -> 453.59237 | I43: =(I19*1.8)/D19 -> 4.2336 | J43: =I43/F43 -> 0.0093334903 | K43: =J43*1000 -> 9.3334903 | L43: =K19*1.8 -> 9.3334903
A44: Carrots | B44: Organic Direct Marketing | C44: 2024 | D44: 1 | E44: lbs | F44: =D44*453.59237 -> 453.59237 | I44: =(I20*1.8)/D20 -> 4.1832 | J44: =I44/F44 -> 0.0092223774 | K44: =J44*1000 -> 9.2223774 | L44: =K20*1.8 -> 9.2223774
A45: Kale | B45: Organic Direct Marketing | C45: 2022 | D45: 1 | E45: lbs | F45: =D45*453.59237 -> 453.59237 | I45: =(I21*1.8)/D21 -> 5.778 | J45: =I45/F45 -> 0.01273831 | K45: =J45*1000 -> 12.73831 | L45: =K21*1.8 -> 12.73831
A46: Kale | B46: Organic Direct Marketing | C46: 2023 | D46: 1 | E46: lbs | F46: =D46*453.59237 -> 453.59237 | I46: =(I22*1.8)/D22 -> 6.156 | J46: =I46/F46 -> 0.013571657 | K46: =J46*1000 -> 13.571657 | L46: =K22*1.8 -> 13.571657
A47: Kale | B47: Organic Direct Marketing | C47: 2024 | D47: 1 | E47: lbs | F47: =D47*453.59237 -> 453.59237 | I47: =(I23*1.8)/D23 -> 5.148 | J47: =I47/F47 -> 0.011349397 | K47: =J47*1000 -> 11.349397 | L47: =K23*1.8 -> 11.349397

Sheet Crop Price Summary (AAFC)
A1: Annual Summary of Weekly Wholesale to Retail Market Prices
A2: Report Generated on 2025-10-25 16:07:59
A3: Wholesale-Vancouver
A4: Commodity | B4: Variety | C4: Origin | D4: Unit Quantity | E4: Grade | F4: 2020 | H4: 2021 | J4: 2022 | L4: 2023 | N4: 2024
F5: Low | G5: High | H5: Low | I5: High | J5: Low | K5: High | L5: Low | M5: High | N5: Low | O5: High
A6: Beans | B6: Cranberry | C6: MEXICO | D6: Ctn 10 lbs | E6: N/A | F6: - | G6: - | H6: 35 | I6: 35 | J6: - | K6: - | L6: - | M6: - | N6: - | O6: -
D7: Ctn 14 lbs | E7: N/A | F7: - | G7: - | H7: - | I7: - | J7: 45 | K7: 45 | L7: - | M7: - | N7: - | O7: -
D8: Ctn 15 lbs | E8: N/A | F8: - | G8: - | H8: 39 | I8: 63.5 | J8: - | K8: - | L8: - | M8: - | N8: - | O8: -
B9: Fava | C9: British Columbia | D9: Ctn 25 lbs | E9: Fancy | F9: 19.85 | G9: 40 | H9: - | I9: - | J9: - | K9: - | L9: - | M9: - | N9: - | O9: -
C10: California | D10: Ctn 1,11 Bu | E10: United States Number 1 | F10: - | G10: - | H10: 46 | I10: 52 | J10: - | K10: - | L10: - | M10: - | N10: - | O10: -
D11: Ctn 25 lbs | E11: United States Number 1 | F11: - | G11: - | H11: 30 | I11: 30 | J11: - | K11: - | L11: - | M11: - | N11: - | O11: -
C12: MEXICO | D12: Ctn 1,11 Bu | E12: N/A | F12: - | G12: - | H12: 40 | I12: 62 | J12: - | K12: - | L12: - | M12: - | N12: - | O12: -
B13: French | C13: California | D13: Ctn 6X340 Gr | E13: United States Number 1 | F13: - | G13: - | H13: - | I13: - | J13: - | K13: - | L13: - | M13: - | N13: 25.25 | O13: 25.26
C14: MEXICO | D14: Ctn 12X340 Gr | E14: N/A | F14: - | G14: - | H14: - | I14: - | J14: - | K14: - | L14: 58 | M14: 61.5 | N14: - | O14: -
D15: Ctn 6X340 Gr | E15: N/A | F15: - | G15: - | H15: - | I15: - | J15: - | K15: - | L15: 25.25 | M15: 25.25 | N15: - | O15: -
D16: Ctn 30 lbs | E16: N/A | F16: 53.7 | G16: 53.7 | H16: - | I16: - | J16: - | K16: - | L16: - | M16: - | N16: - | O16: -
D17: Ctn 5X907 Gr | E17: N/A | F17: - | G17: - | H17: - | I17: - | J17: - | K17: - | L17: 25.25 | M17: 58 | N17: - | O17: -
C18: UNITED STATES | D18: Ctn 6X340 Gr | E18: N/A | F18: - | G18: - | H18: - | I18: - | J18: - | K18: - | L18: - | M18: - | N18: 25.25 | O18: 25.25
B19: Garbanzo | C19: British Columbia | D19: Ctn 15 lbs | E19: N/A | F19: - | G19: - | H19: - | I19: - | J19: - | K19: - | L19: 82 | M19: 82 | N19: - | O19: -
B20: Green | C20: British Columbia | D20: Ctn 30 lbs | E20: N/A | F20: 58.5 | G20: 58.5 | H20: 58 | I20: 61 | J20: - | K20: - | L20: - | M20: - | N20: 68 | O20: 73
D21: Ctn 25 lbs | E21: N/A | F21: - | G21: - | H21: - | I21: - | J21: - | K21: - | L21: 35 | M21: 39.5 | N21: - | O21: -
D22: Ctn 20 lbs | E22: N/A | F22: 32 | G22: 54.75 | H22: 39.5 | I22: 48 | J22: 20 | K22: 61.7 | L22: 28 | M22: 58.5 | N22: 32 | O22: 57
C23: California | D23: Ctn 20 lbs | E23: United States Number 1 | F23: - | G23: - | H23: - | I23: - | J23: - | K23: - | L23: 30 | M23: 52.5 | N23: - | O23: -
D24: Ctn 28 lbs | E24: N/A | F24: - | G24: - | H24: - | I24: - | J24: - | K24: - | L24: 50 | M24: 51.75 | N24: - | O24: -
E25: United States Number 1 | F25: - | G25: - | H25: - | I25: - | J25: - | K25: - | L25: 50 | M25: 50 | N25: 50 | O25: 83.5
D26: Ctn 30 lbs | E26: United States Number 1 | F26: 30 | G26: 53.75 | H26: 48 | I26: 48 | J26: 69 | K26: 80 | L26: 60 | M26: 62 | N26: 49 | O26: 65
D27: Ctn 1,11 Bu | E27: United States Number 1 | F27: - | G27: - | H27: 37 | I27: 53.75 | J27: - | K27: - | L27: - | M27: - | N27: 23.5 | O27: 81
D28: Ctn 1 Bu | E28: United States Number 1 | F28: - | G28: - | H28: - | I28: - | J28: 48.5 | K28: 48.5 | L28: - | M28: - | N28: - | O28: -
D29: Ctn 12X454 Gr | E29: United States Number 1 | F29: - | G29: - | H29: - | I29: - | J29: - | K29: - | L29: 23.5 | M29: 23.5 | N29: - | O29: -
D30: Crt 1,11 Bu | E30: United States Number 1 | F30: - | G30: - | H30: - | I30: - | J30: - | K30: - | L30: - | M30: - | N30: 58 | O30: 86
D31: Ctn 25 lbs | E31: United States Number 1 | F31: - | G31: - | H31: - | I31: - | J31: - | K31: - | L31: 53.7 | M31: 53.7 | N31: - | O31: -
C32: MEXICO | D32: Bag 25 lbs | E32: N/A | F32: 56 | G32: 56 | H32: 34.5 | I32: 57 | J32: - | K32: - | L32: 40 | M32: 100 | N32: - | O32: -
D33: Ctn 25 lbs | E33: N/A | F33: - | G33: - | H33: 40.5 | I33: 72 | J33: - | K33: - | L33: 66 | M33: 76.75 | N33: 69 | O33: 86.5
D34: Ctn 28 lbs | E34: N/A | F34: - | G34: - | H34: - | I34: - | J34: - | K34: - | L34: 63.75 | M34: 66 | N34: 58 | O34: 61
D35: Crt 1,11 Bu | E35: N/A | F35: - | G35: - | H35: - | I35: - | J35: - | K35: - | L35: 73 | M35: 73 | N35: 62.75 | O35: 74
D36: Bag 30 lbs | E36: N/A | F36: 48 | G36: 60 | H36: 38 | I36: 58 | J36: - | K36: - | L36: - | M36: - | N36: - | O36: -
D37: Ctn 1,11 Bu | E37: N/A | F37: - | G37: - | H37: - | I37: - | J37: - | K37: - | L37: - | M37: - | N37: 60.5 | O37: 62
D38: Ctn 10 lbs | E38: N/A | F38: - | G38: - | H38: 42.5 | I38: 42.5 | J38: - | K38: - | L38: - | M38: - | N38: - | O38: -
D39: Ctn 30 lbs | E39: N/A | F39: 35 | G39: 58.5 | H39: 33 | I39: 57 | J39: 40 | K39: 120 | L39: 40 | M39: 76.75 | N39: 39 | O39: 68.5
D40: Ctn 5 lbs | E40: N/A | F40: - | G40: - | H40: - | I40: - | J40: - | K40: - | L40: - | M40: - | N40: 13.5 | O40: 20
C41: UNITED STATES | D41: Bag 30 lbs | E41: United States Number 1 | F41: - | G41: - | H41: - | I41: - | J41: 42 | K41: 58 | L41: - | M41: - | N41: - | O41: -
B42: Organic-Green | C42: British Columbia | D42: Ctn 20 lbs | E42: N/A | F42: - | G42: - | H42: 44 | I42: 60.5 | J42: - | K42: - | L42: - | M42: - | N42: 53.5 | O42: 53.5
C43: California | D43: Ctn 30 lbs | E43: United States Number 1 | F43: - | G43: - | H43: 56.85 | I43: 56.85 | J43: - | K43: - | L43: - | M43: - | N43: - | O43: -
C44: MEXICO | D44: Ctn 25 lbs | E44: N/A | F44: - | G44: - | H44: 48.85 | I44: 68.85 | J44: - | K44: - | L44: - | M44: - | N44: - | O44: -
D45: Ctn 12X12 Oz | E45: N/A | F45: - | G45: - | H45: - | I45: - | J45: - | K45: - | L45: - | M45: - | N45: 48.85 | O45: 48.85
D46: Ctn 15 lbs | E46: N/A | F46: - | G46: - | H46: 38.85 | I46: 56.85 | J46: - | K46: - | L46: - | M46: - | N46: - | O46: -
D47: Ctn 28 lbs | E47: N/A | F47: - | G47: - | H47: - | I47: - | J47: - | K47: - | L47: 52.85 | M47: 52.85 | N47: - | O47: -
B48: Romano | C48: British Columbia | D48: Ctn 30 lbs | E48: N/A | F48: - | G48: - | H48: - | I48: - | J48: - | K48: - | L48: 76 | M48: 76 | N48: 68 | O48: 72
C49: California | D49: Ctn 25 lbs | E49: United States Number 1 | F49: - | G49: - | H49: - | I49: - | J49: - | K49: - | L49: - | M49: - | N49: 53.5 | O49: 60
C50: MEXICO | D50: Ctn 13 lbs | E50: N/A | F50: - | G50: - | H50: - | I50: - | J50: - | K50: - | L50: 42 | M50: 50 | N50: 46.5 | O50: 46.5
D51: Ctn 10 lbs | E51: N/A | F51: - | G51: - | H51: - | I51: - | J51: - | K51: - | L51: 35 | M51: 45 | N51: 38 | O51: 38
D52: Ctn 15 lbs | E52: N/A | F52: - | G52: - | H52: - | I52: - | J52: - | K52: - | L52: 35 | M52: 35 | N52: 38 | O52: 55.5
B53: White | C53: California | D53: Ctn 30 lbs | E53: United States Number 1 | F53: - | G53: - | H53: - | I53: - | J53: 82.25 | K53: 134.9 | L53: 98 | M53: 100 | N53: - | O53: -
D54: Bag 30 lbs | E54: United States Number 1 | F54: - | G54: - | H54: - | I54: - | J54: 78.5 | K54: 100 | L54: - | M54: - | N54: - | O54: -
C55: MEXICO | D55: Ctn 25 lbs | E55: N/A | F55: - | G55: - | H55: - | I55: - | J55: 100 | K55: 120 | L55: 100 | M55: 100 | N55: - | O55: -
D56: Ctn 30 lbs | E56: N/A | F56: - | G56: - | H56: - | I56: - | J56: - | K56: - | L56: 72 | M56: 85 | N56: - | O56: -
D57: Ctn 10 lbs | E57: N/A | F57: - | G57: - | H57: - | I57: - | J57: - | K57: - | L57: 42 | M57: 45 | N57: - | O57: -
B58: Yellow | C58: British Columbia | D58: Ctn 20 lbs | E58: N/A | F58: 39.75 | G58: 48.75 | H58: - | I58: - | J58: 32 | K58: 67.8 | L58: 30 | M58: 76 | N58: 59 | O58: 63
A59: Carrots | B59: Bchd | C59: British Columbia | D59: Ctn 24 | E59: Canada Number 1 | F59: - | G59: - | H59: - | I59: - | J59: - | K59: - | L59: 24 | M59: 30.5 | N59: - | O59: -
D60: Ctn 24 Bchd | E60: Canada Number 1 | F60: 24 | G60: 35 | H60: 21.5 | I60: 30 | J60: 23.5 | K60: 36.75 | L60: 21 | M60: 44.85 | N60: 28 | O60: 41.75
C61: California | D61: Ctn 24 Bchd | E61: United States Number 1 | F61: - | G61: - | H61: 30 | I61: 36 | J61: 20 | K61: 49 | L61: 20 | M61: 56.75 | N61: - | O61: -
C62: MEXICO | D62: Ctn 24 Bchd | E62: N/A | F62: 29 | G62: 37.55 | H62: 26 | I62: 35 | J62: 30 | K62: 43 | L62: 20 | M62: 46.1 | N62: 23.75 | O62: 48
C63: UNITED STATES | D63: Ctn 24 Bchd | E63: United States Number 1 | F63: - | G63: - | H63: - | I63: - | J63: - | K63: - | L63: - | M63: - | N63: 37 | O63: 48.5
B64: Jumbo | C64: Arizona | D64: Ctn 50 lbs Jbo | E64: United States Number 1 | F64: - | G64: - | H64: - | I64: - | J64: - | K64: - | L64: - | M64: - | N64: 49.25 | O64: 56
C65: British Columbia | D65: Ctn 50 lbs Jbo | E65: Canada Number 1 | F65: 26 | G65: 41.5 | H65: 31.75 | I65: 34.75 | J65: 40 | K65: 48.2 | L65: - | M65: - | N65: 36.75 | O65: 61.25
D66: Ctn 50 lbs | E66: Canada Number 1 | F66: - | G66: - | H66: - | I66: - | J66: - | K66: - | L66: 38.5 | M66: 60.75 | N66: 45.25 | O66: 45.25
C67: CANADA | D67: Ctn 50 lbs | E67: Canada Number 1 | F67: - | G67: - | H67: - | I67: - | J67: - | K67: - | L67: 47.5 | M67: 47.5 | N67: - | O67: -
C68: CHINA | D68: Ctn 10 lbs | E68: N/A | F68: - | G68: - | H68: - | I68: - | J68: - | K68: - | L68: - | M68: - | N68: 18 | O68: 25
D69: Ctn 10 kg | E69: N/A | F69: 9 | G69: 18.75 | H69: - | I69: - | J69: - | K69: - | L69: 12.85 | M69: 25 | N69: - | O69: -
D70: Ctn 22 lbs | E70: N/A | F70: - | G70: - | H70: 9.5 | I70: 20.5 | J70: - | K70: - | L70: - | M70: - | N70: - | O70: -
C71: California | D71: Ctn 50 lbs Jbo | E71: United States Number 1 | F71: 30 | G71: 45 | H71: 31.75 | I71: 38 | J71: 34 | K71: 53 | L71: 41.25 | M71: 48 | N71: 35.5 | O71: 54.5
E72: N/A | F72: 31.75 | G72: 31.75 | H72: - | I72: - | J72: - | K72: - | L72: - | M72: - | N72: - | O72: -
D73: Ctn 50 lbs | E73: United States Number 1 | F73: - | G73: - | H73: 36.3 | I73: 45.5 | J73: - | K73: - | L73: 36 | M73: 58.75 | N73: - | O73: -
C74: MEXICO | D74: Ctn 50 lbs | E74: N/A | F74: - | G74: - | H74: - | I74: - | J74: - | K74: - | L74: 42.5 | M74: 42.5 | N74: - | O74: -
C75: UNITED STATES | D75: Ctn 50 lbs Jbo | E75: United States Number 1 | F75: - | G75: - | H75: - | I75: - | J75: - | K75: - | L75: - | M75: - | N75: 46 | O75: 46
B76: Mini | C76: British Columbia | D76: Ctn 15X2 lbs | E76: Canada Number 1 | F76: 33 | G76: 33 | H76: 34.5 | I76: 34.5 | J76: - | K76: - | L76: - | M76: - | N76: 39.75 | O76: 48
D77: Ctn 30X1 lbs | E77: Canada Number 1 | F77: 25 | G77: 35.25 | H77: 35.5 | I77: 36 | J77: 38.75 | K77: 46.4 | L77: 33 | M77: 45.5 | N77: 35 | O77: 48
C78: California | D78: Ctn 30X1 lbs | E78: United States Number 1 | F78: 35.75 | G78: 38 | H78: 33 | I78: 38.75 | J78: 30 | K78: 46.4 | L78: 41 | M78: 46.7 | N78: 42 | O78: 60
D79: Ctn 15X2 lbs | E79: United States Number 1 | F79: - | G79: - | H79: 30 | I79: 38.45 | J79: - | K79: - | L79: - | M79: - | N79: 48 | O79: 48
C80: Washington | D80: Ctn 15X2 lbs | E80: United States Number 1 | F80: 35.75 | G80: 35.75 | H80: - | I80: - | J80: - | K80: - | L80: - | M80: - | N80: - | O80: -
B81: Organic-Rainbow | C81: California | D81: Ctn 24 Bchd | E81: United States Number 1 | F81: 48.75 | G81: 75 | H81: - | I81: - | J81: - | K81: - | L81: 71.25 | M81: 90 | N81: 46.85 | O81: 85.25
D82: Ctn 24X2 lbs | E82: United States Number 1 | F82: 60.5 | G82: 69 | H82: 38.25 | I82: 69.5 | J82: 38.25 | K82: 78.7 | L82: 72.6 | M82: 81.75 | N82: 68.85 | O82: 75.25
D83: Ctn 12X12 Oz | E83: United States Number 1 | F83: - | G83: - | H83: - | I83: - | J83: - | K83: - | L83: 27 | M83: 34.5 | N83: - | O83: -
B84: Organic-Unspecified | C84: British Columbia | D84: Ctn 24X2 lbs | E84: N/A | F84: - | G84: - | H84: - | I84: - | J84: - | K84: - | L84: - | M84: - | N84: 69 | O84: 69
E85: Canada Number 1 | F85: - | G85: - | H85: - | I85: - | J85: - | K85: - | L85: 62.5 | M85: 68 | N85: 65 | O85: 80.35
D86: Ctn 10X5 lbs | E86: Canada Number 1 | F86: - | G86: - | H86: - | I86: - | J86: - | K86: - | L86: - | M86: - | N86: 68.85 | O86: 74.85
C87: California | D87: Ctn 24 Bchd | E87: United States Number 1 | F87: 45 | G87: 63.5 | H87: 25 | I87: 58.5 | J87: 44.5 | K87: 68 | L87: 29.3 | M87: 81.75 | N87: 33 | O87: 85.25
D88: Ctn 10X5 lbs | E88: United States Number 1 | F88: 40 | G88: 65.9 | H88: 40 | I88: 69.5 | J88: - | K88: - | L88: 40 | M88: 71.7 | N88: 58.5 | O88: 68.25
D89: Ctn 24X2 lbs | E89: United States Number 1 | F89: 42 | G89: 65.9 | H89: 43.25 | I89: 65 | J89: 51 | K89: 75.5 | L89: 58.5 | M89: 75.5 | N89: 62.25 | O89: 72.85
D90: Ctn 30X1 lbs | E90: United States Number 1 | F90: - | G90: - | H90: - | I90: - | J90: - | K90: - | L90: - | M90: - | N90: 58.85 | O90: 58.85
C91: MEXICO | D91: Ctn 24 Bchd | E91: N/A | F91: - | G91: - | H91: - | I91: - | J91: - | K91: - | L91: - | M91: - | N91: 33 | O91: 68
C92: UNITED STATES | D92: Ctn 24 Bchd | E92: United States Number 1 | F92: - | G92: - | H92: - | I92: - | J92: - | K92: - | L92: - | M92: - | N92: 55.75 | O92: 78
D93: Ctn 24X2 lbs | E93: United States Number 1 | F93: 47 | G93: 49.85 | H93: - | I93: - | J93: - | K93: - | L93: - | M93: - | N93: - | O93: -
B94: Snaptop | C94: British Columbia | D94: Ctn 50 lbs | E94: Canada Number 1 | F94: 30.5 | G94: 37.75 | H94: 30.25 | I94: 31 | J94: 37 | K94: 40 | L94: 38.75 | M94: 60.75 | N94: 41.5 | O94: 60.75
C95: California | D95: Ctn 50 lbs | E95: United States Number 1 | F95: 29 | G95: 39 | H95: 30.5 | I95: 36.5 | J95: 34.5 | K95: 48.5 | L95: 44 | M95: 55.55 | N95: 44.5 | O95: 60.75
B96: Topped | C96: California | D96: Ctn 24X2 lbs | E96: United States Number 1 | F96: 35 | G96: 35 | H96: 35 | I96: 35 | J96: - | K96: - | L96: - | M96: - | N96: - | O96: -
B97: Unspecified | C97: British Columbia | D97: Bag 10X5 lbs | E97: Canada Number 1 | F97: - | G97: - | H97: - | I97: - | J97: - | K97: - | L97: 38.5 | M97: 61.5 | N97: 36.5 | O97: 66.25
D98: Ctn 24X2 lbs | E98: Canada Number 1 | F98: 26.75 | G98: 35.5 | H98: 30.25 | I98: 31 | J98: 35.75 | K98: 45 | L98: - | M98: - | N98: - | O98: -
D99: Ctn 10X5 lbs | E99: Canada Number 1 | F99: 26.75 | G99: 38.75 | H99: 30.25 | I99: 31 | J99: 35.75 | K99: 45 | L99: 43.5 | M99: 49.45 | N99: - | O99: -
D100: Bag 24X2 lbs | E100: Canada Number 1 | F100: - | G100: - | H100: - | I100: - | J100: - | K100: - | L100: 36.75 | M100: 61.5 | N100: 36.5 | O100: 66.25
...
